Workbook
Name IQ_CH: 110000
Name IQ_CQ: 5000
Name IQ_CY: 10000
Name IQ_DAILY: 500000
Name IQ_FH: 100000
Name IQ_FQ: 500
Name IQ_FY: 1000
Name IQ_LTM: 2000
Name IQ_MONTH: 15000
Name IQ_NTM: 6000
Name IQ_WEEK: 50000
Name IQ_YTD: 3000

Sheet Cover Sheet>
G23: 3 Statement Model DCF Valuation Relative Valuation

Sheet Input Sheet
B4: Please Provide the Below Inputs | L4: L | M4: Y
L5: S | M5: N
B6: Name of the Company | C6: Hindustan Unilever Ltd.
B8: WACC Inputs
B9: Country | C9: India
B10: Local Currency 10Y Government Bond Yield | C10: 0.06679
B11: =C9&"'s"&" Moody's Sovereign Rating" -> India's Moody's Sovereign Rating | C11: =VLOOKUP(C9,'Damodaran Data'!B4:C160,2,FALSE) -> Baa3
B12: =C9&"'s"&" Credit Default Spread as per Dr Damodaran" -> India's Credit Default Spread as per Dr Damodaran | C12: =VLOOKUP(C9,'Damodaran Data'!B4:D160,3,FALSE) -> 0.0187
B13: Implied US Equity Risk Premium | C13: 0.0438
B14: Asset Beta | C14: 0.68
B15: Asset Beta Variation (+/-) | C15: 0.01
B16: Debt to Equity Ratio | C16: ='Assumptions Working'!J1155 -> 0.033205822
B17: Debt to Capital (Gearing) | C17: ='Assumptions Working'!J1156 -> 0.032138199
B18: Marginal Tax Rate | C18: 0.3
B19: Company Credit Rating Available? | C19: Y
B20: Company is a Large Firm or Small Firm? | C20: L
B21: Provide Credit Rating | C21: Aaa/AAA
B22: Interest Coverage Ratio | C22: ='3Statement Model'!I28/-'3Statement Model'!I32 -> 34.167089
B23: ICR Based Corporate Default Spread | C23: =IF(C20="L",VLOOKUP('Input Sheet'!C22,'Damodaran Data'!H5:K20,4,TRUE),VLOOKUP(C22,'Damodaran Data'!H26:K41,4,TRUE)) -> 0.004
B24: Small Size Risk Premium
B25: Asset Specific Risk Premium

Sheet Damodaran Data
B3: Country | C3: Moody's rating | D3: Rating-based Default Spread | H3: For large non-financial service firms | N3: For financial service firms (default spreads are slighty different)
B4: India | C4: Baa3 | D4: 0.0187 | H4: If interest coverage ratio is | N4: If long term interest coverage ratio is
B5: Switzerland | C5: Aaa | D5: 0 | H5: > | I5: ≤ to | J5: Rating is | K5: Spread is | N5: greater than | O5: ≤ to | P5: Rating is | Q5: Spread is
B6: United Kingdom | C6: Aa3 | D6: 0.0051 | H6: -100000 | I6: 0.199999 | J6: D2/D | K6: 0.19 | N6: -100000 | O6: 0.049999 | P6: D2/D | Q6: 0.19
B7: United States | C7: Aa1 | D7: 0.0023 | H7: 0.2 | I7: 0.649999 | J7: C2/C | K7: 0.16 | N7: 0.05 | O7: 0.099999 | P7: C2/C | Q7: 0.16
B8: Abu Dhabi | C8: Aa2 | D8: 0.0042 | H8: 0.65 | I8: 0.799999 | J8: Ca2/CC | K8: 0.1261 | N8: 0.1 | O8: 0.199999 | P8: Ca2/CC | Q8: 0.1261
B9: Albania | C9: Ba3 | D9: 0.0306 | H9: 0.8 | I9: 1.249999 | J9: Caa/CCC | K9: 0.0885 | N9: 0.2 | O9: 0.299999 | P9: Caa/CCC | Q9: 0.0885
B10: Andorra (Principality of) | C10: Baa1 | D10: 0.0136 | H10: 1.25 | I10: 1.499999 | J10: B3/B- | K10: 0.0509 | N10: 0.3 | O10: 0.399999 | P10: B3/B- | Q10: 0.0509
B11: Angola | C11: B3 | D11: 0.0552 | H11: 1.5 | I11: 1.749999 | J11: B2/B | K11: 0.0321 | N11: 0.4 | O11: 0.499999 | P11: B2/B | Q11: 0.0321
B12: Argentina | C12: Caa1 | D12: 0.0637 | H12: 1.75 | I12: 1.999999 | J12: B1/B+ | K12: 0.0275 | N12: 0.5 | O12: 0.599999 | P12: B1/B+ | Q12: 0.0275
B13: Armenia | C13: Ba3 | D13: 0.0306 | H13: 2 | I13: 2.2499999 | J13: Ba2/BB | K13: 0.0184 | N13: 0.6 | O13: 0.749999 | P13: Ba2/BB | Q13: 0.0184
B14: Aruba | C14: Baa3 | D14: 0.0187 | H14: 2.25 | I14: 2.49999 | J14: Ba1/BB+ | K14: 0.0138 | N14: 0.75 | O14: 0.899999 | P14: Ba1/BB+ | Q14: 0.0138
B15: Australia | C15: Aaa | D15: 0 | H15: 2.5 | I15: 2.999999 | J15: Baa2/BBB | K15: 0.0111 | N15: 0.9 | O15: 1.199999 | P15: Baa2/BBB | Q15: 0.0111
B16: Austria | C16: Aa1 | D16: 0.0023 | H16: 3 | I16: 4.249999 | J16: A3/A- | K16: 0.0089 | N16: 1.2 | O16: 1.49999 | P16: A3/A- | Q16: 0.0089
B17: Azerbaijan | C17: Baa3 | D17: 0.0187 | H17: 4.25 | I17: 5.499999 | J17: A2/A | K17: 0.0078 | N17: 1.5 | O17: 1.99999 | P17: A2/A | Q17: 0.0078
... B20: Bangladesh | C20: B2 | D20: 0.0467 | H20: 8.5 | I20: 100000 | J20: Aaa/AAA | K20: 0.004 | N20: 3 | O20: 100000 | P20: Aaa/AAA | Q20: 0.004
B21: Barbados | C21: B2 | D21: 0.0467
B22: Belarus | C22: C | D22: 0.175
B23: Belgium | C23: Aa3 | D23: 0.0051
B24: Belize | C24: Caa1 | D24: 0.0637 | H24: For smaller and riskier firms
B25: Benin | C25: B1 | D25: 0.0383 | H25: If interest coverage ratio is
B26: Bermuda | C26: A2 | D26: 0.0072 | H26: greater than | I26: ≤ to | J26: Rating is | K26: Spread is
B27: Bolivia | C27: Ca | D27: 0.102 | H27: -100000 | I27: 0.499999 | J27: D2/D | K27: 0.19
B28: Bosnia and Herzegovina | C28: B3 | D28: 0.0552 | H28: 0.5 | I28: 0.799999 | J28: C2/C | K28: 0.16
B29: Botswana | C29: Baa1 | D29: 0.0136 | H29: 0.8 | I29: 1.249999 | J29: Ca2/CC | K29: 0.1261
B30: Brazil | C30: Ba1 | D30: 0.0213 | H30: 1.25 | I30: 1.499999 | J30: Caa/CCC | K30: 0.0885
B31: Bulgaria | C31: Baa1 | D31: 0.0136 | H31: 1.5 | I31: 1.999999 | J31: B3/B- | K31: 0.0509
B32: Burkina Faso | C32: Caa1 | D32: 0.0637 | H32: 2 | I32: 2.499999 | J32: B2/B | K32: 0.0321
B33: Cambodia | C33: B2 | D33: 0.0467 | H33: 2.5 | I33: 2.999999 | J33: B1/B+ | K33: 0.0275
B34: Cameroon | C34: Caa1 | D34: 0.0637 | H34: 3 | I34: 3.499999 | J34: Ba2/BB | K34: 0.0184
B35: Canada | C35: Aaa | D35: 0 | H35: 3.5 | I35: 3.9999999 | J35: Ba1/BB+ | K35: 0.0138
B36: Cape Verde | C36: B2 | D36: 0.0467 | H36: 4 | I36: 4.499999 | J36: Baa2/BBB | K36: 0.0111
B37: Cayman Islands | C37: Aa3 | D37: 0.0051 | H37: 4.5 | I37: 5.999999 | J37: A3/A- | K37: 0.0089
B38: Chile | C38: A2 | D38: 0.0072 | H38: 6 | I38: 7.499999 | J38: A2/A | K38: 0.0078
... B41: Congo (Democratic Republic of) | C41: B3 | D41: 0.0552 | H41: 12.5 | I41: 100000 | J41: Aaa/AAA | K41: 0.004
B42: Congo (Republic of) | C42: Caa2 | D42: 0.0765
B43: Cook Islands | C43: B1 | D43: 0.0383
B44: Costa Rica | C44: Ba2 | D44: 0.0256
B45: Côte d'Ivoire | C45: Ba2 | D45: 0.0256
B46: Croatia | C46: A3 | D46: 0.0102
B47: Cuba | C47: Ca | D47: 0.102
B48: Curacao | C48: Baa3 | D48: 0.0187
B49: Cyprus | C49: A3 | D49: 0.0102
B50: Czech Republic | C50: Aa3 | D50: 0.0051
B51: Denmark | C51: Aaa | D51: 0
B52: Dominican Republic | C52: Ba2 | D52: 0.0256
B53: Ecuador | C53: Caa3 | D53: 0.085
... B160: Zambia | C160: Caa2 | D160: 0.0765

Sheet Control Sheet
B2: ='Input Sheet'!C6 -> Hindustan Unilever Ltd.
B3: Control Sheet
G4: Current Case : | K4: 1
E8: Actual | K8: Explicit Forecast Period | P8: Maturity Period
B9: In Crs Unless Stated Otherwise | E9: 2020 | F9: =E9+1 -> 2021 | G9: =F9+1 -> 2022 | H9: =G9+1 -> 2023 | I9: =H9+1 -> 2024 | J9: =I9+1 -> 2025 | K9: =J9+1 -> 2026 | L9: =K9+1 -> 2027 | M9: =L9+1 -> 2028 | ... T9: =S9+1 -> 2035
A11: # | B11: Sales Assumptions
B13: Home Care
B15: Sales yoy % growth
B16: Management Case | E16: ='Assumptions Working'!G298 -> 0.059499767 | F16: ='Assumptions Working'!H298 -> 0.023240469 | G16: ='Assumptions Working'!I298 -> 0.18721788 | H16: ='Assumptions Working'!J298 -> 0.28141219 | I16: ='Assumptions Working'!K298 -> 0.027739839 | J16: 0.11 | K16: 0.11 | L16: 0.11 | M16: 0.11 | N16: 0.11 | O16: 0.11 | P16: 0.11 | Q16: 0.11 | R16: 0.1 | S16: 0.09 | T16: 0.08
B17: Street Case | E17: 0.059499767 | F17: 0.023240469 | G17: 0.18721788 | H17: 0.28141219 | I17: 0.027739839 | J17: 0.15 | K17: 0.15 | L17: 0.15 | M17: 0.15 | N17: 0.15 | O17: 0.15 | P17: 0.15 | Q17: 0.15 | R17: 0.15 | S17: 0.15 | T17: 0.15
B18: Worst Case | E18: 0.059499767 | F18: 0.023240469 | G18: 0.18721788 | H18: 0.28141219 | I18: 0.027739839 | J18: 0.06 | K18: 0.06 | L18: 0.06 | M18: 0.06 | N18: 0.06 | O18: 0.06 | P18: 0.06 | Q18: 0.06 | R18: 0.06 | S18: 0.06 | T18: 0.06
B19: ="Current Case- "&CHOOSE($K$4,$B$16,$B$17,$B$18) -> Current Case- Management Case | E19: =CHOOSE($K$4,E16,E17,E18) -> 0.059499767 | F19: =CHOOSE($K$4,F16,F17,F18) -> 0.023240469 | G19: =CHOOSE($K$4,G16,G17,G18) -> 0.18721788 | H19: =CHOOSE($K$4,H16,H17,H18) -> 0.28141219 | I19: =CHOOSE($K$4,I16,I17,I18) -> 0.027739839 | J19: =CHOOSE($K$4,J16,J17,J18) -> 0.11 | K19: =CHOOSE($K$4,K16,K17,K18) -> 0.11 | L19: =CHOOSE($K$4,L16,L17,L18) -> 0.11 | ... T19: =CHOOSE($K$4,T16,T17,T18) -> 0.08
B21: Personal Care
B23: Sales yoy % growth
B24: Management Case | E24: ='Assumptions Working'!G300 -> -0.01752809 | F24: ='Assumptions Working'!H300 -> 0.031450137 | G24: ='Assumptions Working'!I300 -> 0.084765495 | H24: ='Assumptions Working'!J300 -> 0.12546635 | I24: ='Assumptions Working'!K300 -> -0.40800109 | J24: ='Assumptions Working'!L300 -> 0.037278515 | K24: 0.06 | L24: 0.06 | M24: 0.06 | N24: 0.06 | O24: 0.06 | P24: 0.06 | Q24: 0.06 | R24: 0.06 | S24: 0.06 | T24: 0.06
B25: Street Case | E25: -0.01752809 | F25: 0.031450137 | G25: 0.084765495 | H25: 0.12546635 | I25: -0.40800109 | J25: 0.037278515 | K25: 0.1 | L25: 0.1 | M25: 0.1 | N25: 0.1 | O25: 0.1 | P25: 0.1 | Q25: 0.1 | R25: 0.1 | S25: 0.1 | T25: 0.1
B26: Worst Case | E26: -0.01752809 | F26: 0.031450137 | G26: 0.084765495 | H26: 0.12546635 | I26: -0.40800109 | J26: 0.037278515 | K26: 0.02 | L26: 0.02 | M26: 0.02 | N26: 0.02 | O26: 0.02 | P26: 0.02 | Q26: 0.02 | R26: 0.02 | S26: 0.02 | T26: 0.02
B27: ="Current Case- "&CHOOSE($K$4,$B$16,$B$17,$B$18) -> Current Case- Management Case | E27: =CHOOSE($K$4,E24,E25,E26) -> -0.01752809 | F27: =CHOOSE($K$4,F24,F25,F26) -> 0.031450137 | G27: =CHOOSE($K$4,G24,G25,G26) -> 0.084765495 | H27: =CHOOSE($K$4,H24,H25,H26) -> 0.12546635 | I27: =CHOOSE($K$4,I24,I25,I26) -> -0.40800109 | J27: =CHOOSE($K$4,J24,J25,J26) -> 0.037278515 | K27: =CHOOSE($K$4,K24,K25,K26) -> 0.06 | L27: =CHOOSE($K$4,L24,L25,L26) -> 0.06 | ... T27: =CHOOSE($K$4,T24,T25,T26) -> 0.06
B29: Baeuty & Wellbeing
B31: Sales yoy % growth
B32: Management Case | J32: ='Assumptions Working'!L302 -> -0.026033365 | K32: 0.13 | L32: 0.13 | M32: 0.13 | N32: 0.13 | O32: 0.13 | P32: 0.13 | Q32: 0.13 | R32: 0.13 | S32: 0.13 | T32: 0.13
B33: Street Case | J33: -0.026033365 | K33: 0.11 | L33: 0.11 | M33: 0.11 | N33: 0.11 | O33: 0.11 | P33: 0.11 | Q33: 0.11 | R33: 0.11 | S33: 0.11 | T33: 0.11
B34: Worst Case | J34: -0.026033365 | K34: 0.08 | L34: 0.08 | M34: 0.08 | N34: 0.08 | O34: 0.08 | P34: 0.08 | Q34: 0.08 | R34: 0.08 | S34: 0.08 | T34: 0.08
B35: ="Current Case- "&CHOOSE($K$4,$B$16,$B$17,$B$18) -> Current Case- Management Case | E35: =CHOOSE($K$4,E32,E33,E34) -> 0 | F35: =CHOOSE($K$4,F32,F33,F34) -> 0 | G35: =CHOOSE($K$4,G32,G33,G34) -> 0 | H35: =CHOOSE($K$4,H32,H33,H34) -> 0 | I35: =CHOOSE($K$4,I32,I33,I34) -> 0 | J35: =CHOOSE($K$4,J32,J33,J34) -> -0.026033365 | K35: =CHOOSE($K$4,K32,K33,K34) -> 0.13 | L35: =CHOOSE($K$4,L32,L33,L34) -> 0.13 | ... T35: =CHOOSE($K$4,T32,T33,T34) -> 0.13
B37: Foods
B39: Sales yoy % growth
B40: Management Case | E40: ='Assumptions Working'!F304 -> 0.10114268 | F40: ='Assumptions Working'!G304 -> 0.044734259 | G40: ='Assumptions Working'!H304 -> 0.77234899 | H40: ='Assumptions Working'!I304 -> 0.068236898 | I40: ='Assumptions Working'!J304 -> 0.054661468 | J40: ='Assumptions Working'!K304 -> 0.027897284 | K40: 0.06 | L40: 0.06 | M40: 0.06 | N40: 0.06 | O40: 0.06 | P40: 0.06 | Q40: 0.05 | R40: 0.04 | S40: 0.03 | T40: 0.02
B41: Street Case | E41: 0.10114268 | F41: 0.044734259 | G41: 0.77234899 | H41: 0.068236898 | I41: 0.054661468 | J41: 0.027897284 | K41: 0.08 | L41: 0.08 | M41: 0.08 | N41: 0.08 | O41: 0.08 | P41: 0.08 | Q41: 0.08 | R41: 0.08 | S41: 0.08 | T41: 0.08
B42: Worst Case | E42: 0.10114268 | F42: 0.044734259 | G42: 0.77234899 | H42: 0.068236898 | I42: 0.054661468 | J42: 0.027897284 | K42: 0.02 | L42: 0.02 | M42: 0.02 | N42: 0.02 | O42: 0.02 | P42: 0.02 | Q42: 0.02 | R42: 0.02 | S42: 0.02 | T42: 0.02
B43: ="Current Case- "&CHOOSE($K$4,$B$16,$B$17,$B$18) -> Current Case- Management Case | E43: =CHOOSE($K$4,E40,E41,E42) -> 0.10114268 | F43: =CHOOSE($K$4,F40,F41,F42) -> 0.044734259 | G43: =CHOOSE($K$4,G40,G41,G42) -> 0.77234899 | H43: =CHOOSE($K$4,H40,H41,H42) -> 0.068236898 | I43: =CHOOSE($K$4,I40,I41,I42) -> 0.054661468 | J43: =CHOOSE($K$4,J40,J41,J42) -> 0.027897284 | K43: =CHOOSE($K$4,K40,K41,K42) -> 0.06 | L43: =CHOOSE($K$4,L40,L41,L42) -> 0.06 | ... T43: =CHOOSE($K$4,T40,T41,T42) -> 0.02
B45: Others
B47: Sales yoy % growth
B48: Management Case | E48: ='Assumptions Working'!G306 -> -0.19933555 | F48: ='Assumptions Working'!H306 -> 0.51784232 | G48: ='Assumptions Working'!I306 -> 0.20503007 | H48: ='Assumptions Working'!J306 -> 0.11569873 | I48: ='Assumptions Working'!K306 -> -0.074827166 | J48: ='Assumptions Working'!L306 -> -0.041758242 | K48: 0.02 | L48: 0.02 | M48: 0.02 | N48: 0.02 | O48: 0.02 | P48: 0.02 | Q48: 0.02 | R48: 0.02 | S48: 0.02 | T48: 0.02
B49: Street Case | E49: -0.19933555 | F49: 0.51784232 | G49: 0.20503007 | H49: 0.11569873 | I49: -0.074827166 | J49: -0.041758242 | K49: 0.02 | L49: 0.02 | M49: 0.02 | N49: 0.02 | O49: 0.02 | P49: 0.02 | Q49: 0.02 | R49: 0.02 | S49: 0.02 | T49: 0.02
B50: Worst Case | E50: -0.19933555 | F50: 0.51784232 | G50: 0.20503007 | H50: 0.11569873 | I50: -0.074827166 | J50: -0.041758242 | K50: 0.01 | L50: 0.01 | M50: 0.01 | N50: 0.01 | O50: 0.01 | P50: 0.01 | Q50: 0.01 | R50: 0.01 | S50: 0.01 | T50: 0.01
B51: ="Current Case- "&CHOOSE($K$4,$B$16,$B$17,$B$18) -> Current Case- Management Case | E51: =CHOOSE($K$4,E48,E49,E50) -> -0.19933555 | F51: =CHOOSE($K$4,F48,F49,F50) -> 0.51784232 | G51: =CHOOSE($K$4,G48,G49,G50) -> 0.20503007 | H51: =CHOOSE($K$4,H48,H49,H50) -> 0.11569873 | I51: =CHOOSE($K$4,I48,I49,I50) -> -0.074827166 | J51: =CHOOSE($K$4,J48,J49,J50) -> -0.041758242 | K51: =CHOOSE($K$4,K48,K49,K50) -> 0.02 | L51: =CHOOSE($K$4,L48,L49,L50) -> 0.02 | ... T51: =CHOOSE($K$4,T48,T49,T50) -> 0.02
B53: Other Income
B55: yoy % growth
B56: Management Case | E56: ='Assumptions Working'!E349 -> 0.015886183 | F56: ='Assumptions Working'!F349 -> 0.0087182104 | G56: ='Assumptions Working'!G349 -> 0.0049193456 | H56: ='Assumptions Working'!H349 -> 0.0084516342 | I56: ='Assumptions Working'!I349 -> 0.013102624 | J56: ='Assumptions Working'!J349 -> 0.016111912 | K56: 0 | L56: 0 | M56: 0 | N56: 0 | O56: 0 | P56: 0 | Q56: 0 | R56: 0 | S56: 0 | T56: 0
B57: Street Case | E57: 0.015886183 | F57: 0.0087182104 | G57: 0.0049193456 | H57: 0.0084516342 | I57: 0.013102624 | J57: 0.016111912 | K57: 0 | L57: 0 | M57: 0 | N57: 0 | O57: 0 | P57: 0 | Q57: 0 | R57: 0 | S57: 0 | T57: 0
B58: Worst Case | E58: 0.015886183 | F58: 0.0087182104 | G58: 0.0049193456 | H58: 0.0084516342 | I58: 0.013102624 | J58: 0.016111912 | K58: 0 | L58: 0 | M58: 0 | N58: 0 | O58: 0 | P58: 0 | Q58: 0 | R58: 0 | S58: 0 | T58: 0
B59: ="Current Case- "&CHOOSE($K$4,$B$16,$B$17,$B$18) -> Current Case- Management Case | E59: =CHOOSE($K$4,E56,E57,E58) -> 0.015886183 | F59: =CHOOSE($K$4,F56,F57,F58) -> 0.0087182104 | G59: =CHOOSE($K$4,G56,G57,G58) -> 0.0049193456 | H59: =CHOOSE($K$4,H56,H57,H58) -> 0.0084516342 | I59: =CHOOSE($K$4,I56,I57,I58) -> 0.013102624 | J59: =CHOOSE($K$4,J56,J57,J58) -> 0.016111912 | K59: =CHOOSE($K$4,K56,K57,K58) -> 0 | L59: =CHOOSE($K$4,L56,L57,L58) -> 0 | ... T59: =CHOOSE($K$4,T56,T57,T58) -> 0
A63: # | B63: COGS Assumptions
B65: Gross Margin%
B66: Management Case | E66: 0.54103512 | F66: 0.52904653 | G66: 0.50930481 | H66: 0.47646088 | I66: 0.51919349 | J66: 0.51556534 | K66: 0.51 | L66: =K66+(($O$66-$K$66)/4) -> 0.51225 | M66: =L66+(($O$66-$K$66)/4) -> 0.5145 | N66: =M66+(($O$66-$K$66)/4) -> 0.51675 | O66: 0.519 | P66: 0.519 | Q66: 0.519 | R66: 0.519 | S66: 0.519 | T66: 0.519
B67: Street Case | E67: 0.54103512 | F67: 0.52904653 | G67: 0.50930481 | H67: 0.47646088 | I67: 0.51919349 | J67: 0.51556534 | K67: 0.511 | L67: 0.514 | M67: 0.515 | N67: 0.516 | O67: 0.516 | P67: 0.516 | Q67: 0.516 | R67: 0.516 | S67: 0.516 | T67: 0.516
B68: Worst Case | E68: 0.54103512 | F68: 0.52904653 | G68: 0.50930481 | H68: 0.47646088 | I68: 0.51919349 | J68: 0.51556534 | K68: 0.48 | L68: 0.48 | M68: 0.48 | N68: 0.48 | O68: 0.48 | P68: 0.48 | Q68: 0.48 | R68: 0.48 | S68: 0.48 | T68: 0.48
B69: ="Current Case- "&CHOOSE($K$4,$B$16,$B$17,$B$18) -> Current Case- Management Case | E69: =CHOOSE($K$4,E66,E67,E68) -> 0.54103512 | F69: =CHOOSE($K$4,F66,F67,F68) -> 0.52904653 | G69: =CHOOSE($K$4,G66,G67,G68) -> 0.50930481 | H69: =CHOOSE($K$4,H66,H67,H68) -> 0.47646088 | I69: =CHOOSE($K$4,I66,I67,I68) -> 0.51919349 | J69: =CHOOSE($K$4,J66,J67,J68) -> 0.51556534 | K69: =CHOOSE($K$4,K66,K67,K68) -> 0.51 | L69: =CHOOSE($K$4,L66,L67,L68) -> 0.51225 | ... T69: =CHOOSE($K$4,T66,T67,T68) -> 0.519
B71: COGS % Sales | E71: =100%-E69 -> 0.45896488 | F71: =100%-F69 -> 0.47095347 | G71: =100%-G69 -> 0.49069519 | H71: =100%-H69 -> 0.52353912 | I71: =100%-I69 -> 0.48080651 | J71: =100%-J69 -> 0.48443466 | K71: =100%-K69 -> 0.49 | L71: =100%-L69 -> 0.48775 | ... T71: =100%-T69 -> 0.481
A74: # | B74: Selling, General and Administrative (SG&A) Assumptions
B76: Employee Benefit Expenses % Revenue
B77: Management Case | E77: ='Assumptions Working'!F586 -> 0.045748184 | F77: ='Assumptions Working'!G586 -> 0.050140342 | G77: ='Assumptions Working'!H586 -> 0.048526103 | H77: ='Assumptions Working'!I586 -> 0.047111258 | I77: ='Assumptions Working'!J586 -> 0.048613804 | J77: ='Assumptions Working'!K586 -> 0.047638662 | K77: 0.048 | L77: 0.048 | M77: 0.048 | N77: 0.048 | O77: 0.048 | P77: 0.048 | Q77: 0.048 | R77: 0.048 | S77: 0.048 | T77: 0.048
B78: Street Case | E78: 0.045748184 | F78: 0.050140342 | G78: 0.048526103 | H78: 0.047111258 | I78: 0.048613804 | J78: 0.047638662 | K78: 0.048 | L78: 0.048 | M78: 0.048 | N78: 0.048 | O78: 0.048 | P78: 0.048 | Q78: 0.048 | R78: 0.048 | S78: 0.048 | T78: 0.048
B79: Worst Case | E79: 0.045748184 | F79: 0.050140342 | G79: 0.048526103 | H79: 0.047111258 | I79: 0.048613804 | J79: 0.047638662 | K79: 0.048 | L79: 0.048 | M79: 0.048 | N79: 0.048 | O79: 0.048 | P79: 0.048 | Q79: 0.048 | R79: 0.048 | S79: 0.048 | T79: 0.048
B80: ="Current Case- "&CHOOSE($K$4,$B$16,$B$17,$B$18) -> Current Case- Management Case | E80: =CHOOSE($K$4,E77,E78,E79) -> 0.045748184 | F80: =CHOOSE($K$4,F77,F78,F79) -> 0.050140342 | G80: =CHOOSE($K$4,G77,G78,G79) -> 0.048526103 | H80: =CHOOSE($K$4,H77,H78,H79) -> 0.047111258 | I80: =CHOOSE($K$4,I77,I78,I79) -> 0.048613804 | J80: =CHOOSE($K$4,J77,J78,J79) -> 0.047638662 | K80: =CHOOSE($K$4,K77,K78,K79) -> 0.048 | L80: =CHOOSE($K$4,L77,L78,L79) -> 0.048 | ... T80: =CHOOSE($K$4,T77,T78,T79) -> 0.048
B82: Other Expenses % Revenue
B83: Management Case | E83: 0.24741724 | F83: 0.23169176 | G83: 0.21563132 | H83: 0.19579069 | I83: 0.23368231 | J83: 0.23153942 | K83: 0.232 | L83: 0.232 | M83: 0.232 | N83: 0.232 | O83: 0.232 | P83: 0.232 | Q83: 0.232 | R83: 0.232 | S83: 0.232 | T83: 0.232
B84: Street Case | E84: 0.24741724 | F84: 0.23169176 | G84: 0.21563132 | H84: 0.19579069 | I84: 0.23368231 | J84: 0.23153942 | K84: 0.232 | L84: 0.232 | M84: 0.232 | N84: 0.232 | O84: 0.232 | P84: 0.232 | Q84: 0.232 | R84: 0.232 | S84: 0.232 | T84: 0.232
B85: Worst Case | E85: 0.24741724 | F85: 0.23169176 | G85: 0.21563132 | H85: 0.19579069 | I85: 0.23368231 | J85: 0.23153942 | K85: 0.232 | L85: 0.232 | M85: 0.232 | N85: 0.232 | O85: 0.232 | P85: 0.232 | Q85: 0.232 | R85: 0.232 | S85: 0.232 | T85: 0.232
B86: ="Current Case- "&CHOOSE($K$4,$B$16,$B$17,$B$18) -> Current Case- Management Case | E86: =CHOOSE($K$4,E83,E84,E85) -> 0.24741724 | F86: =CHOOSE($K$4,F83,F84,F85) -> 0.23169176 | G86: =CHOOSE($K$4,G83,G84,G85) -> 0.21563132 | H86: =CHOOSE($K$4,H83,H84,H85) -> 0.19579069 | I86: =CHOOSE($K$4,I83,I84,I85) -> 0.23368231 | J86: =CHOOSE($K$4,J83,J84,J85) -> 0.23153942 | K86: =CHOOSE($K$4,K83,K84,K85) -> 0.232 | L86: =CHOOSE($K$4,L83,L84,L85) -> 0.232 | ... T86: =CHOOSE($K$4,T83,T84,T85) -> 0.232
A88: # | B88: Tax Rate Assumptions
B90: Marginal Tax Rate
B91: Management Case | K91: 0.3 | L91: 0.3 | M91: 0.3 | N91: 0.3 | O91: 0.3 | P91: 0.3 | Q91: 0.3 | R91: 0.3 | S91: 0.3 | T91: 0.3
B92: Street Case | K92: 0.3 | L92: 0.3 | M92: 0.3 | N92: 0.3 | O92: 0.3 | P92: 0.3 | Q92: 0.3 | R92: 0.3 | S92: 0.3 | T92: 0.3
B93: Worst Case | K93: 0.3 | L93: 0.3 | M93: 0.3 | N93: 0.3 | O93: 0.3 | P93: 0.3 | Q93: 0.3 | R93: 0.3 | S93: 0.3 | T93: 0.3
B94: ="Current Case- "&CHOOSE($K$4,$B$16,$B$17,$B$18) -> Current Case- Management Case | K94: =CHOOSE($K$4,K91,K92,K93) -> 0.3 | L94: =CHOOSE($K$4,L91,L92,L93) -> 0.3 | M94: =CHOOSE($K$4,M91,M92,M93) -> 0.3 | N94: =CHOOSE($K$4,N91,N92,N93) -> 0.3 | O94: =CHOOSE($K$4,O91,O92,O93) -> 0.3 | P94: =CHOOSE($K$4,P91,P92,P93) -> 0.3 | Q94: =CHOOSE($K$4,Q91,Q92,Q93) -> 0.3 | R94: =CHOOSE($K$4,R91,R92,R93) -> 0.3 | ... T94: =CHOOSE($K$4,T91,T92,T93) -> 0.3
A96: # | B96: Non-Current Asset Assumptions
B98: Property Plant & Equipments Growth%
B99: Management Case | K99: ='Assumptions Working'!L1001 -> 0.19567264 | L99: ='Assumptions Working'!M1001 -> 0.17802608 | M99: ='Assumptions Working'!N1001 -> 0.16452852 | N99: ='Assumptions Working'!O1001 -> 0.15393872 | O99: ='Assumptions Working'!P1001 -> 0.14546672 | P99: ='Assumptions Working'!V1001 -> 0 | Q99: ='Assumptions Working'!W1001 -> 0 | R99: ='Assumptions Working'!X1001 -> 0 | S99: ='Assumptions Working'!Y1001 -> 0 | T99: ='Assumptions Working'!Z1001 -> 0
B100: Street Case | K100: 0.19567264 | L100: 0.17802608 | M100: 0.16452852 | N100: 0.15393872 | O100: 0.14546672 | P100: 0.14546672 | Q100: 0.14546672 | R100: 0.14546672 | S100: 0.14546672 | T100: 0.14546672
B101: Worst Case | K101: 0.19567264 | L101: 0.17802608 | M101: 0.16452852 | N101: 0.15393872 | O101: 0.14546672 | P101: 0.14546672 | Q101: 0.14546672 | R101: 0.14546672 | S101: 0.14546672 | T101: 0.14546672
B102: ="Current Case- "&CHOOSE($K$4,$B$16,$B$17,$B$18) -> Current Case- Management Case | K102: =CHOOSE($K$4,K99,K100,K101) -> 0.19567264 | L102: =CHOOSE($K$4,L99,L100,L101) -> 0.17802608 | M102: =CHOOSE($K$4,M99,M100,M101) -> 0.16452852 | N102: =CHOOSE($K$4,N99,N100,N101) -> 0.15393872 | O102: =CHOOSE($K$4,O99,O100,O101) -> 0.14546672 | P102: =CHOOSE($K$4,P99,P100,P101) -> 0 | Q102: =CHOOSE($K$4,Q99,Q100,Q101) -> 0 | R102: =CHOOSE($K$4,R99,R100,R101) -> 0 | ... T102: =CHOOSE($K$4,T99,T100,T101) -> 0
B104: Capital Work in Progress Growth%
B105: Management Case | K105: 0.02 | L105: 0.02 | M105: 0.02 | N105: 0.02 | O105: 0.02 | P105: 0.02 | Q105: 0.02 | R105: 0.02 | S105: 0.02 | T105: 0.02
B106: Street Case | K106: 0.02 | L106: 0.02 | M106: 0.02 | N106: 0.02 | O106: 0.02 | P106: 0.02 | Q106: 0.02 | R106: 0.02 | S106: 0.02 | T106: 0.02
B107: Worst Case | K107: 0.02 | L107: 0.02 | M107: 0.02 | N107: 0.02 | O107: 0.02 | P107: 0.02 | Q107: 0.02 | R107: 0.02 | S107: 0.02 | T107: 0.02
B108: ="Current Case- "&CHOOSE($K$4,$B$16,$B$17,$B$18) -> Current Case- Management Case | K108: =CHOOSE($K$4,K105,K106,K107) -> 0.02 | L108: =CHOOSE($K$4,L105,L106,L107) -> 0.02 | M108: =CHOOSE($K$4,M105,M106,M107) -> 0.02 | N108: =CHOOSE($K$4,N105,N106,N107) -> 0.02 | O108: =CHOOSE($K$4,O105,O106,O107) -> 0.02 | P108: =CHOOSE($K$4,P105,P106,P107) -> 0.02 | Q108: =CHOOSE($K$4,Q105,Q106,Q107) -> 0.02 | R108: =CHOOSE($K$4,R105,R106,R107) -> 0.02 | ... T108: =CHOOSE($K$4,T105,T106,T107) -> 0.02
C109: `
B110: Goodwill Growth%
B111: Management Case | K111: 0 | L111: 0 | M111: 0 | N111: 0 | O111: 0 | P111: 0 | Q111: 0 | R111: 0 | S111: 0 | T111: 0
B112: Street Case | K112: 0 | L112: 0 | M112: 0 | N112: 0 | O112: 0 | P112: 0 | Q112: 0 | R112: 0 | S112: 0 | T112: 0
B113: Worst Case | K113: 0 | L113: 0 | M113: 0 | N113: 0 | O113: 0 | P113: 0 | Q113: 0 | R113: 0 | S113: 0 | T113: 0
B114: ="Current Case- "&CHOOSE($K$4,$B$16,$B$17,$B$18) -> Current Case- Management Case | K114: =CHOOSE($K$4,K111,K112,K113) -> 0 | L114: =CHOOSE($K$4,L111,L112,L113) -> 0 | M114: =CHOOSE($K$4,M111,M112,M113) -> 0 | N114: =CHOOSE($K$4,N111,N112,N113) -> 0 | O114: =CHOOSE($K$4,O111,O112,O113) -> 0 | P114: =CHOOSE($K$4,P111,P112,P113) -> 0 | Q114: =CHOOSE($K$4,Q111,Q112,Q113) -> 0 | R114: =CHOOSE($K$4,R111,R112,R113) -> 0 | ... T114: =CHOOSE($K$4,T111,T112,T113) -> 0
B116: Brand Rights Growth %
B117: Management Case | K117: 0 | L117: 0 | M117: 0 | N117: 0 | O117: 0 | P117: 0 | Q117: 0 | R117: 0 | S117: 0 | T117: 0
B118: Street Case | K118: 0 | L118: 0 | M118: 0 | N118: 0 | O118: 0 | P118: 0 | Q118: 0 | R118: 0 | S118: 0 | T118: 0
B119: Worst Case | K119: 0 | L119: 0 | M119: 0 | N119: 0 | O119: 0 | P119: 0 | Q119: 0 | R119: 0 | S119: 0 | T119: 0
B120: ="Current Case- "&CHOOSE($K$4,$B$16,$B$17,$B$18) -> Current Case- Management Case | K120: =CHOOSE($K$4,K117,K118,K119) -> 0 | L120: =CHOOSE($K$4,L117,L118,L119) -> 0 | M120: =CHOOSE($K$4,M117,M118,M119) -> 0 | N120: =CHOOSE($K$4,N117,N118,N119) -> 0 | O120: =CHOOSE($K$4,O117,O118,O119) -> 0 | P120: =CHOOSE($K$4,P117,P118,P119) -> 0 | Q120: =CHOOSE($K$4,Q117,Q118,Q119) -> 0 | R120: =CHOOSE($K$4,R117,R118,R119) -> 0 | ... T120: =CHOOSE($K$4,T117,T118,T119) -> 0
B122: Other Intangibles(Excluding Goodwill & Brand Rights) Growth %
B123: Management Case | K123: 0.19567264 | L123: 0.17802608 | M123: 0.16452852 | N123: 0.15393872 | O123: 0.14546672 | P123: 0.14546672 | Q123: 0.14546672 | R123: 0.14546672 | S123: 0.14546672 | T123: 0.14546672
B124: Street Case | K124: 0.19567264 | L124: 0.17802608 | M124: 0.16452852 | N124: 0.15393872 | O124: 0.14546672 | P124: 0.14546672 | Q124: 0.14546672 | R124: 0.14546672 | S124: 0.14546672 | T124: 0.14546672
B125: Worst Case | K125: 0.19567264 | L125: 0.17802608 | M125: 0.16452852 | N125: 0.15393872 | O125: 0.14546672 | P125: 0.14546672 | Q125: 0.14546672 | R125: 0.14546672 | S125: 0.14546672 | T125: 0.14546672
B126: ="Current Case- "&CHOOSE($K$4,$B$16,$B$17,$B$18) -> Current Case- Management Case | K126: =CHOOSE($K$4,K123,K124,K125) -> 0.19567264 | L126: =CHOOSE($K$4,L123,L124,L125) -> 0.17802608 | M126: =CHOOSE($K$4,M123,M124,M125) -> 0.16452852 | N126: =CHOOSE($K$4,N123,N124,N125) -> 0.15393872 | O126: =CHOOSE($K$4,O123,O124,O125) -> 0.14546672 | P126: =CHOOSE($K$4,P123,P124,P125) -> 0.14546672 | Q126: =CHOOSE($K$4,Q123,Q124,Q125) -> 0.14546672 | R126: =CHOOSE($K$4,R123,R124,R125) -> 0.14546672 | ... T126: =CHOOSE($K$4,T123,T124,T125) -> 0.14546672
B128: Non-Current Financial Assets Growth %
B129: Management Case | K129: 0.015 | L129: 0.015 | M129: 0.015 | N129: 0.015 | O129: 0.015 | P129: 0.015 | Q129: 0.015 | R129: 0.015 | S129: 0.015 | T129: 0.015
B130: Street Case | K130: 0.015 | L130: 0.015 | M130: 0.015 | N130: 0.015 | O130: 0.015 | P130: 0.015 | Q130: 0.015 | R130: 0.015 | S130: 0.015 | T130: 0.015
B131: Worst Case | K131: 0.015 | L131: 0.015 | M131: 0.015 | N131: 0.015 | O131: 0.015 | P131: 0.015 | Q131: 0.015 | R131: 0.015 | S131: 0.015 | T131: 0.015
B132: ="Current Case- "&CHOOSE($K$4,$B$16,$B$17,$B$18) -> Current Case- Management Case | K132: =CHOOSE($K$4,K129,K130,K131) -> 0.015 | L132: =CHOOSE($K$4,L129,L130,L131) -> 0.015 | M132: =CHOOSE($K$4,M129,M130,M131) -> 0.015 | N132: =CHOOSE($K$4,N129,N130,N131) -> 0.015 | O132: =CHOOSE($K$4,O129,O130,O131) -> 0.015 | P132: =CHOOSE($K$4,P129,P130,P131) -> 0.015 | Q132: =CHOOSE($K$4,Q129,Q130,Q131) -> 0.015 | R132: =CHOOSE($K$4,R129,R130,R131) -> 0.015 | ... T132: =CHOOSE($K$4,T129,T130,T131) -> 0.015
B134: Deferred Tax Assets Growth %
B135: Management Case | K135: 0 | L135: 0 | M135: 0 | N135: 0 | O135: 0 | P135: 0 | Q135: 0 | R135: 0 | S135: 0 | T135: 0
...

Sheet Schedules
B2: ='Input Sheet'!C6 -> Hindustan Unilever Ltd.
B3: Schedules
I4: Current Case:
E8: Actual | K8: Explicit Forecast Period | P8: Maturity Period
B9: In Crs Unless Stated Otherwise | E9: 2020 | F9: =E9+1 -> 2021 | G9: =F9+1 -> 2022 | H9: =G9+1 -> 2023 | I9: =H9+1 -> 2024 | J9: =I9+1 -> 2025 | K9: =J9+1 -> 2026 | L9: =K9+1 -> 2027 | M9: =L9+1 -> 2028 | ... T9: =S9+1 -> 2035
A11: # | B11: Sales Schedule
B13: Sales Breakup- Segment Wise
B15: Home Care | E15: 13640 | F15: 13957 | G15: 16570 | H15: 21233 | I15: 21822 | J15: 22958 | K15: =J15*(1+K22) -> 25483.38 | L15: =K15*(1+L22) -> 28286.552 | M15: =L15*(1+M22) -> 31398.072 | N15: =M15*(1+N22) -> 34851.86 | O15: =N15*(1+O22) -> 38685.565 | P15: =O15*(1+P22) -> 42940.977 | Q15: =P15*(1+Q22) -> 47664.485 | R15: =Q15*(1+R22) -> 52430.933 | ... T15: =S15*(1+T22) -> 61721.695
B16: Personal Care | E16: 17488 | F16: 18038 | G16: 19567 | H16: 22022 | I16: 13037 | J16: 13523 | K16: =J16*(1+K23) -> 14334.38 | L16: =K16*(1+L23) -> 15194.443 | M16: =L16*(1+M23) -> 16106.109 | N16: =M16*(1+N23) -> 17072.476 | O16: =N16*(1+O23) -> 18096.824 | P16: =O16*(1+P23) -> 19182.634 | Q16: =P16*(1+Q23) -> 20333.592 | R16: =Q16*(1+R23) -> 21553.608 | ... T16: =S16*(1+T23) -> 24217.633
B17: Beauty & Wellbeing | E17: 0 | F17: 0 | G17: 0 | H17: 0 | I17: 9411 | J17: 9166 | K17: =J17*(1+K24) -> 10357.58 | L17: =K17*(1+L24) -> 11704.065 | M17: =L17*(1+M24) -> 13225.594 | N17: =M17*(1+N24) -> 14944.921 | O17: =N17*(1+O24) -> 16887.761 | P17: =O17*(1+P24) -> 19083.17 | Q17: =P17*(1+Q24) -> 21563.982 | R17: =Q17*(1+R24) -> 24367.299 | ... T17: =S17*(1+T24) -> 31114.605
B18: Foods | E18: 7450 | F18: 13204 | G18: 14105 | H18: 14876 | I18: 15291 | J18: 15294 | K18: =J18*(1+K25) -> 16211.64 | L18: =K18*(1+L25) -> 17184.338 | M18: =L18*(1+M25) -> 18215.399 | N18: =M18*(1+N25) -> 19308.323 | O18: =N18*(1+O25) -> 20466.822 | P18: =O18*(1+P25) -> 21694.831 | Q18: =P18*(1+Q25) -> 22779.573 | R18: =Q18*(1+R25) -> 23690.756 | ... T18: =S18*(1+T25) -> 24889.508
B19: Others | E19: 1205 | F19: 1829 | G19: 2204 | H19: 2459 | I19: 2275 | J19: 2180 | K19: =J19*(1+K26) -> 2223.6 | L19: =K19*(1+L26) -> 2268.072 | M19: =L19*(1+M26) -> 2313.4334 | N19: =M19*(1+N26) -> 2359.7021 | O19: =N19*(1+O26) -> 2406.8962 | P19: =O19*(1+P26) -> 2455.0341 | Q19: =P19*(1+Q26) -> 2504.1348 | R19: =Q19*(1+R26) -> 2554.2175 | ... T19: =S19*(1+T26) -> 2657.4078
B20: Total Sales | E20: =SUM(E15:E19) -> 39783 | F20: =SUM(F15:F19) -> 47028 | G20: =SUM(G15:G19) -> 52446 | H20: =SUM(H15:H19) -> 60590 | I20: =SUM(I15:I19) -> 61836 | J20: =SUM(J15:J19) -> 63121 | K20: =SUM(K15:K19) -> 68610.58 | L20: =SUM(L15:L19) -> 74637.47 | ... T20: =SUM(T15:T19) -> 144600.85
B22: Home Care Sales % yoy | E22: ='Control Sheet'!E19 -> 0.059499767 | F22: ='Control Sheet'!F19 -> 0.023240469 | G22: ='Control Sheet'!G19 -> 0.18721788 | H22: ='Control Sheet'!H19 -> 0.28141219 | I22: ='Control Sheet'!I19 -> 0.027739839 | J22: ='Control Sheet'!J19 -> 0.11 | K22: ='Control Sheet'!K19 -> 0.11 | L22: ='Control Sheet'!L19 -> 0.11 | ... T22: ='Control Sheet'!T19 -> 0.08
B23: Personal Care Sales % yoy | E23: ='Control Sheet'!E27 -> -0.01752809 | F23: ='Control Sheet'!F27 -> 0.031450137 | G23: ='Control Sheet'!G27 -> 0.084765495 | H23: ='Control Sheet'!H27 -> 0.12546635 | I23: ='Control Sheet'!I27 -> -0.40800109 | J23: ='Control Sheet'!J27 -> 0.037278515 | K23: ='Control Sheet'!K27 -> 0.06 | L23: ='Control Sheet'!L27 -> 0.06 | ... T23: ='Control Sheet'!T27 -> 0.06
B24: Beauty & Wellbeing Sales % yoy | E24: ='Control Sheet'!E35 -> 0 | F24: ='Control Sheet'!F35 -> 0 | G24: ='Control Sheet'!G35 -> 0 | H24: ='Control Sheet'!H35 -> 0 | I24: ='Control Sheet'!I35 -> 0 | J24: ='Control Sheet'!J35 -> -0.026033365 | K24: ='Control Sheet'!K35 -> 0.13 | L24: ='Control Sheet'!L35 -> 0.13 | ... T24: ='Control Sheet'!T35 -> 0.13
B25: Foods Sales % yoy | E25: ='Control Sheet'!E43 -> 0.10114268 | F25: ='Control Sheet'!F43 -> 0.044734259 | G25: ='Control Sheet'!G43 -> 0.77234899 | H25: ='Control Sheet'!H43 -> 0.068236898 | I25: ='Control Sheet'!I43 -> 0.054661468 | J25: ='Control Sheet'!J43 -> 0.027897284 | K25: ='Control Sheet'!K43 -> 0.06 | L25: ='Control Sheet'!L43 -> 0.06 | ... T25: ='Control Sheet'!T43 -> 0.02
B26: Others Sales % yoy | E26: ='Control Sheet'!E51 -> -0.19933555 | F26: ='Control Sheet'!F51 -> 0.51784232 | G26: ='Control Sheet'!G51 -> 0.20503007 | H26: ='Control Sheet'!H51 -> 0.11569873 | I26: ='Control Sheet'!I51 -> -0.074827166 | J26: ='Control Sheet'!J51 -> -0.041758242 | K26: ='Control Sheet'!K51 -> 0.02 | L26: ='Control Sheet'!L51 -> 0.02 | ... T26: ='Control Sheet'!T51 -> 0.02
B27: Total Sales growth % yoy | K27: =K20/J20-1 -> 0.086969154 | L27: =L20/K20-1 -> 0.087841998 | M27: =M20/L20-1 -> 0.088710637 | N27: =N20/M20-1 -> 0.089574194 | O27: =O20/N20-1 -> 0.090431806 | P27: =P20/O20-1 -> 0.091282625 | Q27: =Q20/P20-1 -> 0.090066647 | R27: =R20/Q20-1 -> 0.084905587 | ... T27: =T20/S20-1 -> 0.074792631
B29: Other Income
B32: Other Income | E32: =' Income Statement'!D45 -> 632 | F32: =' Income Statement'!E45 -> 410 | G32: =' Income Statement'!F45 -> 258 | H32: =' Income Statement'!G45 -> 512 | I32: =' Income Statement'!H45 -> 811 | J32: =' Income Statement'!I45 -> 1017 | K32: =J32+(J32*K34) -> 1017 | L32: =K32+(K32*L34) -> 1017 | M32: =L32+(L32*M34) -> 1017 | N32: =M32+(M32*N34) -> 1017 | O32: =N32+(N32*O34) -> 1017 | P32: =O32+(O32*P34) -> 1017 | Q32: =P32+(P32*Q34) -> 1017 | R32: =Q32+(Q32*R34) -> 1017 | ... T32: =S32+(S32*T34) -> 1017
B34: Other Income % Revenue | E34: ='Assumptions Working'!E349 -> 0.015886183 | F34: ='Assumptions Working'!F349 -> 0.0087182104 | G34: ='Assumptions Working'!G349 -> 0.0049193456 | H34: ='Assumptions Working'!H349 -> 0.0084516342 | I34: ='Assumptions Working'!I349 -> 0.013102624 | J34: ='Assumptions Working'!J349 -> 0.016111912 | K34: ='Control Sheet'!K59 -> 0 | L34: ='Control Sheet'!L59 -> 0 | M34: ='Control Sheet'!M59 -> 0 | N34: ='Control Sheet'!N59 -> 0 | O34: ='Control Sheet'!O59 -> 0 | P34: ='Control Sheet'!P59 -> 0 | Q34: ='Control Sheet'!Q59 -> 0 | R34: ='Control Sheet'!R59 -> 0 | ... T34: ='Control Sheet'!T59 -> 0
A38: # | B38: COGS Schedule
B40: COGS | E40: =-' Income Statement'!D20 -> 18259 | F40: =-' Income Statement'!E20 -> 22148 | G40: =-' Income Statement'!F20 -> 25735 | H40: =-' Income Statement'!G20 -> 31716 | I40: =-' Income Statement'!H20 -> 29760 | J40: =-' Income Statement'!I20 -> 30578 | K40: =K20*K42 -> 33619.184 | L40: =L20*L42 -> 36404.426 | M40: =M20*M42 -> 39451.054 | N40: =N20*N42 -> 42785.642 | O40: =O20*O42 -> 46437.601 | P40: =P20*P42 -> 50676.547 | Q40: =Q20*Q42 -> 55240.814 | R40: =R20*R42 -> 59931.067 | ... T40: =T20*T42 -> 69553.008
B42: COGS % Sales | E42: ='Control Sheet'!E71 -> 0.45896488 | F42: ='Control Sheet'!F71 -> 0.47095347 | G42: ='Control Sheet'!G71 -> 0.49069519 | H42: ='Control Sheet'!H71 -> 0.52353912 | I42: ='Control Sheet'!I71 -> 0.48080651 | J42: ='Control Sheet'!J71 -> 0.48443466 | K42: ='Control Sheet'!K71 -> 0.49 | L42: ='Control Sheet'!L71 -> 0.48775 | ... T42: ='Control Sheet'!T71 -> 0.481
B43: Gross Margin % Sales | E43: =100%-E42 -> 0.54103512 | F43: =100%-F42 -> 0.52904653 | G43: =100%-G42 -> 0.50930481 | H43: =100%-H42 -> 0.47646088 | I43: =100%-I42 -> 0.51919349 | J43: =100%-J42 -> 0.51556534 | K43: =100%-K42 -> 0.51 | L43: =100%-L42 -> 0.51225 | ... T43: =100%-T42 -> 0.519
A45: # | B45: SG&A Schedule
B47: Employee Benefit Expenses
B50: Employee Benefit Expenses | E50: =-' Income Statement'!D33 -> 1820 | F50: =-' Income Statement'!E33 -> 2358 | G50: =-' Income Statement'!F33 -> 2545 | H50: =-' Income Statement'!G33 -> 2854 | I50: =-' Income Statement'!H33 -> 3009 | J50: =-' Income Statement'!I33 -> 3077 | K50: =K20*K53 -> 3293.3078 | L50: =L20*L53 -> 3582.5986 | M50: =M20*M53 -> 3900.4132 | N50: =N20*N53 -> 4249.7895 | O50: =O20*O53 -> 4634.1057 | P50: =P20*P53 -> 5057.119 | Q50: =Q20*Q53 -> 5512.5968 | R50: =R20*R53 -> 5980.647 | ... T50: =T20*T53 -> 6940.8407
B51: Total Employee Benefit Expenses | E51: =E50 -> 1820 | F51: =F50 -> 2358 | G51: =G50 -> 2545 | H51: =H50 -> 2854 | I51: =I50 -> 3009 | J51: =J50 -> 3077 | K51: =K50 -> 3293.3078 | L51: =L50 -> 3582.5986 | ... T51: =T50 -> 6940.8407
B53: Employee Benefit Expenses % Sales | E53: ='Control Sheet'!E80 -> 0.045748184 | F53: ='Control Sheet'!F80 -> 0.050140342 | G53: ='Control Sheet'!G80 -> 0.048526103 | H53: ='Control Sheet'!H80 -> 0.047111258 | I53: ='Control Sheet'!I80 -> 0.048613804 | J53: ='Control Sheet'!J80 -> 0.047638662 | K53: ='Control Sheet'!K80 -> 0.048 | L53: ='Control Sheet'!L80 -> 0.048 | ... T53: ='Control Sheet'!T80 -> 0.048
B54: Other Expenses % yoy growth | F54: =F51/E51-1 -> 0.2956044 | G54: =G51/F51-1 -> 0.079304495 | H54: =H51/G51-1 -> 0.12141454 | I54: =I51/H51-1 -> 0.054309741 | J54: =J51/I51-1 -> 0.02259887 | K54: =K51/J51-1 -> 0.070298291 | L54: =L51/K51-1 -> 0.087841998 | M54: =M51/L51-1 -> 0.088710637 | ... T54: =T51/S51-1 -> 0.074792631
B56: Other Expenses
B59: Other Expenses | E59: =-' Income Statement'!D34 -> 9843 | F59: =-' Income Statement'!E34 -> 10896 | G59: =-' Income Statement'!F34 -> 11309 | H59: =-' Income Statement'!G34 -> 11861 | I59: =-' Income Statement'!H34 -> 14464 | J59: =-' Income Statement'!I34 -> 14615 | K59: =K20*K62 -> 15917.655 | L59: =L20*L62 -> 17315.893 | M59: =M20*M62 -> 18851.997 | N59: =N20*N62 -> 20540.649 | O59: =O20*O62 -> 22398.178 | P59: =P20*P62 -> 24442.742 | Q59: =Q20*Q62 -> 26644.218 | R59: =R20*R62 -> 28906.461 | ... T59: =T20*T62 -> 33547.397
B60: Total Other Expenses | E60: =E59 -> 9843 | F60: =F59 -> 10896 | G60: =G59 -> 11309 | H60: =H59 -> 11861 | I60: =I59 -> 14464 | J60: =J59 -> 14615 | K60: =K59 -> 15917.655 | L60: =L59 -> 17315.893 | ... T60: =T59 -> 33547.397
B62: Other Expenses % Sales | E62: ='Control Sheet'!E86 -> 0.24741724 | F62: ='Control Sheet'!F86 -> 0.23169176 | G62: ='Control Sheet'!G86 -> 0.21563132 | H62: ='Control Sheet'!H86 -> 0.19579069 | I62: ='Control Sheet'!I86 -> 0.23368231 | J62: ='Control Sheet'!J86 -> 0.23153942 | K62: ='Control Sheet'!K86 -> 0.232 | L62: ='Control Sheet'!L86 -> 0.232 | ... T62: ='Control Sheet'!T86 -> 0.232
B63: Other Expenses % yoy growth | F63: =F60/E60-1 -> 0.10697958 | G63: =G60/F60-1 -> 0.037903818 | H63: =H60/G60-1 -> 0.048810682 | I63: =I60/H60-1 -> 0.21945873 | J63: =J60/I60-1 -> 0.010439712 | K63: =K60/J60-1 -> 0.089131342 | L63: =L60/K60-1 -> 0.087841998 | M63: =M60/L60-1 -> 0.088710637 | ... T63: =T60/S60-1 -> 0.074792631
B65: Total SG&A Expense (Excluding Depriciation & Interest Expense) | E65: =E51+E60 -> 11663 | F65: =F51+F60 -> 13254 | G65: =G51+G60 -> 13854 | H65: =H51+H60 -> 14715 | I65: =I51+I60 -> 17473 | J65: =J51+J60 -> 17692 | K65: =K51+K60 -> 19210.962 | L65: =L51+L60 -> 20898.492 | ... T65: =T51+T60 -> 40488.238
B66: Total SG&A % Sales | E66: =E65/E20 -> 0.29316542 | F66: =F65/F20 -> 0.2818321 | G66: =G65/G20 -> 0.26415742 | H66: =H65/H20 -> 0.24286186 | I66: =I65/I20 -> 0.28257002 | J66: =J65/J20 -> 0.28028707 | K66: =K65/K20 -> 0.28 | L66: =L65/L20 -> 0.28 | ... T66: =T65/T20 -> 0.28
A68: # | B68: Non-Current Asset Schedule
B70: Property, Plant & Equipments
B73: Opening PP&E at the beginning of the Year | E73: ='Balance Sheet'!C39 -> 4170 | F73: ='Balance Sheet'!D39 -> 4109 | G73: ='Balance Sheet'!E39 -> 5067 | H73: ='Balance Sheet'!F39 -> 5101 | I73: ='Balance Sheet'!G39 -> 5767 | J73: ='Balance Sheet'!H39 -> 6517 | K73: ='Balance Sheet'!I39 -> 6941 | L73: =K76 -> 7201.4916 | M73: =L76 -> 7483.6076 | N73: =M76 -> 7790.4923 | O73: =N76 -> 8125.6905 | P73: =O76 -> 8493.1964 | Q73: =P76 -> 8897.5089 | R73: =Q76 -> 9339.5277 | S73: =R76 -> 9811.2674 | T73: =S76 -> 10303.012
B74: Add: Capex During the Year | E74: =-'Cash Flow Statement'!D46 -> 850 | F74: =-'Cash Flow Statement'!E46 -> 741 | G74: =-'Cash Flow Statement'!F46 -> 1225 | H74: =-'Cash Flow Statement'!G46 -> 1174 | I74: =-'Cash Flow Statement'!H46 -> 1468 | J74: =-'Cash Flow Statement'!I46 -> 1254 | K74: ='Assumptions Working'!L1006 -> 1411.5824 | L74: ='Assumptions Working'!M1006 -> 1535.5786 | M74: ='Assumptions Working'!N1006 -> 1671.8008 | N74: ='Assumptions Working'!O1006 -> 1821.551 | O74: ='Assumptions Working'!P1006 -> 1986.2771 | P74: ='Assumptions Working'!Q1006 -> 2167.5897 | Q74: ='Assumptions Working'!R1006 -> 2362.8173 | R74: ='Assumptions Working'!S1006 -> 2563.4337 | ... T74: ='Assumptions Working'!U1006 -> 2974.9933
B75: Less: Depreciation During the Year | D75: 15 | E75: =(' Income Statement'!D41/SUM('Balance Sheet'!D39,'Balance Sheet'!D40,'Assumptions Working'!I930))*'Balance Sheet'!D39 -> -805.0876 | F75: =(' Income Statement'!E41/SUM('Balance Sheet'!E39,'Balance Sheet'!E40,'Assumptions Working'!J930))*'Balance Sheet'!E39 -> -856.46176 | G75: =(' Income Statement'!F41/SUM('Balance Sheet'!F39,'Balance Sheet'!F40,'Assumptions Working'!K930))*'Balance Sheet'!F39 -> -869.01796 | H75: =(' Income Statement'!G41/SUM('Balance Sheet'!G39,'Balance Sheet'!G40,'Assumptions Working'!L930))*'Balance Sheet'!G39 -> -910.32611 | I75: =(' Income Statement'!H41/SUM('Balance Sheet'!H39,'Balance Sheet'!H40,'Assumptions Working'!M930))*'Balance Sheet'!H39 -> -955.47046 | J75: =(' Income Statement'!I41/SUM('Balance Sheet'!I39,'Balance Sheet'!I40,'Assumptions Working'!N930))*'Balance Sheet'!I39 -> -1056.9853 | K75: =J75-(K74/$D$75) -> -1151.0908 | L75: =K75-(L74/$D$75) -> -1253.4627 | M75: =L75-(M74/$D$75) -> -1364.9161 | N75: =M75-(N74/$D$75) -> -1486.3528 | O75: =N75-(O74/$D$75) -> -1618.7713 | P75: =O75-(P74/$D$75) -> -1763.2773 | Q75: =P75-(Q74/$D$75) -> -1920.7984 | R75: =Q75-(R74/$D$75) -> -2091.694 | ... T75: =S75-(T74/$D$75) -> -2474.5582
B76: Closing PP&E at the end of the Year | E76: =SUM(E73:E75) -> 4214.9124 | F76: =SUM(F73:F75) -> 3993.5382 | G76: =SUM(G73:G75) -> 5422.982 | H76: =SUM(H73:H75) -> 5364.6739 | I76: =SUM(I73:I75) -> 6279.5295 | J76: =SUM(J73:J75) -> 6714.0147 | K76: =SUM(K73:K75) -> 7201.4916 | L76: =SUM(L73:L75) -> 7483.6076 | ... T76: =SUM(T73:T75) -> 10803.447
B78: YoY Growth % | F78: =F76/E76-1 -> -0.05252165 | G78: =G76/F76-1 -> 0.35793918 | H78: =H76/G76-1 -> -0.010752047 | I78: =I76/H76-1 -> 0.17053332 | J78: =J76/I76-1 -> 0.069190722 | K78: =K76/J76-1 -> 0.072605876 | L78: =L76/K76-1 -> 0.039174655 | M78: =M76/L76-1 -> 0.041007591 | ... T78: =T76/S76-1 -> 0.048571731
B80: Right-of-Use Assets
B83: Opening Rou Assets at the beginning of the Year | J83: ='Assumptions Working'!N927 -> 2878 | K83: ='Balance Sheet'!I40 -> 1684 | L83: =K86 -> 2522.26 | M83: =L86 -> 3129.6222 | N83: =M86 -> 3754.9328 | O83: =N86 -> 4400.6879 | P83: =O86 -> 5069.6978 | Q83: =P86 -> 5765.1258 | R83: =Q86 -> 6482.2093 | S83: =R86 -> 7203.6834 | T83: =S86 -> 7921.7825
B84: Add: New Lease Liabilities During the Year | K84: =K195 -> 1172.8948 | L84: =L195 -> 1009.2826 | M84: =M195 -> 1100.6047 | N84: =N195 -> 1201.1241 | O84: =O195 -> 1311.8345 | P84: =P195 -> 1433.8421 | Q84: =Q195 -> 1559.4616 | R84: =R195 -> 1675.556 | ... T84: =T195 -> 1906.9438
B85: Less: Depreciation During the Year | D85: 15 | J85: =(' Income Statement'!I41/SUM('Assumptions Working'!N930,'Balance Sheet'!I39,'Balance Sheet'!I40))*'Balance Sheet'!I40 -> -256.4419 | K85: =J85-(K84/$D$85) -> -334.63489 | L85: =K85-(L84/$D$85) -> -401.9204 | M85: =L85-(M84/$D$85) -> -475.29404 | N85: =M85-(N84/$D$85) -> -555.36898 | O85: =N85-(O84/$D$85) -> -642.82461 | P85: =O85-(P84/$D$85) -> -738.41409 | Q85: =P85-(Q84/$D$85) -> -842.37819 | R85: =Q85-(R84/$D$85) -> -954.08193 | ... T85: =S85-(T84/$D$85) -> -1200.653
B86: Closing Rou Assets at the end of the Year | J86: ='Balance Sheet'!I40 -> 1684 | K86: =SUM(K83:K85) -> 2522.26 | L86: =SUM(L83:L85) -> 3129.6222 | M86: =SUM(M83:M85) -> 3754.9328 | N86: =SUM(N83:N85) -> 4400.6879 | O86: =SUM(O83:O85) -> 5069.6978 | P86: =SUM(P83:P85) -> 5765.1258 | Q86: =SUM(Q83:Q85) -> 6482.2093 | R86: =SUM(R83:R85) -> 7203.6834 | ... T86: =SUM(T83:T85) -> 8628.0733
B88: YoY Growth % | K88: =K86/J86-1 -> 0.49777907 | L88: =L86/K86-1 -> 0.24080081 | M88: =M86/L86-1 -> 0.19980387 | N88: =N86/M86-1 -> 0.17197514 | O88: =O86/N86-1 -> 0.15202394 | P88: =P86/O86-1 -> 0.13717347 | Q88: =Q86/P86-1 -> 0.12438296 | R88: =R86/Q86-1 -> 0.11130065 | ... T88: =T86/S86-1 -> 0.08915806
B91: Capital Work in Progress
B94: Capital Work in Progress | E94: ='Balance Sheet'!D41 -> 597 | F94: ='Balance Sheet'!E41 -> 745 | G94: ='Balance Sheet'!F41 -> 1313 | H94: ='Balance Sheet'!G41 -> 1132 | I94: ='Balance Sheet'!H41 -> 1025 | J94: ='Balance Sheet'!I41 -> 1009 | K94: =K97*K95 -> 1058.3955 | L94: =L97*L95 -> 1064.2199 | M94: =M97*M95 -> 1070.5584 | N94: =N97*N95 -> 1077.4846 | O94: =O97*O95 -> 1085.0814 | P94: =P97*P95 -> 1093.5182 | Q94: =Q97*Q95 -> 1102.8282 | R94: =R97*R95 -> 1112.8688 | ... T94: =T97*T95 -> 1134.4153
B95: CWIP % Net Fixed Assets | F95: =F94/E94-1 -> 0.2479062 | G95: =G94/F94-1 -> 0.76241611 | H95: =H94/G94-1 -> -0.13785225 | I95: =I94/H94-1 -> -0.094522968 | J95: =J94/I94-1 -> -0.015609756 | K95: ='Control Sheet'!K108 -> 0.02 | L95: ='Control Sheet'!L108 -> 0.02 | M95: ='Control Sheet'!M108 -> 0.02 | N95: ='Control Sheet'!N108 -> 0.02 | O95: ='Control Sheet'!O108 -> 0.02 | P95: ='Control Sheet'!P108 -> 0.02 | Q95: ='Control Sheet'!Q108 -> 0.02 | R95: ='Control Sheet'!R108 -> 0.02 | ... T95: ='Control Sheet'!T108 -> 0.02
B97: Total Net Fixed Assets | E97: ='3Statement Model'!D83+'3Statement Model'!D86+'3Statement Model'!D87 -> 4628 | F97: ='3Statement Model'!E83+'3Statement Model'!E86+'3Statement Model'!E87 -> 50394 | G97: ='3Statement Model'!F83+'3Statement Model'!F86+'3Statement Model'!F87 -> 50405 | H97: ='3Statement Model'!G83+'3Statement Model'!G86+'3Statement Model'!G87 -> 51496 | I97: ='3Statement Model'!H83+'3Statement Model'!H86+'3Statement Model'!H87 -> 52230 | J97: ='3Statement Model'!I83+'3Statement Model'!I86+'3Statement Model'!I87 -> 52651 | K97: ='3Statement Model'!J83+'3Statement Model'!J86+'3Statement Model'!J87 -> 52919.776 | L97: ='3Statement Model'!K83+'3Statement Model'!K86+'3Statement Model'!K87 -> 53210.995 | ... T97: ='3Statement Model'!S83+'3Statement Model'!S86+'3Statement Model'!S87 -> 56720.764
B99: Goodwill
B102: Goodwill | E102: ='Balance Sheet'!D42 -> 117 | F102: ='Balance Sheet'!E42 -> 17397 | G102: ='Balance Sheet'!F42 -> 17397 | H102: ='Balance Sheet'!G42 -> 17466 | I102: ='Balance Sheet'!H42 -> 17466 | J102: ='Balance Sheet'!I42 -> 17466 | K102: =J102+(J102*K103) -> 17466 | L102: =K102+(K102*L103) -> 17466 | M102: =L102+(L102*M103) -> 17466 | N102: =M102+(M102*N103) -> 17466 | O102: =N102+(N102*O103) -> 17466 | P102: =O102+(O102*P103) -> 17466 | Q102: =P102+(P102*Q103) -> 17466 | R102: =Q102+(Q102*R103) -> 17466 | ... T102: =S102+(S102*T103) -> 17466
B103: YoY Growth % | F103: =F102/E102-1 -> 147.69231 | G103: =G102/F102-1 -> 0 | H103: =H102/G102-1 -> 0.0039662011 | I103: =I102/H102-1 -> 0 | J103: =J102/I102-1 -> 0 | K103: ='Control Sheet'!K114 -> 0 | L103: ='Control Sheet'!L114 -> 0 | M103: ='Control Sheet'!M114 -> 0 | N103: ='Control Sheet'!N114 -> 0 | O103: ='Control Sheet'!O114 -> 0 | P103: ='Control Sheet'!P114 -> 0 | Q103: ='Control Sheet'!Q114 -> 0 | R103: ='Control Sheet'!R114 -> 0 | ... T103: ='Control Sheet'!T114 -> 0
B105: Other Intangibles
B108: Opening Other Intangibles at the beginning of the year | J108: ='Balance Sheet'!H43 -> 28247 | K108: ='Balance Sheet'!I43 -> 28244 | L108: =K112 -> 28252.285 | M108: =L112 -> 28261.387 | N108: =M112 -> 28271.428 | O108: =N112 -> 28282.539 | P108: =O112 -> 28294.874 | Q108: =P112 -> 28312.402 | R108: =Q112 -> 28335.88 | S108: =R112 -> 28366.174 | T108: =S112 -> 28404.274
B109: Addition in Brand Rights | J109: 0 | K109: =J109 -> 0 | L109: =K109 -> 0 | M109: =L109 -> 0 | N109: =M109 -> 0 | O109: =N109 -> 0 | P109: =O109 -> 0 | Q109: =P109 -> 0 | R109: =Q109 -> 0 | ... T109: =S109 -> 0
B110: Addition in Other Intangibles | J110: 12 | K110: =K115-J115 -> 53.41863 | L110: =L115-K115 -> 58.111029 | M110: =M115-L115 -> 63.266096 | N110: =N115-M115 -> 68.933105 | O110: =O115-N115 -> 75.166851 | P110: =P115-O115 -> 86.101126 | Q110: =Q115-P115 -> 98.625974 | R110: =R115-Q115 -> 112.97277 | ... T110: =T115-S115 -> 148.23089
B111: Less: Depreciation | D111: 15 | E111: =(' Income Statement'!D41/SUM('Balance Sheet'!D39,'Balance Sheet'!D40,'Assumptions Working'!I930))*'Assumptions Working'!I930 -> -30.173641 | F111: =(' Income Statement'!E41/SUM('Balance Sheet'!E39,'Balance Sheet'!E40,'Assumptions Working'!J930))*'Assumptions Working'!J930 -> -40.228517 | G111: =(' Income Statement'!F41/SUM('Balance Sheet'!F39,'Balance Sheet'!F40,'Assumptions Working'!K930))*'Assumptions Working'!K930 -> -40.035134 | H111: =(' Income Statement'!G41/SUM('Balance Sheet'!G39,'Balance Sheet'!G40,'Assumptions Working'!L930))*'Assumptions Working'!L930 -> -40.094127 | I111: =(' Income Statement'!H41/SUM('Balance Sheet'!H39,'Balance Sheet'!H40,'Assumptions Working'!M930))*'Assumptions Working'!M930 -> -38.558958 | J111: =(' Income Statement'!I41/SUM('Balance Sheet'!I39,'Balance Sheet'!I40,'Assumptions Working'!N930))*'Assumptions Working'!N930 -> -41.572825 | K111: =J111-(K110/$D$111) -> -45.134067 | L111: =K111-(L110/$D$111) -> -49.008136 | M111: =L111-(M110/$D$111) -> -53.225876 | N111: =M111-(N110/$D$111) -> -57.821416 | O111: =N111-(O110/$D$111) -> -62.832539 | P111: =O111-(P110/$D$111) -> -68.572614 | Q111: =P111-(Q110/$D$111) -> -75.147679 | R111: =Q111-(R110/$D$111) -> -82.679197 | ... T111: =S111-(T110/$D$111) -> -101.18836
B112: Closing Other Intangibles at the beginning of the year | J112: =SUM(J108:J111) -> 28217.427 | K112: =SUM(K108:K111) -> 28252.285 | L112: =SUM(L108:L111) -> 28261.387 | M112: =SUM(M108:M111) -> 28271.428 | N112: =SUM(N108:N111) -> 28282.539 | O112: =SUM(O108:O111) -> 28294.874 | P112: =SUM(P108:P111) -> 28312.402 | Q112: =SUM(Q108:Q111) -> 28335.88 | ... T112: =SUM(T108:T111) -> 28451.317
B114: Brand Rights | E114: ='Assumptions Working'!I929 -> 311 | F114: ='Assumptions Working'!J929 -> 27782 | G114: ='Assumptions Working'!K929 -> 27782 | H114: ='Assumptions Working'!L929 -> 28413 | I114: ='Assumptions Working'!M929 -> 28413 | J114: ='Assumptions Working'!N929 -> 28413 | K114: =J114+(J114*K116) -> 28413 | L114: =K114+(K114*L116) -> 28413 | M114: =L114+(L114*M116) -> 28413 | N114: =M114+(M114*N116) -> 28413 | O114: =N114+(N114*O116) -> 28413 | P114: =O114+(O114*P116) -> 28413 | Q114: =P114+(P114*Q116) -> 28413 | R114: =Q114+(Q114*R116) -> 28413 | ... T114: =S114+(S114*T116) -> 28413
B115: Other Intangibles (Excluding Brand Rights) | E115: ='Assumptions Working'!I930 -> 154 | F115: ='Assumptions Working'!J930 -> 238 | G115: ='Assumptions Working'!K930 -> 235 | H115: ='Assumptions Working'!L930 -> 254 | I115: ='Assumptions Working'!M930 -> 263 | J115: ='Assumptions Working'!N930 -> 273 | K115: =(J115*K117)+J115 -> 326.41863 | L115: =(K115*L117)+K115 -> 384.52966 | M115: =(L115*M117)+L115 -> 447.79576 | N115: =(M115*N117)+M115 -> 516.72886 | O115: =(N115*O117)+N115 -> 591.89571 | P115: =(O115*P117)+O115 -> 677.99684 | Q115: =(P115*Q117)+P115 -> 776.62281 | R115: =(Q115*R117)+Q115 -> 889.59558 | ... T115: =(S115*T117)+S115 -> 1167.233
B116: YoY Growth % | F116: =F114/E114-1 -> 88.33119 | G116: =G114/F114-1 -> 0 | H116: =H114/G114-1 -> 0.022712548 | I116: =I114/H114-1 -> 0 | J116: =J114/I114-1 -> 0 | K116: ='Control Sheet'!K120 -> 0 | L116: ='Control Sheet'!L120 -> 0 | M116: ='Control Sheet'!M120 -> 0 | N116: ='Control Sheet'!N120 -> 0 | O116: ='Control Sheet'!O120 -> 0 | P116: ='Control Sheet'!P120 -> 0 | Q116: ='Control Sheet'!Q120 -> 0 | R116: ='Control Sheet'!R120 -> 0 | ... T116: ='Control Sheet'!T120 -> 0
B117: Other Intangibles YoY Growth % | F117: =F115/E115-1 -> 0.54545455 | G117: =G115/F115-1 -> -0.012605042 | H117: =H115/G115-1 -> 0.080851064 | I117: =I115/H115-1 -> 0.035433071 | J117: =J115/I115-1 -> 0.038022814 | K117: ='Control Sheet'!K126 -> 0.19567264 | L117: ='Control Sheet'!L126 -> 0.17802608 | M117: ='Control Sheet'!M126 -> 0.16452852 | N117: ='Control Sheet'!N126 -> 0.15393872 | O117: ='Control Sheet'!O126 -> 0.14546672 | P117: ='Control Sheet'!P126 -> 0.14546672 | Q117: ='Control Sheet'!Q126 -> 0.14546672 | R117: ='Control Sheet'!R126 -> 0.14546672 | ... T117: ='Control Sheet'!T126 -> 0.14546672
B119: Non-Current Financial Assets
B122: Non-Current Financial Assets | E122: =SUM('Balance Sheet'!D45:D47) -> 243 | F122: =SUM('Balance Sheet'!E45:E47) -> 870 | G122: =SUM('Balance Sheet'!F45:F47) -> 846 | H122: =SUM('Balance Sheet'!G45:G47) -> 894 | I122: =SUM('Balance Sheet'!H45:H47) -> 929 | J122: =SUM('Balance Sheet'!I45:I47) -> 909 | K122: =J122+(J122*K123) -> 922.635 | L122: =K122+(K122*L123) -> 936.47452 | M122: =L122+(L122*M123) -> 950.52164 | N122: =M122+(M122*N123) -> 964.77947 | O122: =N122+(N122*O123) -> 979.25116 | P122: =O122+(O122*P123) -> 993.93993 | Q122: =P122+(P122*Q123) -> 1008.849 | R122: =Q122+(Q122*R123) -> 1023.9818 | ... T122: =S122+(S122*T123) -> 1054.9316
B123: Non-Current Financial Assets % Revenue | E123: ='Assumptions Working'!E1023 -> 0.0061081366 | F123: ='Assumptions Working'!F1023 -> 0.018499617 | G123: ='Assumptions Working'!G1023 -> 0.016130877 | H123: ='Assumptions Working'!H1023 -> 0.014757346 | I123: ='Assumptions Working'!I1023 -> 0.015009047 | J123: ='Assumptions Working'!J1023 -> 0.014400913 | K123: ='Control Sheet'!K132 -> 0.015 | L123: ='Control Sheet'!L132 -> 0.015 | M123: ='Control Sheet'!M132 -> 0.015 | N123: ='Control Sheet'!N132 -> 0.015 | O123: ='Control Sheet'!O132 -> 0.015 | P123: ='Control Sheet'!P132 -> 0.015 | Q123: ='Control Sheet'!Q132 -> 0.015 | R123: ='Control Sheet'!R132 -> 0.015 | ... T123: ='Control Sheet'!T132 -> 0.015
B125: Deferred Tax Assets
B128: Deferred Tax Assets | E128: ='Balance Sheet'!D48 -> 284 | F128: ='Balance Sheet'!E48 -> 17 | G128: ='Balance Sheet'!F48 -> 11 | H128: ='Balance Sheet'!G48 -> 10 | I128: ='Balance Sheet'!H48 -> 10 | J128: ='Balance Sheet'!I48 -> 17 | K128: =J128+(J128*K129) -> 17 | L128: =K128+(K128*L129) -> 17 | M128: =L128+(L128*M129) -> 17 | N128: =M128+(M128*N129) -> 17 | O128: =N128+(N128*O129) -> 17 | P128: =O128+(O128*P129) -> 17 | Q128: =P128+(P128*Q129) -> 17 | R128: =Q128+(Q128*R129) -> 17 | ... T128: =S128+(S128*T129) -> 17
B129: YoY Growth % | F129: =F128/E128-1 -> -0.94014085 | G129: =G128/F128-1 -> -0.35294118 | H129: =H128/G128-1 -> -0.090909091 | I129: =I128/H128-1 -> 0 | J129: =J128/I128-1 -> 0.7 | K129: ='Control Sheet'!K138 -> 0 | L129: ='Control Sheet'!L138 -> 0 | M129: ='Control Sheet'!M138 -> 0 | N129: ='Control Sheet'!N138 -> 0 | O129: ='Control Sheet'!O138 -> 0 | P129: ='Control Sheet'!P138 -> 0 | Q129: ='Control Sheet'!Q138 -> 0 | R129: ='Control Sheet'!R138 -> 0 | ... T129: ='Control Sheet'!T138 -> 0
B131: Non-Current Tax Assets
B134: Non-Current Tax Assets | E134: ='Balance Sheet'!D49 -> 1083 | F134: ='Balance Sheet'!E49 -> 1246 | G134: ='Balance Sheet'!F49 -> 1158 | H134: ='Balance Sheet'!G49 -> 1164 | I134: ='Balance Sheet'!H49 -> 1175 | J134: ='Balance Sheet'!I49 -> 1199 | K134: =J134+(J134*K135) -> 1199 | L134: =K134+(K134*L135) -> 1199 | M134: =L134+(L134*M135) -> 1199 | N134: =M134+(M134*N135) -> 1199 | O134: =N134+(N134*O135) -> 1199 | P134: =O134+(O134*P135) -> 1199 | Q134: =P134+(P134*Q135) -> 1199 | R134: =Q134+(Q134*R135) -> 1199 | ... T134: =S134+(S134*T135) -> 1199
B135: YoY Growth % | F135: =F134/E134-1 -> 0.15050785 | G135: =G134/F134-1 -> -0.070626003 | H135: =H134/G134-1 -> 0.0051813472 | I135: =I134/H134-1 -> 0.0094501718 | J135: =J134/I134-1 -> 0.020425532 | K135: ='Control Sheet'!K144 -> 0 | L135: ='Control Sheet'!L144 -> 0 | M135: ='Control Sheet'!M144 -> 0 | N135: ='Control Sheet'!N144 -> 0 | O135: ='Control Sheet'!O144 -> 0 | P135: ='Control Sheet'!P144 -> 0 | Q135: ='Control Sheet'!Q144 -> 0 | R135: ='Control Sheet'!R144 -> 0 | ... T135: ='Control Sheet'!T144 -> 0
B137: Other Non-Current Assets
B140: Other Non-Current Assets | E140: ='Balance Sheet'!D50 -> 146 | F140: ='Balance Sheet'!E50 -> 219 | G140: ='Balance Sheet'!F50 -> 194 | H140: ='Balance Sheet'!G50 -> 211 | I140: ='Balance Sheet'!H50 -> 292 | J140: ='Balance Sheet'!I50 -> 360 | K140: =J140+(J140*K141) -> 361.44 | L140: =K140+(K140*L141) -> 362.88576 | M140: =L140+(L140*M141) -> 364.3373 | N140: =M140+(M140*N141) -> 365.79465 | O140: =N140+(N140*O141) -> 367.25783 | P140: =O140+(O140*P141) -> 368.72686 | Q140: =P140+(P140*Q141) -> 370.20177 | R140: =Q140+(Q140*R141) -> 371.68258 | ... T140: =S140+(S140*T141) -> 374.66198
B141: Other Non-Current Assets % Revenue | E141: ='Assumptions Working'!E1022 -> 0.0036699093 | F141: ='Assumptions Working'!F1022 -> 0.0046568002 | G141: ='Assumptions Working'!G1022 -> 0.0036990428 | H141: ='Assumptions Working'!H1022 -> 0.0034829977 | I141: ='Assumptions Working'!I1022 -> 0.0047175908 | J141: ='Assumptions Working'!J1022 -> 0.0057033317 | K141: 0.004 | L141: =K141 -> 0.004 | M141: =L141 -> 0.004 | N141: =M141 -> 0.004 | O141: =N141 -> 0.004 | P141: =O141 -> 0.004 | Q141: =P141 -> 0.004 | R141: =Q141 -> 0.004 | S141: =R141 -> 0.004 | T141: =S141 -> 0.004
A144: # | B144: Depreciation & Amortization Schedule
B146: Depreciation & Amortization for the Year | E146: =' Income Statement'!D41 -> -1002 | F146: =' Income Statement'!E41 -> -1074 | G146: =' Income Statement'!F41 -> -1091 | H146: =' Income Statement'!G41 -> -1137 | I146: =' Income Statement'!H41 -> -1216 | J146: =' Income Statement'!I41 -> -1355 | K146: =K111+K85+K75 -> -1530.8597 | L146: =L111+L85+L75 -> -1704.3912 | M146: =M111+M85+M75 -> -1893.436 | N146: =N111+N85+N75 -> -2099.5432 | O146: =O111+O85+O75 -> -2324.4284 | P146: =P111+P85+P75 -> -2570.264 | Q146: =Q111+Q85+Q75 -> -2838.3243 | R146: =R111+R85+R75 -> -3128.4551 | ... T146: =T111+T85+T75 -> -3776.3996
B147: Total Depreciation & Amortization for the Year | E147: =E146 -> -1002 | F147: =F146 -> -1074 | G147: =G146 -> -1091 | H147: =H146 -> -1137 | I147: =I146 -> -1216 | J147: =J146 -> -1355 | K147: =K146 -> -1530.8597 | L147: =L146 -> -1704.3912 | ... T147: =T146 -> -3776.3996
B149: Depreciation & Amortization % Sales | E149: =-E146/'3Statement Model'!D13 -> 0.025186638 | F149: =-F146/'3Statement Model'!E13 -> 0.022837459 | G149: =-G146/'3Statement Model'!F13 -> 0.020802349 | H149: =-H146/'3Statement Model'!G13 -> 0.018765473 | I149: =-I146/'3Statement Model'!H13 -> 0.01966492 | J149: =-J146/'3Statement Model'!I13 -> 0.021466707 | K149: =-K146/'3Statement Model'!J13 -> 0.022312298 | L149: =-L146/'3Statement Model'!K13 -> 0.022835597 | ... T149: =-T146/'3Statement Model'!S13 -> 0.026116026
B151: Depreciation & Amortization Waterfall Schedule
B153: =$J$9 -> 2025 | J153: =J146*-1 -> 1355 | K153: =J153 -> 1355 | L153: =K153 -> 1355 | M153: =L153 -> 1355 | N153: =M153 -> 1355 | O153: =N153 -> 1355 | P153: =O153 -> 1355 | Q153: =P153 -> 1355 | R153: =Q153 -> 1355 | ... T153: =S153 -> 1355
B154: =$K$9 -> 2026 | K154: =(K74/$D$75)+(K110/$D$111) -> 97.666736 | L154: =K154 -> 97.666736 | M154: =L154 -> 97.666736 | N154: =M154 -> 97.666736 | O154: =N154 -> 97.666736 | P154: =O154 -> 97.666736 | Q154: =P154 -> 97.666736 | R154: =Q154 -> 97.666736 | S154: =R154 -> 97.666736 | T154: =S154 -> 97.666736
B155: =$L$9 -> 2027 | L155: =(L74/$D$75)+(L110/$D$111) -> 106.24598 | M155: =L155 -> 106.24598 | N155: =M155 -> 106.24598 | O155: =N155 -> 106.24598 | P155: =O155 -> 106.24598 | Q155: =P155 -> 106.24598 | R155: =Q155 -> 106.24598 | S155: =R155 -> 106.24598 | T155: =S155 -> 106.24598
B156: =$M$9 -> 2028 | M156: =(M74/$D$75)+(M110/$D$111) -> 115.67113 | N156: =M156 -> 115.67113 | O156: =N156 -> 115.67113 | P156: =O156 -> 115.67113 | Q156: =P156 -> 115.67113 | R156: =Q156 -> 115.67113 | S156: =R156 -> 115.67113 | T156: =S156 -> 115.67113
B157: =$N$9 -> 2029 | N157: =(N74/$D$75)+(N110/$D$111) -> 126.03227 | O157: =N157 -> 126.03227 | P157: =O157 -> 126.03227 | Q157: =P157 -> 126.03227 | R157: =Q157 -> 126.03227 | S157: =R157 -> 126.03227 | T157: =S157 -> 126.03227
B158: =$O$9 -> 2030 | O158: =(O74/$D$75)+(O110/$D$111) -> 137.4296 | P158: =(P74/$D$75)+(P110/$D$111) -> 150.24606 | Q158: =(Q74/$D$75)+(Q110/$D$111) -> 164.09622 | R158: =(R74/$D$75)+(R110/$D$111) -> 178.4271 | S158: =(S74/$D$75)+(S110/$D$111) -> 193.15841 | T158: =(T74/$D$75)+(T110/$D$111) -> 208.21495
B159: Total Depreciation | J159: =SUM(J153:J158) -> 1355 | K159: =SUM(K153:K158) -> 1452.6667 | L159: =SUM(L153:L158) -> 1558.9127 | M159: =SUM(M153:M158) -> 1674.5838 | N159: =SUM(N153:N158) -> 1800.6161 | O159: =SUM(O153:O158) -> 1938.0457 | P159: =SUM(P153:P158) -> 1950.8622 | Q159: =SUM(Q153:Q158) -> 1964.7123 | ... T159: =SUM(T153:T158) -> 2008.8311
A161: # | B161: Tax Expense Schedule
B163: Revenue | K163: ='3Statement Model'!J13 -> 68610.58 | L163: ='3Statement Model'!K13 -> 74637.47 | M163: ='3Statement Model'!L13 -> 81258.608 | N163: ='3Statement Model'!M13 -> 88537.282 | O163: ='3Statement Model'!N13 -> 96543.869 | P163: ='3Statement Model'!O13 -> 105356.65 | Q163: ='3Statement Model'!P13 -> 114845.77 | R163: ='3Statement Model'!Q13 -> 124596.81 | ... T163: ='3Statement Model'!S13 -> 144600.85
B164: Less: COGS | K164: ='3Statement Model'!J14 -> -33619.184 | L164: ='3Statement Model'!K14 -> -36404.426 | M164: ='3Statement Model'!L14 -> -39451.054 | N164: ='3Statement Model'!M14 -> -42785.642 | O164: ='3Statement Model'!N14 -> -46437.601 | P164: ='3Statement Model'!O14 -> -50676.547 | Q164: ='3Statement Model'!P14 -> -55240.814 | R164: ='3Statement Model'!Q14 -> -59931.067 | ... T164: ='3Statement Model'!S14 -> -69553.008
B165: Less: SG&A | K165: ='3Statement Model'!J20 -> -19210.962 | L165: ='3Statement Model'!K20 -> -20898.492 | M165: ='3Statement Model'!L20 -> -22752.41 | N165: ='3Statement Model'!M20 -> -24790.439 | O165: ='3Statement Model'!N20 -> -27032.283 | P165: ='3Statement Model'!O20 -> -29499.861 | Q165: ='3Statement Model'!P20 -> -32156.815 | R165: ='3Statement Model'!Q20 -> -34887.108 | ... T165: ='3Statement Model'!S20 -> -40488.238
B166: Less: Depreciation & Amortization | K166: ='3Statement Model'!J27 -> -1530.8597 | L166: ='3Statement Model'!K27 -> -1704.3912 | M166: ='3Statement Model'!L27 -> -1893.436 | N166: ='3Statement Model'!M27 -> -2099.5432 | O166: ='3Statement Model'!N27 -> -2324.4284 | P166: ='3Statement Model'!O27 -> -2570.264 | Q166: ='3Statement Model'!P27 -> -2838.3243 | R166: ='3Statement Model'!Q27 -> -3128.4551 | ... T166: ='3Statement Model'!S27 -> -3776.3996
B167: Less: Finance Costs | K167: ='3Statement Model'!J32 -> -266.84209 | L167: ='3Statement Model'!K32 -> -290.28203 | M167: ='3Statement Model'!L32 -> -316.03314 | N167: ='3Statement Model'!M32 -> -344.34155 | O167: ='3Statement Model'!N32 -> -375.48098 | P167: ='3Statement Model'!O32 -> -409.75587 | Q167: ='3Statement Model'!P32 -> -446.66121 | R167: ='3Statement Model'!Q32 -> -484.58524 | ... T167: ='3Statement Model'!S32 -> -562.38546
B168: Add: Other Income | K168: ='3Statement Model'!J33 -> 1017 | L168: ='3Statement Model'!K33 -> 1017 | M168: ='3Statement Model'!L33 -> 1017 | N168: ='3Statement Model'!M33 -> 1017 | O168: ='3Statement Model'!N33 -> 1017 | P168: ='3Statement Model'!O33 -> 1017 | Q168: ='3Statement Model'!P33 -> 1017 | R168: ='3Statement Model'!Q33 -> 1017 | ... T168: ='3Statement Model'!S33 -> 1017
...

Sheet 3Statement Model
B2: ='Input Sheet'!C6 -> Hindustan Unilever Ltd.
B3: 3 Statement Model
I4: Current Case:
U7: CAGR
D8: Actual | J8: Explicit Forecast Period | O8: Maturity Period | U8: 5 Years | V8: 3 Years
B9: In Crs Unless Stated Otherwise | D9: 2020 | E9: =D9+1 -> 2021 | F9: =E9+1 -> 2022 | G9: =F9+1 -> 2023 | H9: =G9+1 -> 2024 | I9: =H9+1 -> 2025 | J9: =I9+1 -> 2026 | K9: =J9+1 -> 2027 | L9: =K9+1 -> 2028 | ... S9: =R9+1 -> 2035
A11: # | B11: Income Statement
B13: Revenue From Operations | D13: =INDEX(' Income Statement'!$D$7:$I$62,MATCH('3Statement Model'!$B13,' Income Statement'!$B$7:$B$62,0),MATCH('3Statement Model'!D$9,' Income Statement'!$D$6:$I$6,)) -> 39783 | E13: =Schedules!F20 -> 47028 | F13: =Schedules!G20 -> 52446 | G13: =Schedules!H20 -> 60590 | H13: =Schedules!I20 -> 61836 | I13: =Schedules!J20 -> 63121 | J13: =Schedules!K20 -> 68610.58 | K13: =Schedules!L20 -> 74637.47 | L13: =Schedules!M20 -> 81258.608 | ... S13: =Schedules!T20 -> 144600.85 | U13: =_xlfn.RRI(5,I13,N13) -> 0.088704869 | V13: =_xlfn.RRI(3,I13,L13) -> 0.087840364
B14: Less: Cost of Goods Sold | D14: =' Income Statement'!D20 -> -18259 | E14: =' Income Statement'!E20 -> -22148 | F14: =' Income Statement'!F20 -> -25735 | G14: =' Income Statement'!G20 -> -31716 | H14: =' Income Statement'!H20 -> -29760 | I14: =' Income Statement'!I20 -> -30578 | J14: =-Schedules!K40 -> -33619.184 | K14: =-Schedules!L40 -> -36404.426 | L14: =-Schedules!M40 -> -39451.054 | M14: =-Schedules!N40 -> -42785.642 | N14: =-Schedules!O40 -> -46437.601 | O14: =-Schedules!P40 -> -50676.547 | P14: =-Schedules!Q40 -> -55240.814 | Q14: =-Schedules!R40 -> -59931.067 | ... S14: =-Schedules!T40 -> -69553.008 | U14: =_xlfn.RRI(5,I14,N14) -> 0.087156682 | V14: =_xlfn.RRI(3,I14,L14) -> 0.08863722
B15: Gross Profit | D15: =SUM(D13:D14) -> 21524 | E15: =SUM(E13:E14) -> 24880 | F15: =SUM(F13:F14) -> 26711 | G15: =SUM(G13:G14) -> 28874 | H15: =SUM(H13:H14) -> 32076 | I15: =SUM(I13:I14) -> 32543 | J15: =SUM(J13:J14) -> 34991.396 | K15: =SUM(K13:K14) -> 38233.044 | ... S15: =SUM(S13:S14) -> 75047.84
B17: Less: SG&A (Excluding Depriciation & Interest)
B18: Employee Benefit Expenses | D18: =' Income Statement'!D33 -> -1820 | E18: =' Income Statement'!E33 -> -2358 | F18: =' Income Statement'!F33 -> -2545 | G18: =' Income Statement'!G33 -> -2854 | H18: =' Income Statement'!H33 -> -3009 | I18: =' Income Statement'!I33 -> -3077 | J18: =-Schedules!K51 -> -3293.3078 | K18: =-Schedules!L51 -> -3582.5986 | L18: =-Schedules!M51 -> -3900.4132 | M18: =-Schedules!N51 -> -4249.7895 | N18: =-Schedules!O51 -> -4634.1057 | O18: =-Schedules!P51 -> -5057.119 | P18: =-Schedules!Q51 -> -5512.5968 | Q18: =-Schedules!R51 -> -5980.647 | ... S18: =-Schedules!T51 -> -6940.8407 | U18: =_xlfn.RRI(5,I18,N18) -> 0.085344695 | V18: =_xlfn.RRI(3,I18,L18) -> 0.082250279
B19: Othere Expenses | D19: =' Income Statement'!D34 -> -9843 | E19: =' Income Statement'!E34 -> -10896 | F19: =' Income Statement'!F34 -> -11309 | G19: =' Income Statement'!G34 -> -11861 | H19: =' Income Statement'!H34 -> -14464 | I19: =' Income Statement'!I34 -> -14615 | J19: =-Schedules!K60 -> -15917.655 | K19: =-Schedules!L60 -> -17315.893 | L19: =-Schedules!M60 -> -18851.997 | M19: =-Schedules!N60 -> -20540.649 | N19: =-Schedules!O60 -> -22398.178 | O19: =-Schedules!P60 -> -24442.742 | P19: =-Schedules!Q60 -> -26644.218 | Q19: =-Schedules!R60 -> -28906.461 | ... S19: =-Schedules!T60 -> -33547.397 | U19: =_xlfn.RRI(5,I19,N19) -> 0.089137653 | V19: =_xlfn.RRI(3,I19,L19) -> 0.088561193
B20: Total SG&A | D20: =SUM(D18:D19) -> -11663 | E20: =SUM(E18:E19) -> -13254 | F20: =SUM(F18:F19) -> -13854 | G20: =SUM(G18:G19) -> -14715 | H20: =SUM(H18:H19) -> -17473 | I20: =SUM(I18:I19) -> -17692 | J20: =SUM(J18:J19) -> -19210.962 | K20: =SUM(K18:K19) -> -20898.492 | ... S20: =SUM(S18:S19) -> -40488.238
B22: EBITDA | D22: =D15+D20 -> 9861 | E22: =E15+E20 -> 11626 | F22: =F15+F20 -> 12857 | G22: =G15+G20 -> 14159 | H22: =H15+H20 -> 14603 | I22: =I15+I20 -> 14851 | J22: =J15+J20 -> 15780.433 | K22: =K15+K20 -> 17334.553 | ... S22: =S15+S20 -> 34559.603
B24: EBITDA Margins% | D24: =D22/D13 -> 0.24786969 | E24: =E22/E13 -> 0.24721443 | F24: =F22/F13 -> 0.24514739 | G24: =G22/G13 -> 0.23368543 | H24: =H22/H13 -> 0.23615693 | I24: =I22/I13 -> 0.23527828 | J24: =J22/J13 -> 0.23 | K24: =K22/K13 -> 0.23225 | ... S24: =S22/S13 -> 0.239
B27: Less: Depreciation & Amortization | D27: =' Income Statement'!D41 -> -1002 | E27: =Schedules!F146 -> -1074 | F27: =Schedules!G146 -> -1091 | G27: =Schedules!H146 -> -1137 | H27: =Schedules!I146 -> -1216 | I27: =Schedules!J146 -> -1355 | J27: =Schedules!K146 -> -1530.8597 | K27: =Schedules!L146 -> -1704.3912 | L27: =Schedules!M146 -> -1893.436 | ... S27: =Schedules!T146 -> -3776.3996 | U27: =_xlfn.RRI(5,I27,N27) -> 0.11397483 | V27: =_xlfn.RRI(3,I27,L27) -> 0.11798792
B28: Earnings Before Interest & Tax | D28: =SUM(D22,D27:D27) -> 8859 | E28: =SUM(E22,E27:E27) -> 10552 | F28: =SUM(F22,F27:F27) -> 11766 | G28: =SUM(G22,G27:G27) -> 13022 | H28: =SUM(H22,H27:H27) -> 13387 | I28: =SUM(I22,I27:I27) -> 13496 | J28: =SUM(J22,J27:J27) -> 14249.574 | K28: =SUM(K22,K27:K27) -> 15630.161 | ... S28: =SUM(S22,S27:S27) -> 30783.203
B30: EBIT Margins% | D30: =D28/D13 -> 0.22268306 | E30: =E28/E13 -> 0.22437697 | F30: =F28/F13 -> 0.22434504 | G30: =G28/G13 -> 0.21491995 | H30: =H28/H13 -> 0.21649201 | I30: =I28/I13 -> 0.21381157 | J30: =J28/J13 -> 0.2076877 | K30: =K28/K13 -> 0.2094144 | ... S30: =S28/S13 -> 0.21288397
B32: Less: Finance Costs | D32: =INDEX(' Income Statement'!$D$7:$I$62,MATCH('3Statement Model'!$B32,' Income Statement'!$B$7:$B$62,0),MATCH('3Statement Model'!D$9,' Income Statement'!$D$6:$I$6,)) -> -118 | E32: =INDEX(' Income Statement'!$D$7:$I$62,MATCH('3Statement Model'!$B32,' Income Statement'!$B$7:$B$62,0),MATCH('3Statement Model'!E$9,' Income Statement'!$D$6:$I$6,)) -> -117 | F32: =INDEX(' Income Statement'!$D$7:$I$62,MATCH('3Statement Model'!$B32,' Income Statement'!$B$7:$B$62,0),MATCH('3Statement Model'!F$9,' Income Statement'!$D$6:$I$6,)) -> -106 | G32: =INDEX(' Income Statement'!$D$7:$I$62,MATCH('3Statement Model'!$B32,' Income Statement'!$B$7:$B$62,0),MATCH('3Statement Model'!G$9,' Income Statement'!$D$6:$I$6,)) -> -114 | H32: =INDEX(' Income Statement'!$D$7:$I$62,MATCH('3Statement Model'!$B32,' Income Statement'!$B$7:$B$62,0),MATCH('3Statement Model'!H$9,' Income Statement'!$D$6:$I$6,)) -> -334 | I32: =INDEX(' Income Statement'!$D$7:$I$62,MATCH('3Statement Model'!$B32,' Income Statement'!$B$7:$B$62,0),MATCH('3Statement Model'!I$9,' Income Statement'!$D$6:$I$6,)) -> -395 | J32: =-Schedules!K202 -> -266.84209 | K32: =-Schedules!L202 -> -290.28203 | L32: =-Schedules!M202 -> -316.03314 | M32: =-Schedules!N202 -> -344.34155 | N32: =-Schedules!O202 -> -375.48098 | O32: =-Schedules!P202 -> -409.75587 | P32: =-Schedules!Q202 -> -446.66121 | Q32: =-Schedules!R202 -> -484.58524 | ... S32: =-Schedules!T202 -> -562.38546 | U32: =_xlfn.RRI(5,I32,N32) -> -0.010084397 | V32: =_xlfn.RRI(3,I32,L32) -> -0.071649785
B33: Add: Other Income | D33: =INDEX(' Income Statement'!$D$7:$I$62,MATCH('3Statement Model'!$B33,' Income Statement'!$B$7:$B$62,0),MATCH('3Statement Model'!D$9,' Income Statement'!$D$6:$I$6,)) -> 632 | E33: =INDEX(' Income Statement'!$D$7:$I$62,MATCH('3Statement Model'!$B33,' Income Statement'!$B$7:$B$62,0),MATCH('3Statement Model'!E$9,' Income Statement'!$D$6:$I$6,)) -> 410 | F33: =INDEX(' Income Statement'!$D$7:$I$62,MATCH('3Statement Model'!$B33,' Income Statement'!$B$7:$B$62,0),MATCH('3Statement Model'!F$9,' Income Statement'!$D$6:$I$6,)) -> 258 | G33: =INDEX(' Income Statement'!$D$7:$I$62,MATCH('3Statement Model'!$B33,' Income Statement'!$B$7:$B$62,0),MATCH('3Statement Model'!G$9,' Income Statement'!$D$6:$I$6,)) -> 512 | H33: =INDEX(' Income Statement'!$D$7:$I$62,MATCH('3Statement Model'!$B33,' Income Statement'!$B$7:$B$62,0),MATCH('3Statement Model'!H$9,' Income Statement'!$D$6:$I$6,)) -> 811 | I33: =INDEX(' Income Statement'!$D$7:$I$62,MATCH('3Statement Model'!$B33,' Income Statement'!$B$7:$B$62,0),MATCH('3Statement Model'!I$9,' Income Statement'!$D$6:$I$6,)) -> 1017 | J33: =Schedules!K32 -> 1017 | K33: =Schedules!L32 -> 1017 | L33: =Schedules!M32 -> 1017 | M33: =Schedules!N32 -> 1017 | N33: =Schedules!O32 -> 1017 | O33: =Schedules!P32 -> 1017 | P33: =Schedules!Q32 -> 1017 | Q33: =Schedules!R32 -> 1017 | ... S33: =Schedules!T32 -> 1017 | U33: =_xlfn.RRI(5,I33,N33) -> 0 | V33: =_xlfn.RRI(3,I33,L33) -> 0
B34: Add/(Less): Share Of Profit/Loss Of Associates | D34: =INDEX(' Income Statement'!$D$7:$I$62,MATCH('3Statement Model'!$B34,' Income Statement'!$B$7:$B$62,0),MATCH('3Statement Model'!D$9,' Income Statement'!$D$6:$I$6,)) -> 0 | E34: =INDEX(' Income Statement'!$D$7:$I$62,MATCH('3Statement Model'!$B34,' Income Statement'!$B$7:$B$62,0),MATCH('3Statement Model'!E$9,' Income Statement'!$D$6:$I$6,)) -> 0 | F34: =INDEX(' Income Statement'!$D$7:$I$62,MATCH('3Statement Model'!$B34,' Income Statement'!$B$7:$B$62,0),MATCH('3Statement Model'!F$9,' Income Statement'!$D$6:$I$6,)) -> 0 | G34: =INDEX(' Income Statement'!$D$7:$I$62,MATCH('3Statement Model'!$B34,' Income Statement'!$B$7:$B$62,0),MATCH('3Statement Model'!G$9,' Income Statement'!$D$6:$I$6,)) -> -1 | H34: =INDEX(' Income Statement'!$D$7:$I$62,MATCH('3Statement Model'!$B34,' Income Statement'!$B$7:$B$62,0),MATCH('3Statement Model'!H$9,' Income Statement'!$D$6:$I$6,)) -> -4 | I34: =INDEX(' Income Statement'!$D$7:$I$62,MATCH('3Statement Model'!$B34,' Income Statement'!$B$7:$B$62,0),MATCH('3Statement Model'!I$9,' Income Statement'!$D$6:$I$6,)) -> -8 | J34: 0 | K34: 0 | L34: 0 | M34: 0 | N34: 0 | O34: 0 | P34: 0 | Q34: 0 | R34: 0 | S34: 0
B35: Add/(Less): Exceptional Items | D35: =INDEX(' Income Statement'!$D$7:$I$62,MATCH('3Statement Model'!$B35,' Income Statement'!$B$7:$B$62,0),MATCH('3Statement Model'!D$9,' Income Statement'!$D$6:$I$6,)) -> -200 | E35: =INDEX(' Income Statement'!$D$7:$I$62,MATCH('3Statement Model'!$B35,' Income Statement'!$B$7:$B$62,0),MATCH('3Statement Model'!E$9,' Income Statement'!$D$6:$I$6,)) -> -239 | F35: =INDEX(' Income Statement'!$D$7:$I$62,MATCH('3Statement Model'!$B35,' Income Statement'!$B$7:$B$62,0),MATCH('3Statement Model'!F$9,' Income Statement'!$D$6:$I$6,)) -> -44 | G35: =INDEX(' Income Statement'!$D$7:$I$62,MATCH('3Statement Model'!$B35,' Income Statement'!$B$7:$B$62,0),MATCH('3Statement Model'!G$9,' Income Statement'!$D$6:$I$6,)) -> -64 | H35: =INDEX(' Income Statement'!$D$7:$I$62,MATCH('3Statement Model'!$B35,' Income Statement'!$B$7:$B$62,0),MATCH('3Statement Model'!H$9,' Income Statement'!$D$6:$I$6,)) -> 6 | I35: =INDEX(' Income Statement'!$D$7:$I$62,MATCH('3Statement Model'!$B35,' Income Statement'!$B$7:$B$62,0),MATCH('3Statement Model'!I$9,' Income Statement'!$D$6:$I$6,)) -> 305 | J35: 0 | K35: 0 | L35: 0 | M35: 0 | N35: 0 | O35: 0 | P35: 0 | Q35: 0 | R35: 0 | S35: 0
B37: Earnings Before Tax | D37: =SUM(D28,D32:D35) -> 9173 | E37: =SUM(E28,E32:E35) -> 10606 | F37: =SUM(F28,F32:F35) -> 11874 | G37: =SUM(G28,G32:G35) -> 13355 | H37: =SUM(H28,H32:H35) -> 13866 | I37: =SUM(I28,I32:I35) -> 14415 | J37: =SUM(J28,J32:J33) -> 14999.732 | K37: =SUM(K28,K32:K33) -> 16356.879 | L37: =SUM(L28,L32:L33) -> 17862.674 | M37: =SUM(M28,M32:M33) -> 19534.317 | N37: =SUM(N28,N32:N33) -> 21391.075 | O37: =SUM(O28,O32:O33) -> 23217.219 | P37: =SUM(P28,P32:P33) -> 25180.153 | Q37: =SUM(Q28,Q32:Q33) -> 27182.598 | ... S37: =SUM(S28,S32:S33) -> 31237.818
B39: Less: Tax Expenses | D39: =INDEX(' Income Statement'!$D$7:$I$62,MATCH('3Statement Model'!$B39,' Income Statement'!$B$7:$B$62,0),MATCH('3Statement Model'!D$9,' Income Statement'!$D$6:$I$6,)) -> -2409 | E39: =INDEX(' Income Statement'!$D$7:$I$62,MATCH('3Statement Model'!$B39,' Income Statement'!$B$7:$B$62,0),MATCH('3Statement Model'!E$9,' Income Statement'!$D$6:$I$6,)) -> -2606 | F39: =INDEX(' Income Statement'!$D$7:$I$62,MATCH('3Statement Model'!$B39,' Income Statement'!$B$7:$B$62,0),MATCH('3Statement Model'!F$9,' Income Statement'!$D$6:$I$6,)) -> -2987 | G39: =INDEX(' Income Statement'!$D$7:$I$62,MATCH('3Statement Model'!$B39,' Income Statement'!$B$7:$B$62,0),MATCH('3Statement Model'!G$9,' Income Statement'!$D$6:$I$6,)) -> -3201 | H39: =INDEX(' Income Statement'!$D$7:$I$62,MATCH('3Statement Model'!$B39,' Income Statement'!$B$7:$B$62,0),MATCH('3Statement Model'!H$9,' Income Statement'!$D$6:$I$6,)) -> -3644 | I39: =INDEX(' Income Statement'!$D$7:$I$62,MATCH('3Statement Model'!$B39,' Income Statement'!$B$7:$B$62,0),MATCH('3Statement Model'!I$9,' Income Statement'!$D$6:$I$6,)) -> -3744 | J39: =Schedules!K170 -> -4499.9195 | K39: =Schedules!L170 -> -4907.0638 | L39: =Schedules!M170 -> -5358.8023 | M39: =Schedules!N170 -> -5860.295 | N39: =Schedules!O170 -> -6417.3226 | O39: =Schedules!P170 -> -6965.1656 | P39: =Schedules!Q170 -> -7554.0458 | Q39: =Schedules!R170 -> -8154.7794 | ... S39: =Schedules!T170 -> -9371.3453 | U39: =_xlfn.RRI(5,I39,N39) -> 0.11379075 | V39: =_xlfn.RRI(3,I39,L39) -> 0.12696553
B40: Net Income | D40: =SUM(D37:D39) -> 6764 | E40: =SUM(E37:E39) -> 8000 | F40: =SUM(F37:F39) -> 8887 | G40: =SUM(G37:G39) -> 10154 | H40: =SUM(H37:H39) -> 10222 | I40: =SUM(I37:I39) -> 10671 | J40: =SUM(J37:J39) -> 10499.812 | K40: =SUM(K37:K39) -> 11449.815 | ... S40: =SUM(S37:S39) -> 21866.472
B42: Sales Growth % | G42: =IFERROR(G13/F13-1,"NM") -> 0.15528353 | H42: =IFERROR(H13/G13-1,"NM") -> 0.02056445 | I42: =IFERROR(I13/H13-1,"NM") -> 0.020780775 | J42: =IFERROR(J13/I13-1,"NM") -> 0.086969154 | K42: =IFERROR(K13/J13-1,"NM") -> 0.087841998 | L42: =IFERROR(L13/K13-1,"NM") -> 0.088710637 | M42: =IFERROR(M13/L13-1,"NM") -> 0.089574194 | N42: =IFERROR(N13/M13-1,"NM") -> 0.090431806 | ... S42: =IFERROR(S13/R13-1,"NM") -> 0.074792631
B43: Gross Profit Margins % | G43: =G15/G13 -> 0.47654729 | H43: =H15/H13 -> 0.51872696 | I43: =I15/I13 -> 0.51556534 | J43: =J15/J13 -> 0.51 | K43: =K15/K13 -> 0.51225 | L43: =L15/L13 -> 0.5145 | M43: =M15/M13 -> 0.51675 | N43: =N15/N13 -> 0.519 | ... S43: =S15/S13 -> 0.519
B44: EBITDA Margins % | G44: =G22/G13 -> 0.23368543 | H44: =H22/H13 -> 0.23615693 | I44: =I22/I13 -> 0.23527828 | J44: =J22/J13 -> 0.23 | K44: =K22/K13 -> 0.23225 | L44: =L22/L13 -> 0.2345 | M44: =M22/M13 -> 0.23675 | N44: =N22/N13 -> 0.239 | ... S44: =S22/S13 -> 0.239
B45: EBIT Margins % | G45: =G28/G13 -> 0.21491995 | H45: =H28/H13 -> 0.21649201 | I45: =I28/I13 -> 0.21381157 | J45: =J28/J13 -> 0.2076877 | K45: =K28/K13 -> 0.2094144 | L45: =L28/L13 -> 0.21119864 | M45: =M28/M13 -> 0.21303634 | N45: =N28/N13 -> 0.2149236 | ... S45: =S28/S13 -> 0.21288397
B46: Actual Tax Rate % | G46: =-G39/G37 -> 0.23968551 | H46: =-H39/H37 -> 0.2628011 | I46: =-I39/I37 -> 0.25972945 | J46: =-J39/J37 -> 0.3 | K46: =-K39/K37 -> 0.3 | L46: =-L39/L37 -> 0.3 | M46: =-M39/M37 -> 0.3 | N46: =-N39/N37 -> 0.3 | ... S46: =-S39/S37 -> 0.3
B47: Net Income Margin % | G47: =G40/G13 -> 0.16758541 | H47: =H40/H13 -> 0.16530823 | I47: =I40/I13 -> 0.16905626 | J47: =J40/J13 -> 0.15303488 | K47: =K40/K13 -> 0.15340573 | L47: =L40/L13 -> 0.15387751 | M47: =M40/M13 -> 0.15444366 | N47: =N40/N13 -> 0.15509791 | ... S47: =S40/S13 -> 0.15121953
A49: # | B49: Balance Sheet
B51: EQUITIES AND LIABILITIES
B52: SHAREHOLDER'S FUNDS
B53: Equity Share Capital | D53: =INDEX('Balance Sheet'!$D$9:$I$65,MATCH('3Statement Model'!$B53,'Balance Sheet'!$B$9:$B$65,0),MATCH('3Statement Model'!D$9,'Balance Sheet'!$D$6:$I$6,0)) -> 216 | E53: =INDEX('Balance Sheet'!$D$9:$I$65,MATCH('3Statement Model'!$B53,'Balance Sheet'!$B$9:$B$65,0),MATCH('3Statement Model'!E$9,'Balance Sheet'!$D$6:$I$6,0)) -> 235 | F53: =INDEX('Balance Sheet'!$D$9:$I$65,MATCH('3Statement Model'!$B53,'Balance Sheet'!$B$9:$B$65,0),MATCH('3Statement Model'!F$9,'Balance Sheet'!$D$6:$I$6,0)) -> 235 | G53: =INDEX('Balance Sheet'!$D$9:$I$65,MATCH('3Statement Model'!$B53,'Balance Sheet'!$B$9:$B$65,0),MATCH('3Statement Model'!G$9,'Balance Sheet'!$D$6:$I$6,0)) -> 235 | H53: =INDEX('Balance Sheet'!$D$9:$I$65,MATCH('3Statement Model'!$B53,'Balance Sheet'!$B$9:$B$65,0),MATCH('3Statement Model'!H$9,'Balance Sheet'!$D$6:$I$6,0)) -> 235 | I53: =INDEX('Balance Sheet'!$D$9:$I$65,MATCH('3Statement Model'!$B53,'Balance Sheet'!$B$9:$B$65,0),MATCH('3Statement Model'!I$9,'Balance Sheet'!$D$6:$I$6,0)) -> 235 | J53: =I53 -> 235 | K53: =J53 -> 235 | L53: =K53 -> 235 | M53: =L53 -> 235 | N53: =M53 -> 235 | O53: =N53 -> 235 | P53: =O53 -> 235 | Q53: =P53 -> 235 | ... S53: =R53 -> 235 | U53: =_xlfn.RRI(5,I53,N53) -> 0 | V53: =_xlfn.RRI(3,I53,L53) -> 0
B54: Other Equity | D54: =INDEX('Balance Sheet'!$D$9:$I$65,MATCH('3Statement Model'!$B54,'Balance Sheet'!$B$9:$B$65,0),MATCH('3Statement Model'!D$9,'Balance Sheet'!$D$6:$I$6,0)) -> 8013 | E54: =INDEX('Balance Sheet'!$D$9:$I$65,MATCH('3Statement Model'!$B54,'Balance Sheet'!$B$9:$B$65,0),MATCH('3Statement Model'!E$9,'Balance Sheet'!$D$6:$I$6,0)) -> 47439 | F54: =INDEX('Balance Sheet'!$D$9:$I$65,MATCH('3Statement Model'!$B54,'Balance Sheet'!$B$9:$B$65,0),MATCH('3Statement Model'!F$9,'Balance Sheet'!$D$6:$I$6,0)) -> 48826 | G54: =INDEX('Balance Sheet'!$D$9:$I$65,MATCH('3Statement Model'!$B54,'Balance Sheet'!$B$9:$B$65,0),MATCH('3Statement Model'!G$9,'Balance Sheet'!$D$6:$I$6,0)) -> 50069 | H54: =INDEX('Balance Sheet'!$D$9:$I$65,MATCH('3Statement Model'!$B54,'Balance Sheet'!$B$9:$B$65,0),MATCH('3Statement Model'!H$9,'Balance Sheet'!$D$6:$I$6,0)) -> 50983 | I54: =INDEX('Balance Sheet'!$D$9:$I$65,MATCH('3Statement Model'!$B54,'Balance Sheet'!$B$9:$B$65,0),MATCH('3Statement Model'!I$9,'Balance Sheet'!$D$6:$I$6,0)) -> 49167 | J54: =Schedules!K209 -> 50216.981 | K54: =Schedules!L209 -> 51132.966 | L54: =Schedules!M209 -> 51883.199 | M54: =Schedules!N209 -> 52430.16 | N54: =Schedules!O209 -> 52729.635 | O54: =Schedules!P209 -> 52729.635 | P54: =Schedules!Q209 -> 52377.113 | Q54: =Schedules!R209 -> 51616 | ... S54: =Schedules!T209 -> 48639.973 | U54: =_xlfn.RRI(5,I54,N54) -> 0.014089324 | V54: =_xlfn.RRI(3,I54,L54) -> 0.018085717
B55: Total Share Holder's Equity | D55: =INDEX('Balance Sheet'!$D$9:$I$65,MATCH('3Statement Model'!$B55,'Balance Sheet'!$B$9:$B$65,0),MATCH('3Statement Model'!D$9,'Balance Sheet'!$D$6:$I$6,0)) -> 8229 | E55: =INDEX('Balance Sheet'!$D$9:$I$65,MATCH('3Statement Model'!$B55,'Balance Sheet'!$B$9:$B$65,0),MATCH('3Statement Model'!E$9,'Balance Sheet'!$D$6:$I$6,0)) -> 47674 | F55: =INDEX('Balance Sheet'!$D$9:$I$65,MATCH('3Statement Model'!$B55,'Balance Sheet'!$B$9:$B$65,0),MATCH('3Statement Model'!F$9,'Balance Sheet'!$D$6:$I$6,0)) -> 49061 | G55: =INDEX('Balance Sheet'!$D$9:$I$65,MATCH('3Statement Model'!$B55,'Balance Sheet'!$B$9:$B$65,0),MATCH('3Statement Model'!G$9,'Balance Sheet'!$D$6:$I$6,0)) -> 50304 | H55: =INDEX('Balance Sheet'!$D$9:$I$65,MATCH('3Statement Model'!$B55,'Balance Sheet'!$B$9:$B$65,0),MATCH('3Statement Model'!H$9,'Balance Sheet'!$D$6:$I$6,0)) -> 51218 | I55: =INDEX('Balance Sheet'!$D$9:$I$65,MATCH('3Statement Model'!$B55,'Balance Sheet'!$B$9:$B$65,0),MATCH('3Statement Model'!I$9,'Balance Sheet'!$D$6:$I$6,0)) -> 49402 | J55: =SUM(J53:J54) -> 50451.981 | K55: =SUM(K53:K54) -> 51367.966 | L55: =SUM(L53:L54) -> 52118.199 | M55: =SUM(M53:M54) -> 52665.16 | N55: =SUM(N53:N54) -> 52964.635 | O55: =SUM(O53:O54) -> 52964.635 | P55: =SUM(P53:P54) -> 52612.113 | Q55: =SUM(Q53:Q54) -> 51851 | ... S55: =SUM(S53:S54) -> 48874.973 | U55: =_xlfn.RRI(5,I55,N55) -> 0.014024131 | V55: =_xlfn.RRI(3,I55,L55) -> 0.018001197
B56: Minority Interest | D56: =INDEX('Balance Sheet'!$D$9:$I$65,MATCH('3Statement Model'!$B56,'Balance Sheet'!$B$9:$B$65,0),MATCH('3Statement Model'!D$9,'Balance Sheet'!$D$6:$I$6,0)) -> 17 | E56: =INDEX('Balance Sheet'!$D$9:$I$65,MATCH('3Statement Model'!$B56,'Balance Sheet'!$B$9:$B$65,0),MATCH('3Statement Model'!E$9,'Balance Sheet'!$D$6:$I$6,0)) -> 20 | F56: =INDEX('Balance Sheet'!$D$9:$I$65,MATCH('3Statement Model'!$B56,'Balance Sheet'!$B$9:$B$65,0),MATCH('3Statement Model'!F$9,'Balance Sheet'!$D$6:$I$6,0)) -> 26 | G56: =INDEX('Balance Sheet'!$D$9:$I$65,MATCH('3Statement Model'!$B56,'Balance Sheet'!$B$9:$B$65,0),MATCH('3Statement Model'!G$9,'Balance Sheet'!$D$6:$I$6,0)) -> 218 | H56: =INDEX('Balance Sheet'!$D$9:$I$65,MATCH('3Statement Model'!$B56,'Balance Sheet'!$B$9:$B$65,0),MATCH('3Statement Model'!H$9,'Balance Sheet'!$D$6:$I$6,0)) -> 205 | I56: =INDEX('Balance Sheet'!$D$9:$I$65,MATCH('3Statement Model'!$B56,'Balance Sheet'!$B$9:$B$65,0),MATCH('3Statement Model'!I$9,'Balance Sheet'!$D$6:$I$6,0)) -> 207 | J56: =I56 -> 207 | K56: =J56 -> 207 | L56: =K56 -> 207 | M56: =L56 -> 207 | N56: =M56 -> 207 | O56: =N56 -> 207 | P56: =O56 -> 207 | Q56: =P56 -> 207 | ... S56: =R56 -> 207 | U56: =_xlfn.RRI(5,I56,N56) -> 0 | V56: =_xlfn.RRI(3,I56,L56) -> 0
B57: Total Equity | D57: =INDEX('Balance Sheet'!$D$9:$I$65,MATCH('3Statement Model'!$B57,'Balance Sheet'!$B$9:$B$65,0),MATCH('3Statement Model'!D$9,'Balance Sheet'!$D$6:$I$6,0)) -> 8246 | E57: =INDEX('Balance Sheet'!$D$9:$I$65,MATCH('3Statement Model'!$B57,'Balance Sheet'!$B$9:$B$65,0),MATCH('3Statement Model'!E$9,'Balance Sheet'!$D$6:$I$6,0)) -> 47694 | F57: =INDEX('Balance Sheet'!$D$9:$I$65,MATCH('3Statement Model'!$B57,'Balance Sheet'!$B$9:$B$65,0),MATCH('3Statement Model'!F$9,'Balance Sheet'!$D$6:$I$6,0)) -> 49087 | G57: =INDEX('Balance Sheet'!$D$9:$I$65,MATCH('3Statement Model'!$B57,'Balance Sheet'!$B$9:$B$65,0),MATCH('3Statement Model'!G$9,'Balance Sheet'!$D$6:$I$6,0)) -> 50522 | H57: =INDEX('Balance Sheet'!$D$9:$I$65,MATCH('3Statement Model'!$B57,'Balance Sheet'!$B$9:$B$65,0),MATCH('3Statement Model'!H$9,'Balance Sheet'!$D$6:$I$6,0)) -> 51423 | I57: =INDEX('Balance Sheet'!$D$9:$I$65,MATCH('3Statement Model'!$B57,'Balance Sheet'!$B$9:$B$65,0),MATCH('3Statement Model'!I$9,'Balance Sheet'!$D$6:$I$6,0)) -> 49609 | J57: =SUM(J55:J56) -> 50658.981 | K57: =SUM(K55:K56) -> 51574.966 | L57: =SUM(L55:L56) -> 52325.199 | M57: =SUM(M55:M56) -> 52872.16 | N57: =SUM(N55:N56) -> 53171.635 | O57: =SUM(O55:O56) -> 53171.635 | P57: =SUM(P55:P56) -> 52819.113 | Q57: =SUM(Q55:Q56) -> 52058 | ... S57: =SUM(S55:S56) -> 49081.973
B59: NON-CURRENT LIABILITIES
B60: Financial Liabilities
B61: Lease Liabilities (L) | D61: =INDEX('Balance Sheet'!$D$9:$I$65,MATCH('3Statement Model'!$B61,'Balance Sheet'!$B$9:$B$65,0),MATCH('3Statement Model'!D$9,'Balance Sheet'!$D$6:$I$6,0)) -> 0 | E61: =INDEX('Balance Sheet'!$D$9:$I$65,MATCH('3Statement Model'!$B61,'Balance Sheet'!$B$9:$B$65,0),MATCH('3Statement Model'!E$9,'Balance Sheet'!$D$6:$I$6,0)) -> 0 | F61: =INDEX('Balance Sheet'!$D$9:$I$65,MATCH('3Statement Model'!$B61,'Balance Sheet'!$B$9:$B$65,0),MATCH('3Statement Model'!F$9,'Balance Sheet'!$D$6:$I$6,0)) -> 741 | G61: =INDEX('Balance Sheet'!$D$9:$I$65,MATCH('3Statement Model'!$B61,'Balance Sheet'!$B$9:$B$65,0),MATCH('3Statement Model'!G$9,'Balance Sheet'!$D$6:$I$6,0)) -> 807 | H61: =INDEX('Balance Sheet'!$D$9:$I$65,MATCH('3Statement Model'!$B61,'Balance Sheet'!$B$9:$B$65,0),MATCH('3Statement Model'!H$9,'Balance Sheet'!$D$6:$I$6,0)) -> 1106 | I61: =INDEX('Balance Sheet'!$D$9:$I$65,MATCH('3Statement Model'!$B61,'Balance Sheet'!$B$9:$B$65,0),MATCH('3Statement Model'!I$9,'Balance Sheet'!$D$6:$I$6,0)) -> 1243 | J61: =Schedules!K177 -> 1372.2116 | K61: =Schedules!L177 -> 1492.7494 | L61: =Schedules!M177 -> 1625.1722 | M61: =Schedules!N177 -> 1770.7456 | N61: =Schedules!O177 -> 1930.8774 | O61: =Schedules!P177 -> 2107.1329 | P61: =Schedules!Q177 -> 2296.9153 | Q61: =Schedules!R177 -> 2491.9363 | ... S61: =Schedules!T177 -> 2892.017 | U61: =_xlfn.RRI(5,I61,N61) -> 0.092085681 | V61: =_xlfn.RRI(3,I61,L61) -> 0.093476402
B62: Other Financial Liabilities (L) | D62: =INDEX('Balance Sheet'!$D$9:$I$65,MATCH('3Statement Model'!$B62,'Balance Sheet'!$B$9:$B$65,0),MATCH('3Statement Model'!D$9,'Balance Sheet'!$D$6:$I$6,0)) -> 939 | E62: =INDEX('Balance Sheet'!$D$9:$I$65,MATCH('3Statement Model'!$B62,'Balance Sheet'!$B$9:$B$65,0),MATCH('3Statement Model'!E$9,'Balance Sheet'!$D$6:$I$6,0)) -> 1027 | F62: =INDEX('Balance Sheet'!$D$9:$I$65,MATCH('3Statement Model'!$B62,'Balance Sheet'!$B$9:$B$65,0),MATCH('3Statement Model'!F$9,'Balance Sheet'!$D$6:$I$6,0)) -> 357 | G62: =INDEX('Balance Sheet'!$D$9:$I$65,MATCH('3Statement Model'!$B62,'Balance Sheet'!$B$9:$B$65,0),MATCH('3Statement Model'!G$9,'Balance Sheet'!$D$6:$I$6,0)) -> 860 | H62: =INDEX('Balance Sheet'!$D$9:$I$65,MATCH('3Statement Model'!$B62,'Balance Sheet'!$B$9:$B$65,0),MATCH('3Statement Model'!H$9,'Balance Sheet'!$D$6:$I$6,0)) -> 715 | I62: =INDEX('Balance Sheet'!$D$9:$I$65,MATCH('3Statement Model'!$B62,'Balance Sheet'!$B$9:$B$65,0),MATCH('3Statement Model'!I$9,'Balance Sheet'!$D$6:$I$6,0)) -> 680 | J62: =I62 -> 680 | K62: =J62 -> 680 | L62: =K62 -> 680 | M62: =L62 -> 680 | N62: =M62 -> 680 | O62: =N62 -> 680 | P62: =O62 -> 680 | Q62: =P62 -> 680 | ... S62: =R62 -> 680 | U62: =_xlfn.RRI(5,I62,N62) -> 0 | V62: =_xlfn.RRI(3,I62,L62) -> 0
B63: Provisions (L) | D63: =INDEX('Balance Sheet'!$D$9:$I$65,MATCH('3Statement Model'!$B63,'Balance Sheet'!$B$9:$B$65,0),MATCH('3Statement Model'!D$9,'Balance Sheet'!$D$6:$I$6,0)) -> 1227 | E63: =INDEX('Balance Sheet'!$D$9:$I$65,MATCH('3Statement Model'!$B63,'Balance Sheet'!$B$9:$B$65,0),MATCH('3Statement Model'!E$9,'Balance Sheet'!$D$6:$I$6,0)) -> 1578 | F63: =INDEX('Balance Sheet'!$D$9:$I$65,MATCH('3Statement Model'!$B63,'Balance Sheet'!$B$9:$B$65,0),MATCH('3Statement Model'!F$9,'Balance Sheet'!$D$6:$I$6,0)) -> 1580 | G63: =INDEX('Balance Sheet'!$D$9:$I$65,MATCH('3Statement Model'!$B63,'Balance Sheet'!$B$9:$B$65,0),MATCH('3Statement Model'!G$9,'Balance Sheet'!$D$6:$I$6,0)) -> 1363 | H63: =INDEX('Balance Sheet'!$D$9:$I$65,MATCH('3Statement Model'!$B63,'Balance Sheet'!$B$9:$B$65,0),MATCH('3Statement Model'!H$9,'Balance Sheet'!$D$6:$I$6,0)) -> 1576 | I63: =INDEX('Balance Sheet'!$D$9:$I$65,MATCH('3Statement Model'!$B63,'Balance Sheet'!$B$9:$B$65,0),MATCH('3Statement Model'!I$9,'Balance Sheet'!$D$6:$I$6,0)) -> 1528 | J63: =I63 -> 1528 | K63: =J63 -> 1528 | L63: =K63 -> 1528 | M63: =L63 -> 1528 | N63: =M63 -> 1528 | O63: =N63 -> 1528 | P63: =O63 -> 1528 | Q63: =P63 -> 1528 | ... S63: =R63 -> 1528 | U63: =_xlfn.RRI(5,I63,N63) -> 0 | V63: =_xlfn.RRI(5,J63,T63) -> -1
B64: Deferred Tax Liabilities [Net] | D64: =INDEX('Balance Sheet'!$D$9:$I$65,MATCH('3Statement Model'!$B64,'Balance Sheet'!$B$9:$B$65,0),MATCH('3Statement Model'!D$9,'Balance Sheet'!$D$6:$I$6,0)) -> 0 | E64: =INDEX('Balance Sheet'!$D$9:$I$65,MATCH('3Statement Model'!$B64,'Balance Sheet'!$B$9:$B$65,0),MATCH('3Statement Model'!E$9,'Balance Sheet'!$D$6:$I$6,0)) -> 5988 | F64: =INDEX('Balance Sheet'!$D$9:$I$65,MATCH('3Statement Model'!$B64,'Balance Sheet'!$B$9:$B$65,0),MATCH('3Statement Model'!F$9,'Balance Sheet'!$D$6:$I$6,0)) -> 6141 | G64: =INDEX('Balance Sheet'!$D$9:$I$65,MATCH('3Statement Model'!$B64,'Balance Sheet'!$B$9:$B$65,0),MATCH('3Statement Model'!G$9,'Balance Sheet'!$D$6:$I$6,0)) -> 6421 | H64: =INDEX('Balance Sheet'!$D$9:$I$65,MATCH('3Statement Model'!$B64,'Balance Sheet'!$B$9:$B$65,0),MATCH('3Statement Model'!H$9,'Balance Sheet'!$D$6:$I$6,0)) -> 6557 | I64: =INDEX('Balance Sheet'!$D$9:$I$65,MATCH('3Statement Model'!$B64,'Balance Sheet'!$B$9:$B$65,0),MATCH('3Statement Model'!I$9,'Balance Sheet'!$D$6:$I$6,0)) -> 6685 | J64: =I64 -> 6685 | K64: =J64 -> 6685 | L64: =K64 -> 6685 | M64: =L64 -> 6685 | N64: =M64 -> 6685 | O64: =N64 -> 6685 | P64: =O64 -> 6685 | Q64: =P64 -> 6685 | ... S64: =R64 -> 6685 | U64: =_xlfn.RRI(5,I64,N64) -> 0 | V64: =_xlfn.RRI(5,J64,T64) -> -1
B65: Non-Current Tax Liabities (Net) | D65: =INDEX('Balance Sheet'!$D$9:$I$65,MATCH('3Statement Model'!$B65,'Balance Sheet'!$B$9:$B$65,0),MATCH('3Statement Model'!D$9,'Balance Sheet'!$D$6:$I$6,0)) -> 424 | E65: =INDEX('Balance Sheet'!$D$9:$I$65,MATCH('3Statement Model'!$B65,'Balance Sheet'!$B$9:$B$65,0),MATCH('3Statement Model'!E$9,'Balance Sheet'!$D$6:$I$6,0)) -> 1367 | F65: =INDEX('Balance Sheet'!$D$9:$I$65,MATCH('3Statement Model'!$B65,'Balance Sheet'!$B$9:$B$65,0),MATCH('3Statement Model'!F$9,'Balance Sheet'!$D$6:$I$6,0)) -> 1331 | G65: =INDEX('Balance Sheet'!$D$9:$I$65,MATCH('3Statement Model'!$B65,'Balance Sheet'!$B$9:$B$65,0),MATCH('3Statement Model'!G$9,'Balance Sheet'!$D$6:$I$6,0)) -> 1086 | H65: =INDEX('Balance Sheet'!$D$9:$I$65,MATCH('3Statement Model'!$B65,'Balance Sheet'!$B$9:$B$65,0),MATCH('3Statement Model'!H$9,'Balance Sheet'!$D$6:$I$6,0)) -> 4243 | I65: =INDEX('Balance Sheet'!$D$9:$I$65,MATCH('3Statement Model'!$B65,'Balance Sheet'!$B$9:$B$65,0),MATCH('3Statement Model'!I$9,'Balance Sheet'!$D$6:$I$6,0)) -> 3598 | J65: =I65 -> 3598 | K65: =J65 -> 3598 | L65: =K65 -> 3598 | M65: =L65 -> 3598 | N65: =M65 -> 3598 | O65: =N65 -> 3598 | P65: =O65 -> 3598 | Q65: =P65 -> 3598 | ... S65: =R65 -> 3598 | U65: =_xlfn.RRI(5,I65,N65) -> 0 | V65: =_xlfn.RRI(5,J65,T65) -> -1
B66: Total Non-Current Liabilities | D66: =INDEX('Balance Sheet'!$D$9:$I$65,MATCH('3Statement Model'!$B66,'Balance Sheet'!$B$9:$B$65,0),MATCH('3Statement Model'!D$9,'Balance Sheet'!$D$6:$I$6,0)) -> 2590 | E66: =INDEX('Balance Sheet'!$D$9:$I$65,MATCH('3Statement Model'!$B66,'Balance Sheet'!$B$9:$B$65,0),MATCH('3Statement Model'!E$9,'Balance Sheet'!$D$6:$I$6,0)) -> 9960 | F66: =INDEX('Balance Sheet'!$D$9:$I$65,MATCH('3Statement Model'!$B66,'Balance Sheet'!$B$9:$B$65,0),MATCH('3Statement Model'!F$9,'Balance Sheet'!$D$6:$I$6,0)) -> 10150 | G66: =INDEX('Balance Sheet'!$D$9:$I$65,MATCH('3Statement Model'!$B66,'Balance Sheet'!$B$9:$B$65,0),MATCH('3Statement Model'!G$9,'Balance Sheet'!$D$6:$I$6,0)) -> 10537 | H66: =INDEX('Balance Sheet'!$D$9:$I$65,MATCH('3Statement Model'!$B66,'Balance Sheet'!$B$9:$B$65,0),MATCH('3Statement Model'!H$9,'Balance Sheet'!$D$6:$I$6,0)) -> 14197 | I66: =INDEX('Balance Sheet'!$D$9:$I$65,MATCH('3Statement Model'!$B66,'Balance Sheet'!$B$9:$B$65,0),MATCH('3Statement Model'!I$9,'Balance Sheet'!$D$6:$I$6,0)) -> 13734 | J66: =SUM(J61:J65) -> 13863.212 | K66: =SUM(K61:K65) -> 13983.749 | L66: =SUM(L61:L65) -> 14116.172 | M66: =SUM(M61:M65) -> 14261.746 | N66: =SUM(N61:N65) -> 14421.877 | O66: =SUM(O61:O65) -> 14598.133 | P66: =SUM(P61:P65) -> 14787.915 | Q66: =SUM(Q61:Q65) -> 14982.936 | ... S66: =SUM(S61:S65) -> 15383.017 | U66: =_xlfn.RRI(5,I66,N66) -> 0.0098222862
B68: CURRENT LIABILITIES
B69: Financial Liabilities | U69: =_xlfn.RRI(5,I69,N69) -> 0 | V69: =_xlfn.RRI(3,I69,L69) -> 0
B70: Short Term Borrowings | D70: =INDEX('Balance Sheet'!$D$9:$I$65,MATCH('3Statement Model'!$B70,'Balance Sheet'!$B$9:$B$65,0),MATCH('3Statement Model'!D$9,'Balance Sheet'!$D$6:$I$6,0)) -> 0 | E70: =INDEX('Balance Sheet'!$D$9:$I$65,MATCH('3Statement Model'!$B70,'Balance Sheet'!$B$9:$B$65,0),MATCH('3Statement Model'!E$9,'Balance Sheet'!$D$6:$I$6,0)) -> 0 | F70: =INDEX('Balance Sheet'!$D$9:$I$65,MATCH('3Statement Model'!$B70,'Balance Sheet'!$B$9:$B$65,0),MATCH('3Statement Model'!F$9,'Balance Sheet'!$D$6:$I$6,0)) -> 0 | G70: =INDEX('Balance Sheet'!$D$9:$I$65,MATCH('3Statement Model'!$B70,'Balance Sheet'!$B$9:$B$65,0),MATCH('3Statement Model'!G$9,'Balance Sheet'!$D$6:$I$6,0)) -> 98 | H70: =INDEX('Balance Sheet'!$D$9:$I$65,MATCH('3Statement Model'!$B70,'Balance Sheet'!$B$9:$B$65,0),MATCH('3Statement Model'!H$9,'Balance Sheet'!$D$6:$I$6,0)) -> 13 | I70: =INDEX('Balance Sheet'!$D$9:$I$65,MATCH('3Statement Model'!$B70,'Balance Sheet'!$B$9:$B$65,0),MATCH('3Statement Model'!I$9,'Balance Sheet'!$D$6:$I$6,0)) -> 1 | J70: =Schedules!K248 -> 0 | K70: =Schedules!L248 -> 0 | L70: =Schedules!M248 -> 0 | M70: =Schedules!N248 -> 0 | N70: =Schedules!O248 -> 0 | O70: =Schedules!P248 -> 0 | P70: =Schedules!Q248 -> 0 | Q70: =Schedules!R248 -> 0 | ... S70: =Schedules!T248 -> 0 | U70: =_xlfn.RRI(5,I70,N70) -> -1 | V70: =_xlfn.RRI(3,I70,L70) -> -1
B71: Lease Liabilities (S) | D71: =INDEX('Balance Sheet'!$D$9:$I$65,MATCH('3Statement Model'!$B71,'Balance Sheet'!$B$9:$B$65,0),MATCH('3Statement Model'!D$9,'Balance Sheet'!$D$6:$I$6,0)) -> 0 | E71: =INDEX('Balance Sheet'!$D$9:$I$65,MATCH('3Statement Model'!$B71,'Balance Sheet'!$B$9:$B$65,0),MATCH('3Statement Model'!E$9,'Balance Sheet'!$D$6:$I$6,0)) -> 0 | F71: =INDEX('Balance Sheet'!$D$9:$I$65,MATCH('3Statement Model'!$B71,'Balance Sheet'!$B$9:$B$65,0),MATCH('3Statement Model'!F$9,'Balance Sheet'!$D$6:$I$6,0)) -> 302 | G71: =INDEX('Balance Sheet'!$D$9:$I$65,MATCH('3Statement Model'!$B71,'Balance Sheet'!$B$9:$B$65,0),MATCH('3Statement Model'!G$9,'Balance Sheet'!$D$6:$I$6,0)) -> 314 | H71: =INDEX('Balance Sheet'!$D$9:$I$65,MATCH('3Statement Model'!$B71,'Balance Sheet'!$B$9:$B$65,0),MATCH('3Statement Model'!H$9,'Balance Sheet'!$D$6:$I$6,0)) -> 365 | I71: =INDEX('Balance Sheet'!$D$9:$I$65,MATCH('3Statement Model'!$B71,'Balance Sheet'!$B$9:$B$65,0),MATCH('3Statement Model'!I$9,'Balance Sheet'!$D$6:$I$6,0)) -> 404 | J71: =Schedules!K179 -> 686.1058 | K71: =Schedules!L179 -> 746.3747 | L71: =Schedules!M179 -> 812.58608 | M71: =Schedules!N179 -> 885.37282 | N71: =Schedules!O179 -> 965.43869 | O71: =Schedules!P179 -> 1053.5665 | P71: =Schedules!Q179 -> 1148.4577 | Q71: =Schedules!R179 -> 1245.9681 | ... S71: =Schedules!T179 -> 1446.0085 | U71: =_xlfn.RRI(5,I71,N71) -> 0.19033353 | V71: =_xlfn.RRI(3,I71,L71) -> 0.26230026
B72: Trade Payables | D72: =INDEX('Balance Sheet'!$D$9:$I$65,MATCH('3Statement Model'!$B72,'Balance Sheet'!$B$9:$B$65,0),MATCH('3Statement Model'!D$9,'Balance Sheet'!$D$6:$I$6,0)) -> 7535 | E72: =INDEX('Balance Sheet'!$D$9:$I$65,MATCH('3Statement Model'!$B72,'Balance Sheet'!$B$9:$B$65,0),MATCH('3Statement Model'!E$9,'Balance Sheet'!$D$6:$I$6,0)) -> 8802 | F72: =INDEX('Balance Sheet'!$D$9:$I$65,MATCH('3Statement Model'!$B72,'Balance Sheet'!$B$9:$B$65,0),MATCH('3Statement Model'!F$9,'Balance Sheet'!$D$6:$I$6,0)) -> 9068 | G72: =INDEX('Balance Sheet'!$D$9:$I$65,MATCH('3Statement Model'!$B72,'Balance Sheet'!$B$9:$B$65,0),MATCH('3Statement Model'!G$9,'Balance Sheet'!$D$6:$I$6,0)) -> 9574 | H72: =INDEX('Balance Sheet'!$D$9:$I$65,MATCH('3Statement Model'!$B72,'Balance Sheet'!$B$9:$B$65,0),MATCH('3Statement Model'!H$9,'Balance Sheet'!$D$6:$I$6,0)) -> 10486 | I72: =INDEX('Balance Sheet'!$D$9:$I$65,MATCH('3Statement Model'!$B72,'Balance Sheet'!$B$9:$B$65,0),MATCH('3Statement Model'!I$9,'Balance Sheet'!$D$6:$I$6,0)) -> 11315 | J72: =Schedules!K253 -> 14737.177 | K72: =Schedules!L253 -> 15958.105 | L72: =Schedules!M253 -> 17293.613 | M72: =Schedules!N253 -> 18755.35 | N72: =Schedules!O253 -> 20356.209 | O72: =Schedules!P253 -> 22214.377 | P72: =Schedules!Q253 -> 24215.151 | Q72: =Schedules!R253 -> 26271.153 | ... S72: =Schedules!T253 -> 30488.99
B73: Other Financial Liabilities (S) | D73: =INDEX('Balance Sheet'!$D$9:$I$65,MATCH('3Statement Model'!$B73,'Balance Sheet'!$B$9:$B$65,0),MATCH('3Statement Model'!D$9,'Balance Sheet'!$D$6:$I$6,0)) -> 932 | E73: =INDEX('Balance Sheet'!$D$9:$I$65,MATCH('3Statement Model'!$B73,'Balance Sheet'!$B$9:$B$65,0),MATCH('3Statement Model'!E$9,'Balance Sheet'!$D$6:$I$6,0)) -> 1206 | F73: =INDEX('Balance Sheet'!$D$9:$I$65,MATCH('3Statement Model'!$B73,'Balance Sheet'!$B$9:$B$65,0),MATCH('3Statement Model'!F$9,'Balance Sheet'!$D$6:$I$6,0)) -> 899 | G73: =INDEX('Balance Sheet'!$D$9:$I$65,MATCH('3Statement Model'!$B73,'Balance Sheet'!$B$9:$B$65,0),MATCH('3Statement Model'!G$9,'Balance Sheet'!$D$6:$I$6,0)) -> 889 | H73: =INDEX('Balance Sheet'!$D$9:$I$65,MATCH('3Statement Model'!$B73,'Balance Sheet'!$B$9:$B$65,0),MATCH('3Statement Model'!H$9,'Balance Sheet'!$D$6:$I$6,0)) -> 868 | I73: =INDEX('Balance Sheet'!$D$9:$I$65,MATCH('3Statement Model'!$B73,'Balance Sheet'!$B$9:$B$65,0),MATCH('3Statement Model'!I$9,'Balance Sheet'!$D$6:$I$6,0)) -> 1280 | J73: =I73 -> 1280 | K73: =J73 -> 1280 | L73: =K73 -> 1280 | M73: =L73 -> 1280 | N73: =M73 -> 1280 | O73: =N73 -> 1280 | P73: =O73 -> 1280 | Q73: =P73 -> 1280 | ... S73: =R73 -> 1280
B74: Other Current Liabilities | D74: =INDEX('Balance Sheet'!$D$9:$I$65,MATCH('3Statement Model'!$B74,'Balance Sheet'!$B$9:$B$65,0),MATCH('3Statement Model'!D$9,'Balance Sheet'!$D$6:$I$6,0)) -> 428 | E74: =INDEX('Balance Sheet'!$D$9:$I$65,MATCH('3Statement Model'!$B74,'Balance Sheet'!$B$9:$B$65,0),MATCH('3Statement Model'!E$9,'Balance Sheet'!$D$6:$I$6,0)) -> 588 | F74: =INDEX('Balance Sheet'!$D$9:$I$65,MATCH('3Statement Model'!$B74,'Balance Sheet'!$B$9:$B$65,0),MATCH('3Statement Model'!F$9,'Balance Sheet'!$D$6:$I$6,0)) -> 665 | G74: =INDEX('Balance Sheet'!$D$9:$I$65,MATCH('3Statement Model'!$B74,'Balance Sheet'!$B$9:$B$65,0),MATCH('3Statement Model'!G$9,'Balance Sheet'!$D$6:$I$6,0)) -> 764 | H74: =INDEX('Balance Sheet'!$D$9:$I$65,MATCH('3Statement Model'!$B74,'Balance Sheet'!$B$9:$B$65,0),MATCH('3Statement Model'!H$9,'Balance Sheet'!$D$6:$I$6,0)) -> 807 | I74: =INDEX('Balance Sheet'!$D$9:$I$65,MATCH('3Statement Model'!$B74,'Balance Sheet'!$B$9:$B$65,0),MATCH('3Statement Model'!I$9,'Balance Sheet'!$D$6:$I$6,0)) -> 959 | J74: =I74 -> 959 | K74: =J74 -> 959 | L74: =K74 -> 959 | M74: =L74 -> 959 | N74: =M74 -> 959 | O74: =N74 -> 959 | P74: =O74 -> 959 | Q74: =P74 -> 959 | ... S74: =R74 -> 959 | U74: =_xlfn.RRI(5,I74,N74) -> 0 | V74: =_xlfn.RRI(3,I74,L74) -> 0
B75: Provisions (S) | D75: =INDEX('Balance Sheet'!$D$9:$I$65,MATCH('3Statement Model'!$B75,'Balance Sheet'!$B$9:$B$65,0),MATCH('3Statement Model'!D$9,'Balance Sheet'!$D$6:$I$6,0)) -> 422 | E75: =INDEX('Balance Sheet'!$D$9:$I$65,MATCH('3Statement Model'!$B75,'Balance Sheet'!$B$9:$B$65,0),MATCH('3Statement Model'!E$9,'Balance Sheet'!$D$6:$I$6,0)) -> 507 | F75: =INDEX('Balance Sheet'!$D$9:$I$65,MATCH('3Statement Model'!$B75,'Balance Sheet'!$B$9:$B$65,0),MATCH('3Statement Model'!F$9,'Balance Sheet'!$D$6:$I$6,0)) -> 346 | G75: =INDEX('Balance Sheet'!$D$9:$I$65,MATCH('3Statement Model'!$B75,'Balance Sheet'!$B$9:$B$65,0),MATCH('3Statement Model'!G$9,'Balance Sheet'!$D$6:$I$6,0)) -> 389 | H75: =INDEX('Balance Sheet'!$D$9:$I$65,MATCH('3Statement Model'!$B75,'Balance Sheet'!$B$9:$B$65,0),MATCH('3Statement Model'!H$9,'Balance Sheet'!$D$6:$I$6,0)) -> 340 | I75: =INDEX('Balance Sheet'!$D$9:$I$65,MATCH('3Statement Model'!$B75,'Balance Sheet'!$B$9:$B$65,0),MATCH('3Statement Model'!I$9,'Balance Sheet'!$D$6:$I$6,0)) -> 675 | J75: =I75 -> 675 | K75: =J75 -> 675 | L75: =K75 -> 675 | M75: =L75 -> 675 | N75: =M75 -> 675 | O75: =N75 -> 675 | P75: =O75 -> 675 | Q75: =P75 -> 675 | ... S75: =R75 -> 675 | U75: =_xlfn.RRI(5,I75,N75) -> 0 | V75: =_xlfn.RRI(3,I75,L75) -> 0
B76: Current Tax Liabilities | D76: =INDEX('Balance Sheet'!$D$9:$I$65,MATCH('3Statement Model'!$B76,'Balance Sheet'!$B$9:$B$65,0),MATCH('3Statement Model'!D$9,'Balance Sheet'!$D$6:$I$6,0)) -> 0 | E76: =INDEX('Balance Sheet'!$D$9:$I$65,MATCH('3Statement Model'!$B76,'Balance Sheet'!$B$9:$B$65,0),MATCH('3Statement Model'!E$9,'Balance Sheet'!$D$6:$I$6,0)) -> 0 | F76: =INDEX('Balance Sheet'!$D$9:$I$65,MATCH('3Statement Model'!$B76,'Balance Sheet'!$B$9:$B$65,0),MATCH('3Statement Model'!F$9,'Balance Sheet'!$D$6:$I$6,0)) -> 0 | G76: =INDEX('Balance Sheet'!$D$9:$I$65,MATCH('3Statement Model'!$B76,'Balance Sheet'!$B$9:$B$65,0),MATCH('3Statement Model'!G$9,'Balance Sheet'!$D$6:$I$6,0)) -> 0 | H76: =INDEX('Balance Sheet'!$D$9:$I$65,MATCH('3Statement Model'!$B76,'Balance Sheet'!$B$9:$B$65,0),MATCH('3Statement Model'!H$9,'Balance Sheet'!$D$6:$I$6,0)) -> 0 | I76: =INDEX('Balance Sheet'!$D$9:$I$65,MATCH('3Statement Model'!$B76,'Balance Sheet'!$B$9:$B$65,0),MATCH('3Statement Model'!I$9,'Balance Sheet'!$D$6:$I$6,0)) -> 1903 | J76: =I76 -> 1903 | K76: =J76 -> 1903 | L76: =K76 -> 1903 | M76: =L76 -> 1903 | N76: =M76 -> 1903 | O76: =N76 -> 1903 | P76: =O76 -> 1903 | Q76: =P76 -> 1903 | ... S76: =R76 -> 1903 | U76: =_xlfn.RRI(5,I76,N76) -> 0 | V76: =_xlfn.RRI(3,I76,L76) -> 0
B77: Total Current Liabilities | D77: =INDEX('Balance Sheet'!$D$9:$I$65,MATCH('3Statement Model'!$B77,'Balance Sheet'!$B$9:$B$65,0),MATCH('3Statement Model'!D$9,'Balance Sheet'!$D$6:$I$6,0)) -> 9317 | E77: =INDEX('Balance Sheet'!$D$9:$I$65,MATCH('3Statement Model'!$B77,'Balance Sheet'!$B$9:$B$65,0),MATCH('3Statement Model'!E$9,'Balance Sheet'!$D$6:$I$6,0)) -> 11103 | F77: =INDEX('Balance Sheet'!$D$9:$I$65,MATCH('3Statement Model'!$B77,'Balance Sheet'!$B$9:$B$65,0),MATCH('3Statement Model'!F$9,'Balance Sheet'!$D$6:$I$6,0)) -> 11280 | G77: =INDEX('Balance Sheet'!$D$9:$I$65,MATCH('3Statement Model'!$B77,'Balance Sheet'!$B$9:$B$65,0),MATCH('3Statement Model'!G$9,'Balance Sheet'!$D$6:$I$6,0)) -> 12028 | H77: =INDEX('Balance Sheet'!$D$9:$I$65,MATCH('3Statement Model'!$B77,'Balance Sheet'!$B$9:$B$65,0),MATCH('3Statement Model'!H$9,'Balance Sheet'!$D$6:$I$6,0)) -> 12879 | I77: =INDEX('Balance Sheet'!$D$9:$I$65,MATCH('3Statement Model'!$B77,'Balance Sheet'!$B$9:$B$65,0),MATCH('3Statement Model'!I$9,'Balance Sheet'!$D$6:$I$6,0)) -> 16537 | J77: =SUM(J70:J76) -> 20240.282 | K77: =SUM(K70:K76) -> 21521.479 | L77: =SUM(L70:L76) -> 22923.199 | M77: =SUM(M70:M76) -> 24457.723 | N77: =SUM(N70:N76) -> 26138.647 | O77: =SUM(O70:O76) -> 28084.943 | P77: =SUM(P70:P76) -> 30180.609 | Q77: =SUM(Q70:Q76) -> 32334.121 | ... S77: =SUM(S70:S76) -> 36751.998
B79: Total Equity and Liabilities | D79: =INDEX('Balance Sheet'!$D$9:$I$65,MATCH('3Statement Model'!$B79,'Balance Sheet'!$B$9:$B$65,0),MATCH('3Statement Model'!D$9,'Balance Sheet'!$D$6:$I$6,0)) -> 20153 | E79: =INDEX('Balance Sheet'!$D$9:$I$65,MATCH('3Statement Model'!$B79,'Balance Sheet'!$B$9:$B$65,0),MATCH('3Statement Model'!E$9,'Balance Sheet'!$D$6:$I$6,0)) -> 68757 | F79: =INDEX('Balance Sheet'!$D$9:$I$65,MATCH('3Statement Model'!$B79,'Balance Sheet'!$B$9:$B$65,0),MATCH('3Statement Model'!F$9,'Balance Sheet'!$D$6:$I$6,0)) -> 70517 | G79: =INDEX('Balance Sheet'!$D$9:$I$65,MATCH('3Statement Model'!$B79,'Balance Sheet'!$B$9:$B$65,0),MATCH('3Statement Model'!G$9,'Balance Sheet'!$D$6:$I$6,0)) -> 73087 | H79: =INDEX('Balance Sheet'!$D$9:$I$65,MATCH('3Statement Model'!$B79,'Balance Sheet'!$B$9:$B$65,0),MATCH('3Statement Model'!H$9,'Balance Sheet'!$D$6:$I$6,0)) -> 78499 | I79: =INDEX('Balance Sheet'!$D$9:$I$65,MATCH('3Statement Model'!$B79,'Balance Sheet'!$B$9:$B$65,0),MATCH('3Statement Model'!I$9,'Balance Sheet'!$D$6:$I$6,0)) -> 79880 | J79: =SUM(J77,J66,J57) -> 84762.475 | K79: =SUM(K77,K66,K57) -> 87080.195 | L79: =SUM(L77,L66,L57) -> 89364.57 | M79: =SUM(M77,M66,M57) -> 91591.628 | N79: =SUM(N77,N66,N57) -> 93732.159 | O79: =SUM(O77,O66,O57) -> 95854.711 | P79: =SUM(P77,P66,P57) -> 97787.637 | Q79: =SUM(Q77,Q66,Q57) -> 99375.057 | ... S79: =SUM(S77,S66,S57) -> 101216.99 | U79: =_xlfn.RRI(5,I79,N79) -> 0.032500126 | V79: =_xlfn.RRI(3,I79,L79) -> 0.03810776
B81: ASSETS
B82: NON-CURRENT ASSETS
B83: Property, Plant & Equipments | D83: =INDEX('Balance Sheet'!$D$9:$I$65,MATCH('3Statement Model'!$B83,'Balance Sheet'!$B$9:$B$65,0),MATCH('3Statement Model'!D$9,'Balance Sheet'!$D$6:$I$6,0)) -> 4109 | E83: =INDEX('Balance Sheet'!$D$9:$I$65,MATCH('3Statement Model'!$B83,'Balance Sheet'!$B$9:$B$65,0),MATCH('3Statement Model'!E$9,'Balance Sheet'!$D$6:$I$6,0)) -> 5067 | F83: =INDEX('Balance Sheet'!$D$9:$I$65,MATCH('3Statement Model'!$B83,'Balance Sheet'!$B$9:$B$65,0),MATCH('3Statement Model'!F$9,'Balance Sheet'!$D$6:$I$6,0)) -> 5101 | G83: =INDEX('Balance Sheet'!$D$9:$I$65,MATCH('3Statement Model'!$B83,'Balance Sheet'!$B$9:$B$65,0),MATCH('3Statement Model'!G$9,'Balance Sheet'!$D$6:$I$6,0)) -> 5767 | H83: =INDEX('Balance Sheet'!$D$9:$I$65,MATCH('3Statement Model'!$B83,'Balance Sheet'!$B$9:$B$65,0),MATCH('3Statement Model'!H$9,'Balance Sheet'!$D$6:$I$6,0)) -> 6517 | I83: =INDEX('Balance Sheet'!$D$9:$I$65,MATCH('3Statement Model'!$B83,'Balance Sheet'!$B$9:$B$65,0),MATCH('3Statement Model'!I$9,'Balance Sheet'!$D$6:$I$6,0)) -> 6941 | J83: =Schedules!K76 -> 7201.4916 | K83: =Schedules!L76 -> 7483.6076 | L83: =Schedules!M76 -> 7790.4923 | M83: =Schedules!N76 -> 8125.6905 | N83: =Schedules!O76 -> 8493.1964 | O83: =Schedules!P76 -> 8897.5089 | P83: =Schedules!Q76 -> 9339.5277 | Q83: =Schedules!R76 -> 9811.2674 | ... S83: =Schedules!T76 -> 10803.447 | U83: =_xlfn.RRI(5,I83,N83) -> 0.041189607 | V83: =_xlfn.RRI(3,I83,L83) -> 0.039236248
B84: Right-of-Use Asset | D84: ='Balance Sheet'!D40 -> 851 | E84: ='Balance Sheet'!E40 -> 1049 | F84: ='Balance Sheet'!F40 -> 1068 | G84: ='Balance Sheet'!G40 -> 1182 | H84: ='Balance Sheet'!H40 -> 1514 | I84: ='Balance Sheet'!I40 -> 1684 | J84: =Schedules!K86 -> 2522.26 | K84: =Schedules!L86 -> 3129.6222 | L84: =Schedules!M86 -> 3754.9328 | M84: =Schedules!N86 -> 4400.6879 | N84: =Schedules!O86 -> 5069.6978 | O84: =Schedules!P86 -> 5765.1258 | P84: =Schedules!Q86 -> 6482.2093 | Q84: =Schedules!R86 -> 7203.6834 | ... S84: =Schedules!T86 -> 8628.0733
B85: Capital Work-In-Progress | D85: =INDEX('Balance Sheet'!$D$9:$I$65,MATCH('3Statement Model'!$B85,'Balance Sheet'!$B$9:$B$65,0),MATCH('3Statement Model'!D$9,'Balance Sheet'!$D$6:$I$6,0)) -> 597 | E85: =INDEX('Balance Sheet'!$D$9:$I$65,MATCH('3Statement Model'!$B85,'Balance Sheet'!$B$9:$B$65,0),MATCH('3Statement Model'!E$9,'Balance Sheet'!$D$6:$I$6,0)) -> 745 | F85: =INDEX('Balance Sheet'!$D$9:$I$65,MATCH('3Statement Model'!$B85,'Balance Sheet'!$B$9:$B$65,0),MATCH('3Statement Model'!F$9,'Balance Sheet'!$D$6:$I$6,0)) -> 1313 | G85: =INDEX('Balance Sheet'!$D$9:$I$65,MATCH('3Statement Model'!$B85,'Balance Sheet'!$B$9:$B$65,0),MATCH('3Statement Model'!G$9,'Balance Sheet'!$D$6:$I$6,0)) -> 1132 | H85: =INDEX('Balance Sheet'!$D$9:$I$65,MATCH('3Statement Model'!$B85,'Balance Sheet'!$B$9:$B$65,0),MATCH('3Statement Model'!H$9,'Balance Sheet'!$D$6:$I$6,0)) -> 1025 | I85: =INDEX('Balance Sheet'!$D$9:$I$65,MATCH('3Statement Model'!$B85,'Balance Sheet'!$B$9:$B$65,0),MATCH('3Statement Model'!I$9,'Balance Sheet'!$D$6:$I$6,0)) -> 1009 | J85: =Schedules!K94 -> 1058.3955 | K85: =Schedules!L94 -> 1064.2199 | L85: =Schedules!M94 -> 1070.5584 | M85: =Schedules!N94 -> 1077.4846 | N85: =Schedules!O94 -> 1085.0814 | O85: =Schedules!P94 -> 1093.5182 | P85: =Schedules!Q94 -> 1102.8282 | Q85: =Schedules!R94 -> 1112.8688 | ... S85: =Schedules!T94 -> 1134.4153 | U85: =_xlfn.RRI(5,I85,N85) -> 0.014645259 | V85: =_xlfn.RRI(3,I85,L85) -> 0.01993634
B86: Goodwill | D86: =INDEX('Balance Sheet'!$D$9:$I$65,MATCH('3Statement Model'!$B86,'Balance Sheet'!$B$9:$B$65,0),MATCH('3Statement Model'!D$9,'Balance Sheet'!$D$6:$I$6,0)) -> 117 | E86: =INDEX('Balance Sheet'!$D$9:$I$65,MATCH('3Statement Model'!$B86,'Balance Sheet'!$B$9:$B$65,0),MATCH('3Statement Model'!E$9,'Balance Sheet'!$D$6:$I$6,0)) -> 17397 | F86: =INDEX('Balance Sheet'!$D$9:$I$65,MATCH('3Statement Model'!$B86,'Balance Sheet'!$B$9:$B$65,0),MATCH('3Statement Model'!F$9,'Balance Sheet'!$D$6:$I$6,0)) -> 17397 | G86: =INDEX('Balance Sheet'!$D$9:$I$65,MATCH('3Statement Model'!$B86,'Balance Sheet'!$B$9:$B$65,0),MATCH('3Statement Model'!G$9,'Balance Sheet'!$D$6:$I$6,0)) -> 17466 | H86: =INDEX('Balance Sheet'!$D$9:$I$65,MATCH('3Statement Model'!$B86,'Balance Sheet'!$B$9:$B$65,0),MATCH('3Statement Model'!H$9,'Balance Sheet'!$D$6:$I$6,0)) -> 17466 | I86: =INDEX('Balance Sheet'!$D$9:$I$65,MATCH('3Statement Model'!$B86,'Balance Sheet'!$B$9:$B$65,0),MATCH('3Statement Model'!I$9,'Balance Sheet'!$D$6:$I$6,0)) -> 17466 | J86: =Schedules!K102 -> 17466 | K86: =Schedules!L102 -> 17466 | L86: =Schedules!M102 -> 17466 | M86: =Schedules!N102 -> 17466 | N86: =Schedules!O102 -> 17466 | O86: =Schedules!P102 -> 17466 | P86: =Schedules!Q102 -> 17466 | Q86: =Schedules!R102 -> 17466 | ... S86: =Schedules!T102 -> 17466 | U86: =_xlfn.RRI(5,I86,N86) -> 0 | V86: =_xlfn.RRI(3,I86,L86) -> 0
B87: Intangible Assets | D87: =INDEX('Balance Sheet'!$D$9:$I$65,MATCH('3Statement Model'!$B87,'Balance Sheet'!$B$9:$B$65,0),MATCH('3Statement Model'!D$9,'Balance Sheet'!$D$6:$I$6,0)) -> 402 | E87: =INDEX('Balance Sheet'!$D$9:$I$65,MATCH('3Statement Model'!$B87,'Balance Sheet'!$B$9:$B$65,0),MATCH('3Statement Model'!E$9,'Balance Sheet'!$D$6:$I$6,0)) -> 27930 | F87: =INDEX('Balance Sheet'!$D$9:$I$65,MATCH('3Statement Model'!$B87,'Balance Sheet'!$B$9:$B$65,0),MATCH('3Statement Model'!F$9,'Balance Sheet'!$D$6:$I$6,0)) -> 27907 | G87: =INDEX('Balance Sheet'!$D$9:$I$65,MATCH('3Statement Model'!$B87,'Balance Sheet'!$B$9:$B$65,0),MATCH('3Statement Model'!G$9,'Balance Sheet'!$D$6:$I$6,0)) -> 28263 | H87: =INDEX('Balance Sheet'!$D$9:$I$65,MATCH('3Statement Model'!$B87,'Balance Sheet'!$B$9:$B$65,0),MATCH('3Statement Model'!H$9,'Balance Sheet'!$D$6:$I$6,0)) -> 28247 | I87: =INDEX('Balance Sheet'!$D$9:$I$65,MATCH('3Statement Model'!$B87,'Balance Sheet'!$B$9:$B$65,0),MATCH('3Statement Model'!I$9,'Balance Sheet'!$D$6:$I$6,0)) -> 28244 | J87: =Schedules!K112 -> 28252.285 | K87: =Schedules!L112 -> 28261.387 | L87: =Schedules!M112 -> 28271.428 | M87: =Schedules!N112 -> 28282.539 | N87: =Schedules!O112 -> 28294.874 | O87: =Schedules!P112 -> 28312.402 | P87: =Schedules!Q112 -> 28335.88 | Q87: =Schedules!R112 -> 28366.174 | ... S87: =Schedules!T112 -> 28451.317 | U87: =_xlfn.RRI(5,I87,N87) -> 0.00035998486 | V87: =_xlfn.RRI(3,I87,L87) -> 0.00032359443
B88: Financial Assets | U88: =_xlfn.RRI(5,I88,N88) -> 0 | V88: =_xlfn.RRI(3,I88,L88) -> 0
B89: Non-Current Investments | D89: =INDEX('Balance Sheet'!$D$9:$I$65,MATCH('3Statement Model'!$B89,'Balance Sheet'!$B$9:$B$65,0),MATCH('3Statement Model'!D$9,'Balance Sheet'!$D$6:$I$6,0)) -> 2 | E89: =INDEX('Balance Sheet'!$D$9:$I$65,MATCH('3Statement Model'!$B89,'Balance Sheet'!$B$9:$B$65,0),MATCH('3Statement Model'!E$9,'Balance Sheet'!$D$6:$I$6,0)) -> 2 | F89: =INDEX('Balance Sheet'!$D$9:$I$65,MATCH('3Statement Model'!$B89,'Balance Sheet'!$B$9:$B$65,0),MATCH('3Statement Model'!F$9,'Balance Sheet'!$D$6:$I$6,0)) -> 2 | G89: =INDEX('Balance Sheet'!$D$9:$I$65,MATCH('3Statement Model'!$B89,'Balance Sheet'!$B$9:$B$65,0),MATCH('3Statement Model'!G$9,'Balance Sheet'!$D$6:$I$6,0)) -> 71 | H89: =INDEX('Balance Sheet'!$D$9:$I$65,MATCH('3Statement Model'!$B89,'Balance Sheet'!$B$9:$B$65,0),MATCH('3Statement Model'!H$9,'Balance Sheet'!$D$6:$I$6,0)) -> 67 | I89: =INDEX('Balance Sheet'!$D$9:$I$65,MATCH('3Statement Model'!$B89,'Balance Sheet'!$B$9:$B$65,0),MATCH('3Statement Model'!I$9,'Balance Sheet'!$D$6:$I$6,0)) -> 59 | J89: =I89+(I89*Schedules!K$123) -> 59.885 | K89: =J89+(J89*Schedules!L$123) -> 60.783275 | L89: =K89+(K89*Schedules!M$123) -> 61.695024 | M89: =L89+(L89*Schedules!N$123) -> 62.620449 | N89: =M89+(M89*Schedules!O$123) -> 63.559756 | O89: =N89+(N89*Schedules!P$123) -> 64.513153 | P89: =O89+(O89*Schedules!Q$123) -> 65.48085 | Q89: =P89+(P89*Schedules!R$123) -> 66.463063 | ... S89: =R89+(R89*Schedules!T$123) -> 68.471909 | U89: =_xlfn.RRI(5,I89,N89) -> 0.015 | V89: =_xlfn.RRI(3,I89,L89) -> 0.015
B90: Long Term Loans And Advances | D90: =INDEX('Balance Sheet'!$D$9:$I$65,MATCH('3Statement Model'!$B90,'Balance Sheet'!$B$9:$B$65,0),MATCH('3Statement Model'!D$9,'Balance Sheet'!$D$6:$I$6,0)) -> 238 | E90: =INDEX('Balance Sheet'!$D$9:$I$65,MATCH('3Statement Model'!$B90,'Balance Sheet'!$B$9:$B$65,0),MATCH('3Statement Model'!E$9,'Balance Sheet'!$D$6:$I$6,0)) -> 111 | F90: =INDEX('Balance Sheet'!$D$9:$I$65,MATCH('3Statement Model'!$B90,'Balance Sheet'!$B$9:$B$65,0),MATCH('3Statement Model'!F$9,'Balance Sheet'!$D$6:$I$6,0)) -> 115 | G90: =INDEX('Balance Sheet'!$D$9:$I$65,MATCH('3Statement Model'!$B90,'Balance Sheet'!$B$9:$B$65,0),MATCH('3Statement Model'!G$9,'Balance Sheet'!$D$6:$I$6,0)) -> 98 | H90: =INDEX('Balance Sheet'!$D$9:$I$65,MATCH('3Statement Model'!$B90,'Balance Sheet'!$B$9:$B$65,0),MATCH('3Statement Model'!H$9,'Balance Sheet'!$D$6:$I$6,0)) -> 102 | I90: =INDEX('Balance Sheet'!$D$9:$I$65,MATCH('3Statement Model'!$B90,'Balance Sheet'!$B$9:$B$65,0),MATCH('3Statement Model'!I$9,'Balance Sheet'!$D$6:$I$6,0)) -> 87 | J90: =I90+(I90*Schedules!K$123) -> 88.305 | K90: =J90+(J90*Schedules!L$123) -> 89.629575 | L90: =K90+(K90*Schedules!M$123) -> 90.974019 | M90: =L90+(L90*Schedules!N$123) -> 92.338629 | N90: =M90+(M90*Schedules!O$123) -> 93.723708 | O90: =N90+(N90*Schedules!P$123) -> 95.129564 | P90: =O90+(O90*Schedules!Q$123) -> 96.556507 | Q90: =P90+(P90*Schedules!R$123) -> 98.004855 | ... S90: =R90+(R90*Schedules!T$123) -> 100.96705 | U90: =_xlfn.RRI(5,I90,N90) -> 0.015 | V90: =_xlfn.RRI(3,I90,L90) -> 0.015
B91: Other Financial Asset | D91: =INDEX('Balance Sheet'!$D$9:$I$65,MATCH('3Statement Model'!$B91,'Balance Sheet'!$B$9:$B$65,0),MATCH('3Statement Model'!D$9,'Balance Sheet'!$D$6:$I$6,0)) -> 3 | E91: =INDEX('Balance Sheet'!$D$9:$I$65,MATCH('3Statement Model'!$B91,'Balance Sheet'!$B$9:$B$65,0),MATCH('3Statement Model'!E$9,'Balance Sheet'!$D$6:$I$6,0)) -> 757 | F91: =INDEX('Balance Sheet'!$D$9:$I$65,MATCH('3Statement Model'!$B91,'Balance Sheet'!$B$9:$B$65,0),MATCH('3Statement Model'!F$9,'Balance Sheet'!$D$6:$I$6,0)) -> 729 | G91: =INDEX('Balance Sheet'!$D$9:$I$65,MATCH('3Statement Model'!$B91,'Balance Sheet'!$B$9:$B$65,0),MATCH('3Statement Model'!G$9,'Balance Sheet'!$D$6:$I$6,0)) -> 725 | H91: =INDEX('Balance Sheet'!$D$9:$I$65,MATCH('3Statement Model'!$B91,'Balance Sheet'!$B$9:$B$65,0),MATCH('3Statement Model'!H$9,'Balance Sheet'!$D$6:$I$6,0)) -> 760 | I91: =INDEX('Balance Sheet'!$D$9:$I$65,MATCH('3Statement Model'!$B91,'Balance Sheet'!$B$9:$B$65,0),MATCH('3Statement Model'!I$9,'Balance Sheet'!$D$6:$I$6,0)) -> 763 | J91: =I91+(I91*Schedules!K$123) -> 774.445 | K91: =J91+(J91*Schedules!L$123) -> 786.06168 | L91: =K91+(K91*Schedules!M$123) -> 797.8526 | M91: =L91+(L91*Schedules!N$123) -> 809.82039 | N91: =M91+(M91*Schedules!O$123) -> 821.96769 | O91: =N91+(N91*Schedules!P$123) -> 834.29721 | P91: =O91+(O91*Schedules!Q$123) -> 846.81167 | Q91: =P91+(P91*Schedules!R$123) -> 859.51384 | ... S91: =R91+(R91*Schedules!T$123) -> 885.49265 | U91: =_xlfn.RRI(5,I91,N91) -> 0.015 | V91: =_xlfn.RRI(3,I91,L91) -> 0.015
B92: Deferred Tax Assets [Net] | D92: =INDEX('Balance Sheet'!$D$9:$I$65,MATCH('3Statement Model'!$B92,'Balance Sheet'!$B$9:$B$65,0),MATCH('3Statement Model'!D$9,'Balance Sheet'!$D$6:$I$6,0)) -> 284 | E92: =INDEX('Balance Sheet'!$D$9:$I$65,MATCH('3Statement Model'!$B92,'Balance Sheet'!$B$9:$B$65,0),MATCH('3Statement Model'!E$9,'Balance Sheet'!$D$6:$I$6,0)) -> 17 | F92: =INDEX('Balance Sheet'!$D$9:$I$65,MATCH('3Statement Model'!$B92,'Balance Sheet'!$B$9:$B$65,0),MATCH('3Statement Model'!F$9,'Balance Sheet'!$D$6:$I$6,0)) -> 11 | G92: =INDEX('Balance Sheet'!$D$9:$I$65,MATCH('3Statement Model'!$B92,'Balance Sheet'!$B$9:$B$65,0),MATCH('3Statement Model'!G$9,'Balance Sheet'!$D$6:$I$6,0)) -> 10 | H92: =INDEX('Balance Sheet'!$D$9:$I$65,MATCH('3Statement Model'!$B92,'Balance Sheet'!$B$9:$B$65,0),MATCH('3Statement Model'!H$9,'Balance Sheet'!$D$6:$I$6,0)) -> 10 | I92: =INDEX('Balance Sheet'!$D$9:$I$65,MATCH('3Statement Model'!$B92,'Balance Sheet'!$B$9:$B$65,0),MATCH('3Statement Model'!I$9,'Balance Sheet'!$D$6:$I$6,0)) -> 17 | J92: =Schedules!K128 -> 17 | K92: =Schedules!L128 -> 17 | L92: =Schedules!M128 -> 17 | M92: =Schedules!N128 -> 17 | N92: =Schedules!O128 -> 17 | O92: =Schedules!P128 -> 17 | P92: =Schedules!Q128 -> 17 | Q92: =Schedules!R128 -> 17 | ... S92: =Schedules!T128 -> 17 | U92: =_xlfn.RRI(5,I92,N92) -> 0 | V92: =_xlfn.RRI(3,I92,L92) -> 0
B93: Non-Current Tax Assets | D93: =INDEX('Balance Sheet'!$D$9:$I$65,MATCH('3Statement Model'!$B93,'Balance Sheet'!$B$9:$B$65,0),MATCH('3Statement Model'!D$9,'Balance Sheet'!$D$6:$I$6,0)) -> 1083 | E93: =INDEX('Balance Sheet'!$D$9:$I$65,MATCH('3Statement Model'!$B93,'Balance Sheet'!$B$9:$B$65,0),MATCH('3Statement Model'!E$9,'Balance Sheet'!$D$6:$I$6,0)) -> 1246 | F93: =INDEX('Balance Sheet'!$D$9:$I$65,MATCH('3Statement Model'!$B93,'Balance Sheet'!$B$9:$B$65,0),MATCH('3Statement Model'!F$9,'Balance Sheet'!$D$6:$I$6,0)) -> 1158 | G93: =INDEX('Balance Sheet'!$D$9:$I$65,MATCH('3Statement Model'!$B93,'Balance Sheet'!$B$9:$B$65,0),MATCH('3Statement Model'!G$9,'Balance Sheet'!$D$6:$I$6,0)) -> 1164 | H93: =INDEX('Balance Sheet'!$D$9:$I$65,MATCH('3Statement Model'!$B93,'Balance Sheet'!$B$9:$B$65,0),MATCH('3Statement Model'!H$9,'Balance Sheet'!$D$6:$I$6,0)) -> 1175 | I93: =INDEX('Balance Sheet'!$D$9:$I$65,MATCH('3Statement Model'!$B93,'Balance Sheet'!$B$9:$B$65,0),MATCH('3Statement Model'!I$9,'Balance Sheet'!$D$6:$I$6,0)) -> 1199 | J93: =Schedules!K134 -> 1199 | K93: =Schedules!L134 -> 1199 | L93: =Schedules!M134 -> 1199 | M93: =Schedules!N134 -> 1199 | N93: =Schedules!O134 -> 1199 | O93: =Schedules!P134 -> 1199 | P93: =Schedules!Q134 -> 1199 | Q93: =Schedules!R134 -> 1199 | ... S93: =Schedules!T134 -> 1199 | U93: =_xlfn.RRI(5,I93,N93) -> 0 | V93: =_xlfn.RRI(3,I93,L93) -> 0
B94: Other Non-Current Assets | D94: =INDEX('Balance Sheet'!$D$9:$I$65,MATCH('3Statement Model'!$B94,'Balance Sheet'!$B$9:$B$65,0),MATCH('3Statement Model'!D$9,'Balance Sheet'!$D$6:$I$6,0)) -> 146 | E94: =INDEX('Balance Sheet'!$D$9:$I$65,MATCH('3Statement Model'!$B94,'Balance Sheet'!$B$9:$B$65,0),MATCH('3Statement Model'!E$9,'Balance Sheet'!$D$6:$I$6,0)) -> 219 | F94: =INDEX('Balance Sheet'!$D$9:$I$65,MATCH('3Statement Model'!$B94,'Balance Sheet'!$B$9:$B$65,0),MATCH('3Statement Model'!F$9,'Balance Sheet'!$D$6:$I$6,0)) -> 194 | G94: =INDEX('Balance Sheet'!$D$9:$I$65,MATCH('3Statement Model'!$B94,'Balance Sheet'!$B$9:$B$65,0),MATCH('3Statement Model'!G$9,'Balance Sheet'!$D$6:$I$6,0)) -> 211 | H94: =INDEX('Balance Sheet'!$D$9:$I$65,MATCH('3Statement Model'!$B94,'Balance Sheet'!$B$9:$B$65,0),MATCH('3Statement Model'!H$9,'Balance Sheet'!$D$6:$I$6,0)) -> 292 | I94: =INDEX('Balance Sheet'!$D$9:$I$65,MATCH('3Statement Model'!$B94,'Balance Sheet'!$B$9:$B$65,0),MATCH('3Statement Model'!I$9,'Balance Sheet'!$D$6:$I$6,0)) -> 360 | J94: =Schedules!K140 -> 361.44 | K94: =Schedules!L140 -> 362.88576 | L94: =Schedules!M140 -> 364.3373 | M94: =Schedules!N140 -> 365.79465 | N94: =Schedules!O140 -> 367.25783 | O94: =Schedules!P140 -> 368.72686 | P94: =Schedules!Q140 -> 370.20177 | Q94: =Schedules!R140 -> 371.68258 | ... S94: =Schedules!T140 -> 374.66198 | U94: =_xlfn.RRI(5,I94,N94) -> 0.004 | V94: =_xlfn.RRI(3,I94,L94) -> 0.004
B95: Total Non-Current Assets | D95: =INDEX('Balance Sheet'!$D$9:$I$65,MATCH('3Statement Model'!$B95,'Balance Sheet'!$B$9:$B$65,0),MATCH('3Statement Model'!D$9,'Balance Sheet'!$D$6:$I$6,0)) -> 7832 | E95: =INDEX('Balance Sheet'!$D$9:$I$65,MATCH('3Statement Model'!$B95,'Balance Sheet'!$B$9:$B$65,0),MATCH('3Statement Model'!E$9,'Balance Sheet'!$D$6:$I$6,0)) -> 54540 | F95: =INDEX('Balance Sheet'!$D$9:$I$65,MATCH('3Statement Model'!$B95,'Balance Sheet'!$B$9:$B$65,0),MATCH('3Statement Model'!F$9,'Balance Sheet'!$D$6:$I$6,0)) -> 54995 | G95: =INDEX('Balance Sheet'!$D$9:$I$65,MATCH('3Statement Model'!$B95,'Balance Sheet'!$B$9:$B$65,0),MATCH('3Statement Model'!G$9,'Balance Sheet'!$D$6:$I$6,0)) -> 56089 | H95: =INDEX('Balance Sheet'!$D$9:$I$65,MATCH('3Statement Model'!$B95,'Balance Sheet'!$B$9:$B$65,0),MATCH('3Statement Model'!H$9,'Balance Sheet'!$D$6:$I$6,0)) -> 57175 | I95: =INDEX('Balance Sheet'!$D$9:$I$65,MATCH('3Statement Model'!$B95,'Balance Sheet'!$B$9:$B$65,0),MATCH('3Statement Model'!I$9,'Balance Sheet'!$D$6:$I$6,0)) -> 57829 | J95: =SUM(J83:J94) -> 59000.507 | K95: =SUM(K83:K94) -> 59920.197 | L95: =SUM(L83:L94) -> 60884.27 | M95: =SUM(M83:M94) -> 61898.977 | N95: =SUM(N83:N94) -> 62971.358 | O95: =SUM(O83:O94) -> 64113.222 | P95: =SUM(P83:P94) -> 65321.496 | Q95: =SUM(Q83:Q94) -> 66571.658 | ... S95: =SUM(S83:S94) -> 69128.846 | U95: =_xlfn.RRI(5,I95,N95) -> 0.017183896 | V95: =_xlfn.RRI(3,I95,L95) -> 0.017309595
B97: CURRENT ASSETS
B98: Inventories | D98: =INDEX('Balance Sheet'!$D$9:$I$65,MATCH('3Statement Model'!$B98,'Balance Sheet'!$B$9:$B$65,0),MATCH('3Statement Model'!D$9,'Balance Sheet'!$D$6:$I$6,0)) -> 2767 | E98: =INDEX('Balance Sheet'!$D$9:$I$65,MATCH('3Statement Model'!$B98,'Balance Sheet'!$B$9:$B$65,0),MATCH('3Statement Model'!E$9,'Balance Sheet'!$D$6:$I$6,0)) -> 3579 | F98: =INDEX('Balance Sheet'!$D$9:$I$65,MATCH('3Statement Model'!$B98,'Balance Sheet'!$B$9:$B$65,0),MATCH('3Statement Model'!F$9,'Balance Sheet'!$D$6:$I$6,0)) -> 4096 | G98: =INDEX('Balance Sheet'!$D$9:$I$65,MATCH('3Statement Model'!$B98,'Balance Sheet'!$B$9:$B$65,0),MATCH('3Statement Model'!G$9,'Balance Sheet'!$D$6:$I$6,0)) -> 4251 | H98: =INDEX('Balance Sheet'!$D$9:$I$65,MATCH('3Statement Model'!$B98,'Balance Sheet'!$B$9:$B$65,0),MATCH('3Statement Model'!H$9,'Balance Sheet'!$D$6:$I$6,0)) -> 4022 | I98: =INDEX('Balance Sheet'!$D$9:$I$65,MATCH('3Statement Model'!$B98,'Balance Sheet'!$B$9:$B$65,0),MATCH('3Statement Model'!I$9,'Balance Sheet'!$D$6:$I$6,0)) -> 4415 | J98: =Schedules!K224 -> 5526.4412 | K98: =Schedules!L224 -> 5984.2892 | L98: =Schedules!M224 -> 6485.1048 | M98: =Schedules!N224 -> 7033.2562 | N98: =Schedules!O224 -> 7633.5782 | O98: =Schedules!P224 -> 8330.3913 | P98: =Schedules!Q224 -> 9080.6817 | Q98: =Schedules!R224 -> 9851.6823 | ... S98: =Schedules!T224 -> 11433.371
B99: Financial Assets
B100: Current Investments | D100: =INDEX('Balance Sheet'!$D$9:$I$65,MATCH('3Statement Model'!$B100,'Balance Sheet'!$B$9:$B$65,0),MATCH('3Statement Model'!D$9,'Balance Sheet'!$D$6:$I$6,0)) -> 1253 | E100: =INDEX('Balance Sheet'!$D$9:$I$65,MATCH('3Statement Model'!$B100,'Balance Sheet'!$B$9:$B$65,0),MATCH('3Statement Model'!E$9,'Balance Sheet'!$D$6:$I$6,0)) -> 2707 | F100: =INDEX('Balance Sheet'!$D$9:$I$65,MATCH('3Statement Model'!$B100,'Balance Sheet'!$B$9:$B$65,0),MATCH('3Statement Model'!F$9,'Balance Sheet'!$D$6:$I$6,0)) -> 3519 | G100: =INDEX('Balance Sheet'!$D$9:$I$65,MATCH('3Statement Model'!$B100,'Balance Sheet'!$B$9:$B$65,0),MATCH('3Statement Model'!G$9,'Balance Sheet'!$D$6:$I$6,0)) -> 2811 | H100: =INDEX('Balance Sheet'!$D$9:$I$65,MATCH('3Statement Model'!$B100,'Balance Sheet'!$B$9:$B$65,0),MATCH('3Statement Model'!H$9,'Balance Sheet'!$D$6:$I$6,0)) -> 4558 | I100: =INDEX('Balance Sheet'!$D$9:$I$65,MATCH('3Statement Model'!$B100,'Balance Sheet'!$B$9:$B$65,0),MATCH('3Statement Model'!I$9,'Balance Sheet'!$D$6:$I$6,0)) -> 3751 | J100: =Schedules!K234 -> 3751 | K100: =Schedules!L234 -> 3751 | L100: =Schedules!M234 -> 3751 | M100: =Schedules!N234 -> 3751 | N100: =Schedules!O234 -> 3751 | O100: =Schedules!P234 -> 3751 | P100: =Schedules!Q234 -> 3751 | Q100: =Schedules!R234 -> 3751 | ... S100: =Schedules!T234 -> 3751
B101: Trade Receivables | D101: =INDEX('Balance Sheet'!$D$9:$I$65,MATCH('3Statement Model'!$B101,'Balance Sheet'!$B$9:$B$65,0),MATCH('3Statement Model'!D$9,'Balance Sheet'!$D$6:$I$6,0)) -> 1149 | E101: =INDEX('Balance Sheet'!$D$9:$I$65,MATCH('3Statement Model'!$B101,'Balance Sheet'!$B$9:$B$65,0),MATCH('3Statement Model'!E$9,'Balance Sheet'!$D$6:$I$6,0)) -> 1758 | F101: =INDEX('Balance Sheet'!$D$9:$I$65,MATCH('3Statement Model'!$B101,'Balance Sheet'!$B$9:$B$65,0),MATCH('3Statement Model'!F$9,'Balance Sheet'!$D$6:$I$6,0)) -> 2236 | G101: =INDEX('Balance Sheet'!$D$9:$I$65,MATCH('3Statement Model'!$B101,'Balance Sheet'!$B$9:$B$65,0),MATCH('3Statement Model'!G$9,'Balance Sheet'!$D$6:$I$6,0)) -> 3079 | H101: =INDEX('Balance Sheet'!$D$9:$I$65,MATCH('3Statement Model'!$B101,'Balance Sheet'!$B$9:$B$65,0),MATCH('3Statement Model'!H$9,'Balance Sheet'!$D$6:$I$6,0)) -> 2997 | I101: =INDEX('Balance Sheet'!$D$9:$I$65,MATCH('3Statement Model'!$B101,'Balance Sheet'!$B$9:$B$65,0),MATCH('3Statement Model'!I$9,'Balance Sheet'!$D$6:$I$6,0)) -> 3819 | J101: =Schedules!K219 -> 3383.5355 | K101: =Schedules!L219 -> 3271.7795 | L101: =Schedules!M219 -> 3562.0212 | M101: =Schedules!N219 -> 3881.0863 | N101: =Schedules!O219 -> 4232.06 | O101: =Schedules!P219 -> 4618.3735 | P101: =Schedules!Q219 -> 5034.335 | Q101: =Schedules!R219 -> 5461.7781 | ... S101: =Schedules!T219 -> 6338.6673
B102: Cash And Cash Equivalents | D102: =D165 -> 3216 | E102: =E165 -> 1842 | F102: =F165 -> 1147 | G102: =G165 -> 714 | H102: =H165 -> 812 | I102: =I165 -> 6070 | J102: =J165 -> 10212.502 | K102: =K165 -> 11148.466 | ... S102: =S165 -> 6198.0351
B103: Bank Balances | D103: =INDEX('Balance Sheet'!$D$9:$I$65,MATCH('3Statement Model'!$B103,'Balance Sheet'!$B$9:$B$65,0),MATCH('3Statement Model'!D$9,'Balance Sheet'!$D$6:$I$6,0)) -> 1897 | E103: =INDEX('Balance Sheet'!$D$9:$I$65,MATCH('3Statement Model'!$B103,'Balance Sheet'!$B$9:$B$65,0),MATCH('3Statement Model'!E$9,'Balance Sheet'!$D$6:$I$6,0)) -> 2629 | F103: =INDEX('Balance Sheet'!$D$9:$I$65,MATCH('3Statement Model'!$B103,'Balance Sheet'!$B$9:$B$65,0),MATCH('3Statement Model'!F$9,'Balance Sheet'!$D$6:$I$6,0)) -> 2699 | G103: =INDEX('Balance Sheet'!$D$9:$I$65,MATCH('3Statement Model'!$B103,'Balance Sheet'!$B$9:$B$65,0),MATCH('3Statement Model'!G$9,'Balance Sheet'!$D$6:$I$6,0)) -> 3964 | H103: =INDEX('Balance Sheet'!$D$9:$I$65,MATCH('3Statement Model'!$B103,'Balance Sheet'!$B$9:$B$65,0),MATCH('3Statement Model'!H$9,'Balance Sheet'!$D$6:$I$6,0)) -> 6747 | I103: =INDEX('Balance Sheet'!$D$9:$I$65,MATCH('3Statement Model'!$B103,'Balance Sheet'!$B$9:$B$65,0),MATCH('3Statement Model'!I$9,'Balance Sheet'!$D$6:$I$6,0)) -> 1484 | J103: =I103 -> 1484 | K103: =J103 -> 1484 | L103: =K103 -> 1484 | M103: =L103 -> 1484 | N103: =M103 -> 1484 | O103: =N103 -> 1484 | P103: =O103 -> 1484 | Q103: =P103 -> 1484 | ... S103: =R103 -> 1484
B104: Loans | D104: =INDEX('Balance Sheet'!$D$9:$I$65,MATCH('3Statement Model'!$B104,'Balance Sheet'!$B$9:$B$65,0),MATCH('3Statement Model'!D$9,'Balance Sheet'!$D$6:$I$6,0)) -> 0 | E104: =INDEX('Balance Sheet'!$D$9:$I$65,MATCH('3Statement Model'!$B104,'Balance Sheet'!$B$9:$B$65,0),MATCH('3Statement Model'!E$9,'Balance Sheet'!$D$6:$I$6,0)) -> 0 | F104: =INDEX('Balance Sheet'!$D$9:$I$65,MATCH('3Statement Model'!$B104,'Balance Sheet'!$B$9:$B$65,0),MATCH('3Statement Model'!F$9,'Balance Sheet'!$D$6:$I$6,0)) -> 35 | G104: =INDEX('Balance Sheet'!$D$9:$I$65,MATCH('3Statement Model'!$B104,'Balance Sheet'!$B$9:$B$65,0),MATCH('3Statement Model'!G$9,'Balance Sheet'!$D$6:$I$6,0)) -> 36 | H104: =INDEX('Balance Sheet'!$D$9:$I$65,MATCH('3Statement Model'!$B104,'Balance Sheet'!$B$9:$B$65,0),MATCH('3Statement Model'!H$9,'Balance Sheet'!$D$6:$I$6,0)) -> 38 | I104: =INDEX('Balance Sheet'!$D$9:$I$65,MATCH('3Statement Model'!$B104,'Balance Sheet'!$B$9:$B$65,0),MATCH('3Statement Model'!I$9,'Balance Sheet'!$D$6:$I$6,0)) -> 46 | J104: =I104 -> 46 | K104: =J104 -> 46 | L104: =K104 -> 46 | M104: =L104 -> 46 | N104: =M104 -> 46 | O104: =N104 -> 46 | P104: =O104 -> 46 | Q104: =P104 -> 46 | ... S104: =R104 -> 46
B105: Other Financial Assets | D105: =INDEX('Balance Sheet'!$D$9:$I$65,MATCH('3Statement Model'!$B105,'Balance Sheet'!$B$9:$B$65,0),MATCH('3Statement Model'!D$9,'Balance Sheet'!$D$6:$I$6,0)) -> 1420 | E105: =INDEX('Balance Sheet'!$D$9:$I$65,MATCH('3Statement Model'!$B105,'Balance Sheet'!$B$9:$B$65,0),MATCH('3Statement Model'!E$9,'Balance Sheet'!$D$6:$I$6,0)) -> 1188 | F105: =INDEX('Balance Sheet'!$D$9:$I$65,MATCH('3Statement Model'!$B105,'Balance Sheet'!$B$9:$B$65,0),MATCH('3Statement Model'!F$9,'Balance Sheet'!$D$6:$I$6,0)) -> 1089 | G105: =INDEX('Balance Sheet'!$D$9:$I$65,MATCH('3Statement Model'!$B105,'Balance Sheet'!$B$9:$B$65,0),MATCH('3Statement Model'!G$9,'Balance Sheet'!$D$6:$I$6,0)) -> 1386 | H105: =INDEX('Balance Sheet'!$D$9:$I$65,MATCH('3Statement Model'!$B105,'Balance Sheet'!$B$9:$B$65,0),MATCH('3Statement Model'!H$9,'Balance Sheet'!$D$6:$I$6,0)) -> 1425 | I105: =INDEX('Balance Sheet'!$D$9:$I$65,MATCH('3Statement Model'!$B105,'Balance Sheet'!$B$9:$B$65,0),MATCH('3Statement Model'!I$9,'Balance Sheet'!$D$6:$I$6,0)) -> 1488 | J105: =Schedules!K244 -> 672.38368 | K105: =Schedules!L244 -> 728.08852 | L105: =Schedules!M244 -> 789.02108 | M105: =Schedules!N244 -> 855.71283 | N105: =Schedules!O244 -> 928.75202 | O105: =Schedules!P244 -> 1013.5309 | P105: =Schedules!Q244 -> 1104.8163 | Q105: =Schedules!R244 -> 1198.6213 | ... S105: =Schedules!T244 -> 1391.0602
B106: OtherCurrentAssets | D106: =INDEX('Balance Sheet'!$D$9:$I$65,MATCH('3Statement Model'!$B106,'Balance Sheet'!$B$9:$B$65,0),MATCH('3Statement Model'!D$9,'Balance Sheet'!$D$6:$I$6,0)) -> 619 | E106: =INDEX('Balance Sheet'!$D$9:$I$65,MATCH('3Statement Model'!$B106,'Balance Sheet'!$B$9:$B$65,0),MATCH('3Statement Model'!E$9,'Balance Sheet'!$D$6:$I$6,0)) -> 514 | F106: =INDEX('Balance Sheet'!$D$9:$I$65,MATCH('3Statement Model'!$B106,'Balance Sheet'!$B$9:$B$65,0),MATCH('3Statement Model'!F$9,'Balance Sheet'!$D$6:$I$6,0)) -> 701 | G106: =INDEX('Balance Sheet'!$D$9:$I$65,MATCH('3Statement Model'!$B106,'Balance Sheet'!$B$9:$B$65,0),MATCH('3Statement Model'!G$9,'Balance Sheet'!$D$6:$I$6,0)) -> 757 | H106: =INDEX('Balance Sheet'!$D$9:$I$65,MATCH('3Statement Model'!$B106,'Balance Sheet'!$B$9:$B$65,0),MATCH('3Statement Model'!H$9,'Balance Sheet'!$D$6:$I$6,0)) -> 725 | I106: =INDEX('Balance Sheet'!$D$9:$I$65,MATCH('3Statement Model'!$B106,'Balance Sheet'!$B$9:$B$65,0),MATCH('3Statement Model'!I$9,'Balance Sheet'!$D$6:$I$6,0)) -> 978 | J106: =Schedules!K229 -> 686.1058 | K106: =Schedules!L229 -> 746.3747 | L106: =Schedules!M229 -> 812.58608 | M106: =Schedules!N229 -> 885.37282 | N106: =Schedules!O229 -> 965.43869 | O106: =Schedules!P229 -> 1053.5665 | P106: =Schedules!Q229 -> 1148.4577 | Q106: =Schedules!R229 -> 1245.9681 | ... S106: =Schedules!T229 -> 1446.0085
B107: Total Current Assets | D107: =INDEX('Balance Sheet'!$D$9:$I$65,MATCH('3Statement Model'!$B107,'Balance Sheet'!$B$9:$B$65,0),MATCH('3Statement Model'!D$9,'Balance Sheet'!$D$6:$I$6,0)) -> 12321 | E107: =INDEX('Balance Sheet'!$D$9:$I$65,MATCH('3Statement Model'!$B107,'Balance Sheet'!$B$9:$B$65,0),MATCH('3Statement Model'!E$9,'Balance Sheet'!$D$6:$I$6,0)) -> 14217 | F107: =INDEX('Balance Sheet'!$D$9:$I$65,MATCH('3Statement Model'!$B107,'Balance Sheet'!$B$9:$B$65,0),MATCH('3Statement Model'!F$9,'Balance Sheet'!$D$6:$I$6,0)) -> 15522 | G107: =INDEX('Balance Sheet'!$D$9:$I$65,MATCH('3Statement Model'!$B107,'Balance Sheet'!$B$9:$B$65,0),MATCH('3Statement Model'!G$9,'Balance Sheet'!$D$6:$I$6,0)) -> 16998 | H107: =INDEX('Balance Sheet'!$D$9:$I$65,MATCH('3Statement Model'!$B107,'Balance Sheet'!$B$9:$B$65,0),MATCH('3Statement Model'!H$9,'Balance Sheet'!$D$6:$I$6,0)) -> 21324 | I107: =INDEX('Balance Sheet'!$D$9:$I$65,MATCH('3Statement Model'!$B107,'Balance Sheet'!$B$9:$B$65,0),MATCH('3Statement Model'!I$9,'Balance Sheet'!$D$6:$I$6,0)) -> 22051 | J107: =SUM(J98:J106) -> 25761.969 | K107: =SUM(K98:K106) -> 27159.998 | L107: =SUM(L98:L106) -> 28480.3 | M107: =SUM(M98:M106) -> 29692.651 | N107: =SUM(N98:N106) -> 30760.801 | O107: =SUM(O98:O106) -> 31741.489 | P107: =SUM(P98:P106) -> 32466.14 | Q107: =SUM(Q98:Q106) -> 32803.399 | ... S107: =SUM(S98:S106) -> 32088.142
B109: Total Assets | D109: =INDEX('Balance Sheet'!$D$9:$I$65,MATCH('3Statement Model'!$B109,'Balance Sheet'!$B$9:$B$65,0),MATCH('3Statement Model'!D$9,'Balance Sheet'!$D$6:$I$6,0)) -> 20153 | E109: =INDEX('Balance Sheet'!$D$9:$I$65,MATCH('3Statement Model'!$B109,'Balance Sheet'!$B$9:$B$65,0),MATCH('3Statement Model'!E$9,'Balance Sheet'!$D$6:$I$6,0)) -> 68757 | F109: =INDEX('Balance Sheet'!$D$9:$I$65,MATCH('3Statement Model'!$B109,'Balance Sheet'!$B$9:$B$65,0),MATCH('3Statement Model'!F$9,'Balance Sheet'!$D$6:$I$6,0)) -> 70517 | G109: =INDEX('Balance Sheet'!$D$9:$I$65,MATCH('3Statement Model'!$B109,'Balance Sheet'!$B$9:$B$65,0),MATCH('3Statement Model'!G$9,'Balance Sheet'!$D$6:$I$6,0)) -> 73087 | H109: =INDEX('Balance Sheet'!$D$9:$I$65,MATCH('3Statement Model'!$B109,'Balance Sheet'!$B$9:$B$65,0),MATCH('3Statement Model'!H$9,'Balance Sheet'!$D$6:$I$6,0)) -> 78499 | I109: =INDEX('Balance Sheet'!$D$9:$I$65,MATCH('3Statement Model'!$B109,'Balance Sheet'!$B$9:$B$65,0),MATCH('3Statement Model'!I$9,'Balance Sheet'!$D$6:$I$6,0)) -> 79880 | J109: =J107+J95 -> 84762.475 | K109: =K107+K95 -> 87080.195 | L109: =L107+L95 -> 89364.57 | M109: =M107+M95 -> 91591.628 | N109: =N107+N95 -> 93732.159 | O109: =O107+O95 -> 95854.711 | P109: =P107+P95 -> 97787.637 | Q109: =Q107+Q95 -> 99375.057 | ... S109: =S107+S95 -> 101216.99
B111: Check | D111: =D79-D109 -> 0 | E111: =E79-E109 -> 0 | F111: =F79-F109 -> 0 | G111: =G79-G109 -> 0 | H111: =H79-H109 -> 0 | I111: =I79-I109 -> 0 | J111: =J79-J109 -> 0 | K111: =K79-K109 -> 0 | ... S111: =S79-S109 -> 0
B113: Net Working Capital | D113: =Schedules!E270 -> 0 | E113: =Schedules!F270 -> 1271 | F113: =Schedules!G270 -> 1664 | G113: =Schedules!H270 -> 138 | H113: =Schedules!I270 -> 533 | I113: =Schedules!J270 -> -97 | J113: =Schedules!K270 -> -3853.7105 | K113: =Schedules!L270 -> -758.86218 | ... S113: =Schedules!T270 -> -687.52093
B114: Debtor Days | D114: =(D101/D13)*365 -> 10.541814 | E114: =(E101/E13)*365 -> 13.644425 | F114: =(F101/F13)*365 -> 15.56153 | G114: =(G101/G13)*365 -> 18.548193 | H114: =(H101/H13)*365 -> 17.690423 | I114: =(I101/I13)*365 -> 22.083538 | J114: =(J101/J13)*365 -> 18 | K114: =(K101/K13)*365 -> 16 | ... S114: =(S101/S13)*365 -> 16
B115: Inventory Days | D115: =(D98/-D14)*365 -> 55.312722 | E115: =(E98/-E14)*365 -> 58.982075 | F115: =(F98/-F14)*365 -> 58.093647 | G115: =(G98/-G14)*365 -> 48.922153 | H115: =(H98/-H14)*365 -> 49.328965 | I115: =(I98/-I14)*365 -> 52.700471 | J115: =(J98/-J14)*365 -> 60 | K115: =(K98/-K14)*365 -> 60 | ... S115: =(S98/-S14)*365 -> 60
B116: Creditor Days | D116: =(D72/-D14)*365 -> 150.62572 | E116: =(E72/-E14)*365 -> 145.05734 | F116: =(F72/-F14)*365 -> 128.61162 | G116: =(G72/-G14)*365 -> 110.1813 | H116: =(H72/-H14)*365 -> 128.60853 | I116: =(I72/-I14)*365 -> 135.06361 | J116: =(J72/-J14)*365 -> 160 | K116: =(K72/-K14)*365 -> 160 | ... S116: =(S72/-S14)*365 -> 160
B117: Other Current Assets % Sales | D117: =D106/D13 -> 0.01555941 | E117: =E106/E13 -> 0.010929659 | F117: =F106/F13 -> 0.013366129 | G117: =G106/G13 -> 0.012493811 | H117: =H106/H13 -> 0.011724562 | I117: =I106/I13 -> 0.015494051 | J117: =J106/J13 -> 0.01 | K117: =K106/K13 -> 0.01 | ... S117: =S106/S13 -> 0.01
B118: Other Current Liabilities % Sales | D118: =D74/D13 -> 0.010758364 | E118: =E74/E13 -> 0.01250319 | F118: =F74/F13 -> 0.012679709 | G118: =G74/G13 -> 0.012609341 | H118: =H74/H13 -> 0.01305065 | I118: =I74/I13 -> 0.015193042 | J118: =J74/J13 -> 0.013977436 | K118: =K74/K13 -> 0.012848774 | ... S118: =S74/S13 -> 0.0066320496
A120: # | B120: Cash Flow Statement
B122: A. CASH FLOWS FROM OPERATING ACTIVITIES
B124: Profit before tax | D124: =D37 -> 9173 | E124: =E37 -> 10606 | F124: =F37 -> 11874 | G124: =G37 -> 13355 | H124: =H37 -> 13866 | I124: =I37 -> 14415 | J124: =J37 -> 14999.732 | K124: =K37 -> 16356.879 | ... S124: =S37 -> 31237.818
B125: Adjustments for:
B126: Depreciation and amortisation expense | D126: =INDEX('Cash Flow Statement'!$C$7:$I$80,MATCH('3Statement Model'!$B126,'Cash Flow Statement'!$B$7:$B$80,0),MATCH('3Statement Model'!D$9,'Cash Flow Statement'!$C$6:$I$6,0)) -> 1002 | E126: =INDEX('Cash Flow Statement'!$C$7:$I$80,MATCH('3Statement Model'!$B126,'Cash Flow Statement'!$B$7:$B$80,0),MATCH('3Statement Model'!E$9,'Cash Flow Statement'!$C$6:$I$6,0)) -> 1134 | F126: =INDEX('Cash Flow Statement'!$C$7:$I$80,MATCH('3Statement Model'!$B126,'Cash Flow Statement'!$B$7:$B$80,0),MATCH('3Statement Model'!F$9,'Cash Flow Statement'!$C$6:$I$6,0)) -> 1106 | G126: =INDEX('Cash Flow Statement'!$C$7:$I$80,MATCH('3Statement Model'!$B126,'Cash Flow Statement'!$B$7:$B$80,0),MATCH('3Statement Model'!G$9,'Cash Flow Statement'!$C$6:$I$6,0)) -> 1152 | H126: =INDEX('Cash Flow Statement'!$C$7:$I$80,MATCH('3Statement Model'!$B126,'Cash Flow Statement'!$B$7:$B$80,0),MATCH('3Statement Model'!H$9,'Cash Flow Statement'!$C$6:$I$6,0)) -> 1216 | I126: =INDEX('Cash Flow Statement'!$C$7:$I$80,MATCH('3Statement Model'!$B126,'Cash Flow Statement'!$B$7:$B$80,0),MATCH('3Statement Model'!I$9,'Cash Flow Statement'!$C$6:$I$6,0)) -> 1363 | J126: =-J27 -> 1530.8597 | K126: =-K27 -> 1704.3912 | L126: =-L27 -> 1893.436 | M126: =-M27 -> 2099.5432 | N126: =-N27 -> 2324.4284 | O126: =-O27 -> 2570.264 | P126: =-P27 -> 2838.3243 | Q126: =-Q27 -> 3128.4551 | ... S126: =-S27 -> 3776.3996
B127: Interest income | D127: =INDEX('Cash Flow Statement'!$C$7:$I$80,MATCH('3Statement Model'!$B127,'Cash Flow Statement'!$B$7:$B$80,0),MATCH('3Statement Model'!D$9,'Cash Flow Statement'!$C$6:$I$6,0)) -> -492 | E127: =INDEX('Cash Flow Statement'!$C$7:$I$80,MATCH('3Statement Model'!$B127,'Cash Flow Statement'!$B$7:$B$80,0),MATCH('3Statement Model'!E$9,'Cash Flow Statement'!$C$6:$I$6,0)) -> -346 | F127: =INDEX('Cash Flow Statement'!$C$7:$I$80,MATCH('3Statement Model'!$B127,'Cash Flow Statement'!$B$7:$B$80,0),MATCH('3Statement Model'!F$9,'Cash Flow Statement'!$C$6:$I$6,0)) -> -198 | G127: =INDEX('Cash Flow Statement'!$C$7:$I$80,MATCH('3Statement Model'!$B127,'Cash Flow Statement'!$B$7:$B$80,0),MATCH('3Statement Model'!G$9,'Cash Flow Statement'!$C$6:$I$6,0)) -> -411 | H127: =INDEX('Cash Flow Statement'!$C$7:$I$80,MATCH('3Statement Model'!$B127,'Cash Flow Statement'!$B$7:$B$80,0),MATCH('3Statement Model'!H$9,'Cash Flow Statement'!$C$6:$I$6,0)) -> -546 | I127: =INDEX('Cash Flow Statement'!$C$7:$I$80,MATCH('3Statement Model'!$B127,'Cash Flow Statement'!$B$7:$B$80,0),MATCH('3Statement Model'!I$9,'Cash Flow Statement'!$C$6:$I$6,0)) -> -755 | J127: =I127 -> -755 | K127: =J127 -> -755 | L127: =K127 -> -755 | M127: =L127 -> -755 | N127: =M127 -> -755 | O127: =N127 -> -755 | P127: =O127 -> -755 | Q127: =P127 -> -755 | ... S127: =R127 -> -755
B128: Dividend income | D128: =INDEX('Cash Flow Statement'!$C$7:$I$80,MATCH('3Statement Model'!$B128,'Cash Flow Statement'!$B$7:$B$80,0),MATCH('3Statement Model'!D$9,'Cash Flow Statement'!$C$6:$I$6,0)) -> -1 | E128: =INDEX('Cash Flow Statement'!$C$7:$I$80,MATCH('3Statement Model'!$B128,'Cash Flow Statement'!$B$7:$B$80,0),MATCH('3Statement Model'!E$9,'Cash Flow Statement'!$C$6:$I$6,0)) -> -1 | F128: =INDEX('Cash Flow Statement'!$C$7:$I$80,MATCH('3Statement Model'!$B128,'Cash Flow Statement'!$B$7:$B$80,0),MATCH('3Statement Model'!F$9,'Cash Flow Statement'!$C$6:$I$6,0)) -> -1 | G128: =INDEX('Cash Flow Statement'!$C$7:$I$80,MATCH('3Statement Model'!$B128,'Cash Flow Statement'!$B$7:$B$80,0),MATCH('3Statement Model'!G$9,'Cash Flow Statement'!$C$6:$I$6,0)) -> -2 | H128: =INDEX('Cash Flow Statement'!$C$7:$I$80,MATCH('3Statement Model'!$B128,'Cash Flow Statement'!$B$7:$B$80,0),MATCH('3Statement Model'!H$9,'Cash Flow Statement'!$C$6:$I$6,0)) -> -3 | I128: =INDEX('Cash Flow Statement'!$C$7:$I$80,MATCH('3Statement Model'!$B128,'Cash Flow Statement'!$B$7:$B$80,0),MATCH('3Statement Model'!I$9,'Cash Flow Statement'!$C$6:$I$6,0)) -> - | J128: 0 | K128: 0 | L128: 0 | M128: 0 | N128: 0 | O128: 0 | P128: 0 | Q128: 0 | R128: 0 | S128: 0
...

Sheet CommonSize Statement
B2: ='Input Sheet'!C6 -> Hindustan Unilever Ltd.
B3: 3 Statement Model
I4: Current Case:
D8: Actual | J8: Explicit Forecast Period | O8: Maturity Period
B9: In Crs Unless Stated Otherwise | D9: 2020 | E9: =D9+1 -> 2021 | F9: =E9+1 -> 2022 | G9: =F9+1 -> 2023 | H9: =G9+1 -> 2024 | I9: =H9+1 -> 2025 | J9: =I9+1 -> 2026 | K9: =J9+1 -> 2027 | L9: =K9+1 -> 2028 | ... S9: =R9+1 -> 2035
A11: # | B11: Income Statement
B13: Revenue From Operations | D13: ='3Statement Model'!D13/'3Statement Model'!D$13 -> 1 | E13: ='3Statement Model'!E13/'3Statement Model'!E$13 -> 1 | F13: ='3Statement Model'!F13/'3Statement Model'!F$13 -> 1 | G13: ='3Statement Model'!G13/'3Statement Model'!G$13 -> 1 | H13: ='3Statement Model'!H13/'3Statement Model'!H$13 -> 1 | I13: ='3Statement Model'!I13/'3Statement Model'!I$13 -> 1 | J13: ='3Statement Model'!J13/'3Statement Model'!J$13 -> 1 | K13: ='3Statement Model'!K13/'3Statement Model'!K$13 -> 1 | ... S13: ='3Statement Model'!S13/'3Statement Model'!S$13 -> 1
B14: Less: Cost of Goods Sold | D14: ='3Statement Model'!D14/'3Statement Model'!D$13 -> -0.45896488 | E14: ='3Statement Model'!E14/'3Statement Model'!E$13 -> -0.47095347 | F14: ='3Statement Model'!F14/'3Statement Model'!F$13 -> -0.49069519 | G14: ='3Statement Model'!G14/'3Statement Model'!G$13 -> -0.52345271 | H14: ='3Statement Model'!H14/'3Statement Model'!H$13 -> -0.48127304 | I14: ='3Statement Model'!I14/'3Statement Model'!I$13 -> -0.48443466 | J14: ='3Statement Model'!J14/'3Statement Model'!J$13 -> -0.49 | K14: ='3Statement Model'!K14/'3Statement Model'!K$13 -> -0.48775 | ... S14: ='3Statement Model'!S14/'3Statement Model'!S$13 -> -0.481
B15: Gross Profit | D15: ='3Statement Model'!D15/'3Statement Model'!D$13 -> 0.54103512 | E15: ='3Statement Model'!E15/'3Statement Model'!E$13 -> 0.52904653 | F15: ='3Statement Model'!F15/'3Statement Model'!F$13 -> 0.50930481 | G15: ='3Statement Model'!G15/'3Statement Model'!G$13 -> 0.47654729 | H15: ='3Statement Model'!H15/'3Statement Model'!H$13 -> 0.51872696 | I15: ='3Statement Model'!I15/'3Statement Model'!I$13 -> 0.51556534 | J15: ='3Statement Model'!J15/'3Statement Model'!J$13 -> 0.51 | K15: ='3Statement Model'!K15/'3Statement Model'!K$13 -> 0.51225 | ... S15: ='3Statement Model'!S15/'3Statement Model'!S$13 -> 0.519
B17: Less: SG&A (Excluding Depriciation & Interest)
B18: Employee Benefit Expenses | D18: ='3Statement Model'!D18/'3Statement Model'!D$13 -> -0.045748184 | E18: ='3Statement Model'!E18/'3Statement Model'!E$13 -> -0.050140342 | F18: ='3Statement Model'!F18/'3Statement Model'!F$13 -> -0.048526103 | G18: ='3Statement Model'!G18/'3Statement Model'!G$13 -> -0.047103482 | H18: ='3Statement Model'!H18/'3Statement Model'!H$13 -> -0.048660974 | I18: ='3Statement Model'!I18/'3Statement Model'!I$13 -> -0.048747643 | J18: ='3Statement Model'!J18/'3Statement Model'!J$13 -> -0.048 | K18: ='3Statement Model'!K18/'3Statement Model'!K$13 -> -0.048 | ... S18: ='3Statement Model'!S18/'3Statement Model'!S$13 -> -0.048
B19: Othere Expenses | D19: ='3Statement Model'!D19/'3Statement Model'!D$13 -> -0.24741724 | E19: ='3Statement Model'!E19/'3Statement Model'!E$13 -> -0.23169176 | F19: ='3Statement Model'!F19/'3Statement Model'!F$13 -> -0.21563132 | G19: ='3Statement Model'!G19/'3Statement Model'!G$13 -> -0.19575838 | H19: ='3Statement Model'!H19/'3Statement Model'!H$13 -> -0.23390905 | I19: ='3Statement Model'!I19/'3Statement Model'!I$13 -> -0.23153942 | J19: ='3Statement Model'!J19/'3Statement Model'!J$13 -> -0.232 | K19: ='3Statement Model'!K19/'3Statement Model'!K$13 -> -0.232 | ... S19: ='3Statement Model'!S19/'3Statement Model'!S$13 -> -0.232
B20: Total SG&A | D20: ='3Statement Model'!D20/'3Statement Model'!D$13 -> -0.29316542 | E20: ='3Statement Model'!E20/'3Statement Model'!E$13 -> -0.2818321 | F20: ='3Statement Model'!F20/'3Statement Model'!F$13 -> -0.26415742 | G20: ='3Statement Model'!G20/'3Statement Model'!G$13 -> -0.24286186 | H20: ='3Statement Model'!H20/'3Statement Model'!H$13 -> -0.28257002 | I20: ='3Statement Model'!I20/'3Statement Model'!I$13 -> -0.28028707 | J20: ='3Statement Model'!J20/'3Statement Model'!J$13 -> -0.28 | K20: ='3Statement Model'!K20/'3Statement Model'!K$13 -> -0.28 | ... S20: ='3Statement Model'!S20/'3Statement Model'!S$13 -> -0.28
B22: EBITDA | D22: ='3Statement Model'!D22/'3Statement Model'!D$13 -> 0.24786969 | E22: ='3Statement Model'!E22/'3Statement Model'!E$13 -> 0.24721443 | F22: ='3Statement Model'!F22/'3Statement Model'!F$13 -> 0.24514739 | G22: ='3Statement Model'!G22/'3Statement Model'!G$13 -> 0.23368543 | H22: ='3Statement Model'!H22/'3Statement Model'!H$13 -> 0.23615693 | I22: ='3Statement Model'!I22/'3Statement Model'!I$13 -> 0.23527828 | J22: ='3Statement Model'!J22/'3Statement Model'!J$13 -> 0.23 | K22: ='3Statement Model'!K22/'3Statement Model'!K$13 -> 0.23225 | ... S22: ='3Statement Model'!S22/'3Statement Model'!S$13 -> 0.239
B25: Less: Depreciation & Amortization | D25: ='3Statement Model'!D27/'3Statement Model'!D$13 -> -0.025186638 | E25: ='3Statement Model'!E27/'3Statement Model'!E$13 -> -0.022837459 | F25: ='3Statement Model'!F27/'3Statement Model'!F$13 -> -0.020802349 | G25: ='3Statement Model'!G27/'3Statement Model'!G$13 -> -0.018765473 | H25: ='3Statement Model'!H27/'3Statement Model'!H$13 -> -0.01966492 | I25: ='3Statement Model'!I27/'3Statement Model'!I$13 -> -0.021466707 | J25: ='3Statement Model'!J27/'3Statement Model'!J$13 -> -0.022312298 | K25: ='3Statement Model'!K27/'3Statement Model'!K$13 -> -0.022835597 | ... S25: ='3Statement Model'!S27/'3Statement Model'!S$13 -> -0.026116026
B26: Earnings Before Interest & Tax | D26: ='3Statement Model'!D28/'3Statement Model'!D$13 -> 0.22268306 | E26: ='3Statement Model'!E28/'3Statement Model'!E$13 -> 0.22437697 | F26: ='3Statement Model'!F28/'3Statement Model'!F$13 -> 0.22434504 | G26: ='3Statement Model'!G28/'3Statement Model'!G$13 -> 0.21491995 | H26: ='3Statement Model'!H28/'3Statement Model'!H$13 -> 0.21649201 | I26: ='3Statement Model'!I28/'3Statement Model'!I$13 -> 0.21381157 | J26: ='3Statement Model'!J28/'3Statement Model'!J$13 -> 0.2076877 | K26: ='3Statement Model'!K28/'3Statement Model'!K$13 -> 0.2094144 | ... S26: ='3Statement Model'!S28/'3Statement Model'!S$13 -> 0.21288397
B28: Less: Finance Costs | D28: ='3Statement Model'!D32/'3Statement Model'!D$13 -> -0.002966091 | E28: ='3Statement Model'!E32/'3Statement Model'!E$13 -> -0.0024878796 | F28: ='3Statement Model'!F32/'3Statement Model'!F$13 -> -0.0020211265 | G28: ='3Statement Model'!G32/'3Statement Model'!G$13 -> -0.0018814986 | H28: ='3Statement Model'!H32/'3Statement Model'!H$13 -> -0.0054013843 | I28: ='3Statement Model'!I32/'3Statement Model'!I$13 -> -0.0062578223 | J28: ='3Statement Model'!J32/'3Statement Model'!J$13 -> -0.0038892266 | K28: ='3Statement Model'!K32/'3Statement Model'!K$13 -> -0.0038892266 | ... S28: ='3Statement Model'!S32/'3Statement Model'!S$13 -> -0.0038892266
B29: Add: Other Income | D29: ='3Statement Model'!D33/'3Statement Model'!D$13 -> 0.015886183 | E29: ='3Statement Model'!E33/'3Statement Model'!E$13 -> 0.0087182104 | F29: ='3Statement Model'!F33/'3Statement Model'!F$13 -> 0.0049193456 | G29: ='3Statement Model'!G33/'3Statement Model'!G$13 -> 0.0084502393 | H29: ='3Statement Model'!H33/'3Statement Model'!H$13 -> 0.013115337 | I29: ='3Statement Model'!I33/'3Statement Model'!I$13 -> 0.016111912 | J29: ='3Statement Model'!J33/'3Statement Model'!J$13 -> 0.014822787 | K29: ='3Statement Model'!K33/'3Statement Model'!K$13 -> 0.013625864 | ... S29: ='3Statement Model'!S33/'3Statement Model'!S$13 -> 0.0070331537
B30: Add/(Less): Share Of Profit/Loss Of Associates | D30: ='3Statement Model'!D34/'3Statement Model'!D$13 -> 0 | E30: ='3Statement Model'!E34/'3Statement Model'!E$13 -> 0 | F30: ='3Statement Model'!F34/'3Statement Model'!F$13 -> 0 | G30: ='3Statement Model'!G34/'3Statement Model'!G$13 -> -1.6504374e-05 | H30: ='3Statement Model'!H34/'3Statement Model'!H$13 -> -6.4687237e-05 | I30: ='3Statement Model'!I34/'3Statement Model'!I$13 -> -0.0001267407 | J30: ='3Statement Model'!J34/'3Statement Model'!J$13 -> 0 | K30: ='3Statement Model'!K34/'3Statement Model'!K$13 -> 0 | ... S30: ='3Statement Model'!S34/'3Statement Model'!S$13 -> 0
B31: Add/(Less): Exceptional Items | D31: ='3Statement Model'!D35/'3Statement Model'!D$13 -> -0.005027273 | E31: ='3Statement Model'!E35/'3Statement Model'!E$13 -> -0.0050820788 | F31: ='3Statement Model'!F35/'3Statement Model'!F$13 -> -0.00083895817 | G31: ='3Statement Model'!G35/'3Statement Model'!G$13 -> -0.0010562799 | H31: ='3Statement Model'!H35/'3Statement Model'!H$13 -> 9.7030856e-05 | I31: ='3Statement Model'!I35/'3Statement Model'!I$13 -> 0.0048319894 | J31: ='3Statement Model'!J35/'3Statement Model'!J$13 -> 0 | K31: ='3Statement Model'!K35/'3Statement Model'!K$13 -> 0 | ... S31: ='3Statement Model'!S35/'3Statement Model'!S$13 -> 0
B33: Earnings Before Tax | D33: ='3Statement Model'!D37/'3Statement Model'!D$13 -> 0.23057587 | E33: ='3Statement Model'!E37/'3Statement Model'!E$13 -> 0.22552522 | F33: ='3Statement Model'!F37/'3Statement Model'!F$13 -> 0.2264043 | G33: ='3Statement Model'!G37/'3Statement Model'!G$13 -> 0.22041591 | H33: ='3Statement Model'!H37/'3Statement Model'!H$13 -> 0.22423831 | I33: ='3Statement Model'!I37/'3Statement Model'!I$13 -> 0.22837091 | J33: ='3Statement Model'!J37/'3Statement Model'!J$13 -> 0.21862126 | K33: ='3Statement Model'!K37/'3Statement Model'!K$13 -> 0.21915104 | ... S33: ='3Statement Model'!S37/'3Statement Model'!S$13 -> 0.2160279
B35: Less: Tax Expenses | D35: ='3Statement Model'!D39/'3Statement Model'!D$13 -> -0.060553503 | E35: ='3Statement Model'!E39/'3Statement Model'!E$13 -> -0.055413796 | F35: ='3Statement Model'!F39/'3Statement Model'!F$13 -> -0.056953819 | G35: ='3Statement Model'!G39/'3Statement Model'!G$13 -> -0.0528305 | H35: ='3Statement Model'!H39/'3Statement Model'!H$13 -> -0.058930073 | I35: ='3Statement Model'!I39/'3Statement Model'!I$13 -> -0.05931465 | J35: ='3Statement Model'!J39/'3Statement Model'!J$13 -> -0.065586379 | K35: ='3Statement Model'!K39/'3Statement Model'!K$13 -> -0.065745312 | ... S35: ='3Statement Model'!S39/'3Statement Model'!S$13 -> -0.06480837
B36: Net Income | D36: ='3Statement Model'!D40/'3Statement Model'!D$13 -> 0.17002237 | E36: ='3Statement Model'!E40/'3Statement Model'!E$13 -> 0.17011142 | F36: ='3Statement Model'!F40/'3Statement Model'!F$13 -> 0.16945048 | G36: ='3Statement Model'!G40/'3Statement Model'!G$13 -> 0.16758541 | H36: ='3Statement Model'!H40/'3Statement Model'!H$13 -> 0.16530823 | I36: ='3Statement Model'!I40/'3Statement Model'!I$13 -> 0.16905626 | J36: ='3Statement Model'!J40/'3Statement Model'!J$13 -> 0.15303488 | K36: ='3Statement Model'!K40/'3Statement Model'!K$13 -> 0.15340573 | ... S36: ='3Statement Model'!S40/'3Statement Model'!S$13 -> 0.15121953
A38: # | B38: Balance Sheet
B40: EQUITIES AND LIABILITIES
B41: SHAREHOLDER'S FUNDS
B42: Equity Share Capital | D42: ='3Statement Model'!D53/'3Statement Model'!D$79 -> 0.010718007 | E42: ='3Statement Model'!E53/'3Statement Model'!E$79 -> 0.0034178338 | F42: ='3Statement Model'!F53/'3Statement Model'!F$79 -> 0.0033325297 | G42: ='3Statement Model'!G53/'3Statement Model'!G$79 -> 0.0032153461 | H42: ='3Statement Model'!H53/'3Statement Model'!H$79 -> 0.0029936687 | I42: ='3Statement Model'!I53/'3Statement Model'!I$79 -> 0.0029419129 | J42: ='3Statement Model'!J53/'3Statement Model'!J$79 -> 0.0027724533 | K42: ='3Statement Model'!K53/'3Statement Model'!K$79 -> 0.0026986618 | ... S42: ='3Statement Model'!S53/'3Statement Model'!S$79 -> 0.0023217446
B43: Other Equity | D43: ='3Statement Model'!D54/'3Statement Model'!D$79 -> 0.3976083 | E43: ='3Statement Model'!E54/'3Statement Model'!E$79 -> 0.68995157 | F43: ='3Statement Model'!F54/'3Statement Model'!F$79 -> 0.69240041 | G43: ='3Statement Model'!G54/'3Statement Model'!G$79 -> 0.68506027 | H43: ='3Statement Model'!H54/'3Statement Model'!H$79 -> 0.64947324 | I43: ='3Statement Model'!I54/'3Statement Model'!I$79 -> 0.61551077 | J43: ='3Statement Model'!J54/'3Statement Model'!J$79 -> 0.59244354 | K43: ='3Statement Model'!K54/'3Statement Model'!K$79 -> 0.58719398 | ... S43: ='3Statement Model'!S54/'3Statement Model'!S$79 -> 0.48055147
B44: Total Share Holder's Equity | D44: ='3Statement Model'!D55/'3Statement Model'!D$79 -> 0.4083263 | E44: ='3Statement Model'!E55/'3Statement Model'!E$79 -> 0.6933694 | F44: ='3Statement Model'!F55/'3Statement Model'!F$79 -> 0.69573294 | G44: ='3Statement Model'!G55/'3Statement Model'!G$79 -> 0.68827562 | H44: ='3Statement Model'!H55/'3Statement Model'!H$79 -> 0.65246691 | I44: ='3Statement Model'!I55/'3Statement Model'!I$79 -> 0.61845268 | J44: ='3Statement Model'!J55/'3Statement Model'!J$79 -> 0.595216 | K44: ='3Statement Model'!K55/'3Statement Model'!K$79 -> 0.58989264 | ... S44: ='3Statement Model'!S55/'3Statement Model'!S$79 -> 0.48287322
B45: Minority Interest | D45: ='3Statement Model'!D56/'3Statement Model'!D$79 -> 0.00084354687 | E45: ='3Statement Model'!E56/'3Statement Model'!E$79 -> 0.00029087947 | F45: ='3Statement Model'!F56/'3Statement Model'!F$79 -> 0.00036870542 | G45: ='3Statement Model'!G56/'3Statement Model'!G$79 -> 0.0029827466 | H45: ='3Statement Model'!H56/'3Statement Model'!H$79 -> 0.0026114982 | I45: ='3Statement Model'!I56/'3Statement Model'!I$79 -> 0.0025913871 | J45: ='3Statement Model'!J56/'3Statement Model'!J$79 -> 0.0024421184 | K45: ='3Statement Model'!K56/'3Statement Model'!K$79 -> 0.0023771192 | ... S45: ='3Statement Model'!S56/'3Statement Model'!S$79 -> 0.0020451112
B46: Total Equity | D46: ='3Statement Model'!D57/'3Statement Model'!D$79 -> 0.40916985 | E46: ='3Statement Model'!E57/'3Statement Model'!E$79 -> 0.69366028 | F46: ='3Statement Model'!F57/'3Statement Model'!F$79 -> 0.69610165 | G46: ='3Statement Model'!G57/'3Statement Model'!G$79 -> 0.69125836 | H46: ='3Statement Model'!H57/'3Statement Model'!H$79 -> 0.65507841 | I46: ='3Statement Model'!I57/'3Statement Model'!I$79 -> 0.62104407 | J46: ='3Statement Model'!J57/'3Statement Model'!J$79 -> 0.59765812 | K46: ='3Statement Model'!K57/'3Statement Model'!K$79 -> 0.59226976 | ... S46: ='3Statement Model'!S57/'3Statement Model'!S$79 -> 0.48491833
B48: NON-CURRENT LIABILITIES
B49: Financial Liabilities
B50: Lease Liabilities (L) | D50: ='3Statement Model'!D61/'3Statement Model'!D$79 -> 0 | E50: ='3Statement Model'!E61/'3Statement Model'!E$79 -> 0 | F50: ='3Statement Model'!F61/'3Statement Model'!F$79 -> 0.010508104 | G50: ='3Statement Model'!G61/'3Statement Model'!G$79 -> 0.011041635 | H50: ='3Statement Model'!H61/'3Statement Model'!H$79 -> 0.014089351 | I50: ='3Statement Model'!I61/'3Statement Model'!I$79 -> 0.015560841 | J50: ='3Statement Model'!J61/'3Statement Model'!J$79 -> 0.016188904 | K50: ='3Statement Model'!K61/'3Statement Model'!K$79 -> 0.017142238 | ... S50: ='3Statement Model'!S61/'3Statement Model'!S$79 -> 0.028572446
B51: Other Financial Liabilities (L) | D51: ='3Statement Model'!D62/'3Statement Model'!D$79 -> 0.046593559 | E51: ='3Statement Model'!E62/'3Statement Model'!E$79 -> 0.014936661 | F51: ='3Statement Model'!F62/'3Statement Model'!F$79 -> 0.005062609 | G51: ='3Statement Model'!G62/'3Statement Model'!G$79 -> 0.011766798 | H51: ='3Statement Model'!H62/'3Statement Model'!H$79 -> 0.0091083963 | I51: ='3Statement Model'!I62/'3Statement Model'!I$79 -> 0.0085127692 | J51: ='3Statement Model'!J62/'3Statement Model'!J$79 -> 0.0080224179 | K51: ='3Statement Model'!K62/'3Statement Model'!K$79 -> 0.0078088938 | ... S51: ='3Statement Model'!S62/'3Statement Model'!S$79 -> 0.0067182398
B52: Provisions (L) | D52: ='3Statement Model'!D63/'3Statement Model'!D$79 -> 0.060884236 | E52: ='3Statement Model'!E63/'3Statement Model'!E$79 -> 0.022950391 | F52: ='3Statement Model'!F63/'3Statement Model'!F$79 -> 0.022405945 | G52: ='3Statement Model'!G63/'3Statement Model'!G$79 -> 0.018649007 | H52: ='3Statement Model'!H63/'3Statement Model'!H$79 -> 0.020076689 | I52: ='3Statement Model'!I63/'3Statement Model'!I$79 -> 0.019128693 | J52: ='3Statement Model'!J63/'3Statement Model'!J$79 -> 0.018026845 | K52: ='3Statement Model'!K63/'3Statement Model'!K$79 -> 0.017547044 | ... S52: ='3Statement Model'!S63/'3Statement Model'!S$79 -> 0.01509628
B53: Deferred Tax Liabilities [Net] | D53: ='3Statement Model'!D64/'3Statement Model'!D$79 -> 0 | E53: ='3Statement Model'!E64/'3Statement Model'!E$79 -> 0.087089315 | F53: ='3Statement Model'!F64/'3Statement Model'!F$79 -> 0.087085384 | G53: ='3Statement Model'!G64/'3Statement Model'!G$79 -> 0.087854201 | H53: ='3Statement Model'!H64/'3Statement Model'!H$79 -> 0.083529726 | I53: ='3Statement Model'!I64/'3Statement Model'!I$79 -> 0.083688032 | J53: ='3Statement Model'!J64/'3Statement Model'!J$79 -> 0.078867447 | K53: ='3Statement Model'!K64/'3Statement Model'!K$79 -> 0.076768317 | ... S53: ='3Statement Model'!S64/'3Statement Model'!S$79 -> 0.066046225
B54: Non-Current Tax Liabities (Net) | D54: ='3Statement Model'!D65/'3Statement Model'!D$79 -> 0.021039051 | E54: ='3Statement Model'!E65/'3Statement Model'!E$79 -> 0.019881612 | F54: ='3Statement Model'!F65/'3Statement Model'!F$79 -> 0.018874881 | G54: ='3Statement Model'!G65/'3Statement Model'!G$79 -> 0.014859004 | H54: ='3Statement Model'!H65/'3Statement Model'!H$79 -> 0.054051644 | I54: ='3Statement Model'!I65/'3Statement Model'!I$79 -> 0.045042564 | J54: ='3Statement Model'!J65/'3Statement Model'!J$79 -> 0.042448029 | K54: ='3Statement Model'!K65/'3Statement Model'!K$79 -> 0.041318235 | ... S54: ='3Statement Model'!S65/'3Statement Model'!S$79 -> 0.035547392
B55: Total Non-Current Liabilities | D55: ='3Statement Model'!D66/'3Statement Model'!D$79 -> 0.12851685 | E55: ='3Statement Model'!E66/'3Statement Model'!E$79 -> 0.14485798 | F55: ='3Statement Model'!F66/'3Statement Model'!F$79 -> 0.14393692 | G55: ='3Statement Model'!G66/'3Statement Model'!G$79 -> 0.14417065 | H55: ='3Statement Model'!H66/'3Statement Model'!H$79 -> 0.18085581 | I55: ='3Statement Model'!I66/'3Statement Model'!I$79 -> 0.1719329 | J55: ='3Statement Model'!J66/'3Statement Model'!J$79 -> 0.16355364 | K55: ='3Statement Model'!K66/'3Statement Model'!K$79 -> 0.16058473 | ... S55: ='3Statement Model'!S66/'3Statement Model'!S$79 -> 0.15198058
B57: CURRENT LIABILITIES
B58: Financial Liabilities
B59: Short Term Borrowings | D59: ='3Statement Model'!D70/'3Statement Model'!D$79 -> 0 | E59: ='3Statement Model'!E70/'3Statement Model'!E$79 -> 0 | F59: ='3Statement Model'!F70/'3Statement Model'!F$79 -> 0 | G59: ='3Statement Model'!G70/'3Statement Model'!G$79 -> 0.0013408677 | H59: ='3Statement Model'!H70/'3Statement Model'!H$79 -> 0.00016560721 | I59: ='3Statement Model'!I70/'3Statement Model'!I$79 -> 1.2518778e-05 | J59: ='3Statement Model'!J70/'3Statement Model'!J$79 -> 0 | K59: ='3Statement Model'!K70/'3Statement Model'!K$79 -> 0 | ... S59: ='3Statement Model'!S70/'3Statement Model'!S$79 -> 0
B60: Lease Liabilities (S) | D60: ='3Statement Model'!D71/'3Statement Model'!D$79 -> 0 | E60: ='3Statement Model'!E71/'3Statement Model'!E$79 -> 0 | F60: ='3Statement Model'!F71/'3Statement Model'!F$79 -> 0.0042826552 | G60: ='3Statement Model'!G71/'3Statement Model'!G$79 -> 0.0042962497 | H60: ='3Statement Model'!H71/'3Statement Model'!H$79 -> 0.0046497408 | I60: ='3Statement Model'!I71/'3Statement Model'!I$79 -> 0.0050575864 | J60: ='3Statement Model'!J71/'3Statement Model'!J$79 -> 0.0080944522 | K60: ='3Statement Model'!K71/'3Statement Model'!K$79 -> 0.0085711189 | ... S60: ='3Statement Model'!S71/'3Statement Model'!S$79 -> 0.014286223
B61: Trade Payables | D61: ='3Statement Model'!D72/'3Statement Model'!D$79 -> 0.37388974 | E61: ='3Statement Model'!E72/'3Statement Model'!E$79 -> 0.12801606 | F61: ='3Statement Model'!F72/'3Statement Model'!F$79 -> 0.12859311 | G61: ='3Statement Model'!G72/'3Statement Model'!G$79 -> 0.13099457 | H61: ='3Statement Model'!H72/'3Statement Model'!H$79 -> 0.13358132 | I61: ='3Statement Model'!I72/'3Statement Model'!I$79 -> 0.14164997 | J61: ='3Statement Model'!J72/'3Statement Model'!J$79 -> 0.1738644 | K61: ='3Statement Model'!K72/'3Statement Model'!K$79 -> 0.18325757 | ... S61: ='3Statement Model'!S72/'3Statement Model'!S$79 -> 0.30122404
B62: Other Financial Liabilities (S) | D62: ='3Statement Model'!D73/'3Statement Model'!D$79 -> 0.046246216 | E62: ='3Statement Model'!E73/'3Statement Model'!E$79 -> 0.017540032 | F62: ='3Statement Model'!F73/'3Statement Model'!F$79 -> 0.012748699 | G62: ='3Statement Model'!G73/'3Statement Model'!G$79 -> 0.012163586 | H62: ='3Statement Model'!H73/'3Statement Model'!H$79 -> 0.011057466 | I62: ='3Statement Model'!I73/'3Statement Model'!I$79 -> 0.016024036 | J62: ='3Statement Model'!J73/'3Statement Model'!J$79 -> 0.015101022 | K62: ='3Statement Model'!K73/'3Statement Model'!K$79 -> 0.014699094 | ... S62: ='3Statement Model'!S73/'3Statement Model'!S$79 -> 0.012646098
B63: Other Current Liabilities | D63: ='3Statement Model'!D74/'3Statement Model'!D$79 -> 0.021237533 | E63: ='3Statement Model'!E74/'3Statement Model'!E$79 -> 0.0085518565 | F63: ='3Statement Model'!F74/'3Statement Model'!F$79 -> 0.0094303501 | G63: ='3Statement Model'!G74/'3Statement Model'!G$79 -> 0.010453295 | H63: ='3Statement Model'!H74/'3Statement Model'!H$79 -> 0.010280386 | I63: ='3Statement Model'!I74/'3Statement Model'!I$79 -> 0.012005508 | J63: ='3Statement Model'!J74/'3Statement Model'!J$79 -> 0.011313969 | K63: ='3Statement Model'!K74/'3Statement Model'!K$79 -> 0.011012837 | ... S63: ='3Statement Model'!S74/'3Statement Model'!S$79 -> 0.0094746941
B64: Provisions (S) | D64: ='3Statement Model'!D75/'3Statement Model'!D$79 -> 0.02093981 | E64: ='3Statement Model'!E75/'3Statement Model'!E$79 -> 0.0073737947 | F64: ='3Statement Model'!F75/'3Statement Model'!F$79 -> 0.0049066183 | G64: ='3Statement Model'!G75/'3Statement Model'!G$79 -> 0.005322424 | H64: ='3Statement Model'!H75/'3Statement Model'!H$79 -> 0.0043312654 | I64: ='3Statement Model'!I75/'3Statement Model'!I$79 -> 0.0084501753 | J64: ='3Statement Model'!J75/'3Statement Model'!J$79 -> 0.0079634295 | K64: ='3Statement Model'!K75/'3Statement Model'!K$79 -> 0.0077514755 | ... S64: ='3Statement Model'!S75/'3Statement Model'!S$79 -> 0.006668841
B65: Current Tax Liabilities | D65: ='3Statement Model'!D76/'3Statement Model'!D$79 -> 0 | E65: ='3Statement Model'!E76/'3Statement Model'!E$79 -> 0 | F65: ='3Statement Model'!F76/'3Statement Model'!F$79 -> 0 | G65: ='3Statement Model'!G76/'3Statement Model'!G$79 -> 0 | H65: ='3Statement Model'!H76/'3Statement Model'!H$79 -> 0 | I65: ='3Statement Model'!I76/'3Statement Model'!I$79 -> 0.023823235 | J65: ='3Statement Model'!J76/'3Statement Model'!J$79 -> 0.022450972 | K65: ='3Statement Model'!K76/'3Statement Model'!K$79 -> 0.021853419 | ... S65: ='3Statement Model'!S76/'3Statement Model'!S$79 -> 0.018801192
B66: Total Current Liabilities | D66: ='3Statement Model'!D77/'3Statement Model'!D$79 -> 0.4623133 | E66: ='3Statement Model'!E77/'3Statement Model'!E$79 -> 0.16148174 | F66: ='3Statement Model'!F77/'3Statement Model'!F$79 -> 0.15996143 | G66: ='3Statement Model'!G77/'3Statement Model'!G$79 -> 0.16457099 | H66: ='3Statement Model'!H77/'3Statement Model'!H$79 -> 0.16406578 | I66: ='3Statement Model'!I77/'3Statement Model'!I$79 -> 0.20702303 | J66: ='3Statement Model'!J77/'3Statement Model'!J$79 -> 0.23878824 | K66: ='3Statement Model'!K77/'3Statement Model'!K$79 -> 0.24714551 | ... S66: ='3Statement Model'!S77/'3Statement Model'!S$79 -> 0.36310109
B68: Total Equity and Liabilities | D68: ='3Statement Model'!D79/'3Statement Model'!D$79 -> 1 | E68: ='3Statement Model'!E79/'3Statement Model'!E$79 -> 1 | F68: ='3Statement Model'!F79/'3Statement Model'!F$79 -> 1 | G68: ='3Statement Model'!G79/'3Statement Model'!G$79 -> 1 | H68: ='3Statement Model'!H79/'3Statement Model'!H$79 -> 1 | I68: ='3Statement Model'!I79/'3Statement Model'!I$79 -> 1 | J68: ='3Statement Model'!J79/'3Statement Model'!J$79 -> 1 | K68: ='3Statement Model'!K79/'3Statement Model'!K$79 -> 1 | ... S68: ='3Statement Model'!S79/'3Statement Model'!S$79 -> 1
B70: ASSETS
B71: NON-CURRENT ASSETS
B72: Property, Plant & Equipments | D72: ='3Statement Model'!D83/'3Statement Model'!D$109 -> 0.20389024 | E72: ='3Statement Model'!E83/'3Statement Model'!E$109 -> 0.073694315 | F72: ='3Statement Model'!F83/'3Statement Model'!F$109 -> 0.072337167 | G72: ='3Statement Model'!G83/'3Statement Model'!G$109 -> 0.078905961 | H72: ='3Statement Model'!H83/'3Statement Model'!H$109 -> 0.083020166 | I72: ='3Statement Model'!I83/'3Statement Model'!I$109 -> 0.086892839 | J72: ='3Statement Model'!J83/'3Statement Model'!J$109 -> 0.084960846 | K72: ='3Statement Model'!K83/'3Statement Model'!K$109 -> 0.085939261 | ... S72: ='3Statement Model'!S83/'3Statement Model'!S$109 -> 0.10673551
B73: Right-of-Use Asset | D73: ='3Statement Model'!D84/'3Statement Model'!D$109 -> 0.042226964 | E73: ='3Statement Model'!E84/'3Statement Model'!E$109 -> 0.015256628 | F73: ='3Statement Model'!F84/'3Statement Model'!F$109 -> 0.015145284 | G73: ='3Statement Model'!G84/'3Statement Model'!G$109 -> 0.016172507 | H73: ='3Statement Model'!H84/'3Statement Model'!H$109 -> 0.01928687 | I73: ='3Statement Model'!I84/'3Statement Model'!I$109 -> 0.021081622 | J73: ='3Statement Model'!J84/'3Statement Model'!J$109 -> 0.029756799 | K73: ='3Statement Model'!K84/'3Statement Model'!K$109 -> 0.03593954 | ... S73: ='3Statement Model'!S84/'3Statement Model'!S$109 -> 0.085243332
B74: Capital Work-In-Progress | D74: ='3Statement Model'!D85/'3Statement Model'!D$109 -> 0.029623381 | E74: ='3Statement Model'!E85/'3Statement Model'!E$109 -> 0.01083526 | F74: ='3Statement Model'!F85/'3Statement Model'!F$109 -> 0.018619624 | G74: ='3Statement Model'!G85/'3Statement Model'!G$109 -> 0.015488391 | H74: ='3Statement Model'!H85/'3Statement Model'!H$109 -> 0.013057491 | I74: ='3Statement Model'!I85/'3Statement Model'!I$109 -> 0.012631447 | J74: ='3Statement Model'!J85/'3Statement Model'!J$109 -> 0.012486605 | K74: ='3Statement Model'!K85/'3Statement Model'!K$109 -> 0.012221147 | ... S74: ='3Statement Model'!S85/'3Statement Model'!S$109 -> 0.011207756
B75: Goodwill | D75: ='3Statement Model'!D86/'3Statement Model'!D$109 -> 0.0058055873 | E75: ='3Statement Model'!E86/'3Statement Model'!E$109 -> 0.25302151 | F75: ='3Statement Model'!F86/'3Statement Model'!F$109 -> 0.24670647 | G75: ='3Statement Model'!G86/'3Statement Model'!G$109 -> 0.23897547 | H75: ='3Statement Model'!H86/'3Statement Model'!H$109 -> 0.22249965 | I75: ='3Statement Model'!I86/'3Statement Model'!I$109 -> 0.21865298 | J75: ='3Statement Model'!J86/'3Statement Model'!J$109 -> 0.20605816 | K75: ='3Statement Model'!K86/'3Statement Model'!K$109 -> 0.20057374 | ... S75: ='3Statement Model'!S86/'3Statement Model'!S$109 -> 0.17255997
B76: Intangible Assets | D76: ='3Statement Model'!D87/'3Statement Model'!D$109 -> 0.019947402 | E76: ='3Statement Model'!E87/'3Statement Model'!E$109 -> 0.40621319 | F76: ='3Statement Model'!F87/'3Statement Model'!F$109 -> 0.39574854 | G76: ='3Statement Model'!G87/'3Statement Model'!G$109 -> 0.38670352 | H76: ='3Statement Model'!H87/'3Statement Model'!H$109 -> 0.35983898 | I76: ='3Statement Model'!I87/'3Statement Model'!I$109 -> 0.35358037 | J76: ='3Statement Model'!J87/'3Statement Model'!J$109 -> 0.33331123 | K76: ='3Statement Model'!K87/'3Statement Model'!K$109 -> 0.32454437 | ... S76: ='3Statement Model'!S87/'3Statement Model'!S$109 -> 0.28109231
B77: Financial Assets
B78: Non-Current Investments | D78: ='3Statement Model'!D89/'3Statement Model'!D$109 -> 9.9240808e-05 | E78: ='3Statement Model'!E89/'3Statement Model'!E$109 -> 2.9087947e-05 | F78: ='3Statement Model'!F89/'3Statement Model'!F$109 -> 2.8361955e-05 | G78: ='3Statement Model'!G89/'3Statement Model'!G$109 -> 0.00097144499 | H78: ='3Statement Model'!H89/'3Statement Model'!H$109 -> 0.00085351406 | I78: ='3Statement Model'!I89/'3Statement Model'!I$109 -> 0.00073860791 | J78: ='3Statement Model'!J89/'3Statement Model'!J$109 -> 0.00070650367 | K78: ='3Statement Model'!K89/'3Statement Model'!K$109 -> 0.00069801491 | ... S78: ='3Statement Model'!S89/'3Statement Model'!S$109 -> 0.00067648633
B79: Long Term Loans And Advances | D79: ='3Statement Model'!D90/'3Statement Model'!D$109 -> 0.011809656 | E79: ='3Statement Model'!E90/'3Statement Model'!E$109 -> 0.0016143811 | F79: ='3Statement Model'!F90/'3Statement Model'!F$109 -> 0.0016308124 | G79: ='3Statement Model'!G90/'3Statement Model'!G$109 -> 0.0013408677 | H79: ='3Statement Model'!H90/'3Statement Model'!H$109 -> 0.0012993796 | I79: ='3Statement Model'!I90/'3Statement Model'!I$109 -> 0.0010891337 | J79: ='3Statement Model'!J90/'3Statement Model'!J$109 -> 0.0010417936 | K79: ='3Statement Model'!K90/'3Statement Model'!K$109 -> 0.0010292762 | ... S79: ='3Statement Model'!S90/'3Statement Model'!S$109 -> 0.00099753069
B80: Other Financial Asset | D80: ='3Statement Model'!D91/'3Statement Model'!D$109 -> 0.00014886121 | E80: ='3Statement Model'!E91/'3Statement Model'!E$109 -> 0.011009788 | F80: ='3Statement Model'!F91/'3Statement Model'!F$109 -> 0.010337933 | G80: ='3Statement Model'!G91/'3Statement Model'!G$109 -> 0.0099196848 | H80: ='3Statement Model'!H91/'3Statement Model'!H$109 -> 0.009681652 | I80: ='3Statement Model'!I91/'3Statement Model'!I$109 -> 0.0095518277 | J80: ='3Statement Model'!J91/'3Statement Model'!J$109 -> 0.0091366492 | K80: ='3Statement Model'!K91/'3Statement Model'!K$109 -> 0.0090268708 | ... S80: ='3Statement Model'!S91/'3Statement Model'!S$109 -> 0.0087484588
B81: Deferred Tax Assets [Net] | D81: ='3Statement Model'!D92/'3Statement Model'!D$109 -> 0.014092195 | E81: ='3Statement Model'!E92/'3Statement Model'!E$109 -> 0.00024724755 | F81: ='3Statement Model'!F92/'3Statement Model'!F$109 -> 0.00015599075 | G81: ='3Statement Model'!G92/'3Statement Model'!G$109 -> 0.00013682324 | H81: ='3Statement Model'!H92/'3Statement Model'!H$109 -> 0.00012739016 | I81: ='3Statement Model'!I92/'3Statement Model'!I$109 -> 0.00021281923 | J81: ='3Statement Model'!J92/'3Statement Model'!J$109 -> 0.00020056045 | K81: ='3Statement Model'!K92/'3Statement Model'!K$109 -> 0.00019522235 | ... S81: ='3Statement Model'!S92/'3Statement Model'!S$109 -> 0.000167956
B82: Non-Current Tax Assets | D82: ='3Statement Model'!D93/'3Statement Model'!D$109 -> 0.053738897 | E82: ='3Statement Model'!E93/'3Statement Model'!E$109 -> 0.018121791 | F82: ='3Statement Model'!F93/'3Statement Model'!F$109 -> 0.016421572 | G82: ='3Statement Model'!G93/'3Statement Model'!G$109 -> 0.015926225 | H82: ='3Statement Model'!H93/'3Statement Model'!H$109 -> 0.014968344 | I82: ='3Statement Model'!I93/'3Statement Model'!I$109 -> 0.015010015 | J82: ='3Statement Model'!J93/'3Statement Model'!J$109 -> 0.01414541 | K82: ='3Statement Model'!K93/'3Statement Model'!K$109 -> 0.013768917 | ... S82: ='3Statement Model'!S93/'3Statement Model'!S$109 -> 0.011845838
B83: Other Non-Current Assets | D83: ='3Statement Model'!D94/'3Statement Model'!D$109 -> 0.007244579 | E83: ='3Statement Model'!E94/'3Statement Model'!E$109 -> 0.0031851302 | F83: ='3Statement Model'!F94/'3Statement Model'!F$109 -> 0.0027511097 | G83: ='3Statement Model'!G94/'3Statement Model'!G$109 -> 0.0028869703 | H83: ='3Statement Model'!H94/'3Statement Model'!H$109 -> 0.0037197926 | I83: ='3Statement Model'!I94/'3Statement Model'!I$109 -> 0.0045067601 | J83: ='3Statement Model'!J94/'3Statement Model'!J$109 -> 0.0042641511 | K83: ='3Statement Model'!K94/'3Statement Model'!K$109 -> 0.0041672594 | ... S83: ='3Statement Model'!S94/'3Statement Model'!S$109 -> 0.0037015722
B84: Total Non-Current Assets | D84: ='3Statement Model'!D95/'3Statement Model'!D$109 -> 0.388627 | E84: ='3Statement Model'!E95/'3Statement Model'!E$109 -> 0.79322833 | F84: ='3Statement Model'!F95/'3Statement Model'!F$109 -> 0.77988287 | G84: ='3Statement Model'!G95/'3Statement Model'!G$109 -> 0.76742786 | H84: ='3Statement Model'!H95/'3Statement Model'!H$109 -> 0.72835323 | I84: ='3Statement Model'!I95/'3Statement Model'!I$109 -> 0.72394842 | J84: ='3Statement Model'!J95/'3Statement Model'!J$109 -> 0.69606871 | K84: ='3Statement Model'!K95/'3Statement Model'!K$109 -> 0.68810362 | ... S84: ='3Statement Model'!S95/'3Statement Model'!S$109 -> 0.68297671
B86: CURRENT ASSETS
B87: Inventories | D87: ='3Statement Model'!D98/'3Statement Model'!D$109 -> 0.13729966 | E87: ='3Statement Model'!E98/'3Statement Model'!E$109 -> 0.052052882 | F87: ='3Statement Model'!F98/'3Statement Model'!F$109 -> 0.058085284 | G87: ='3Statement Model'!G98/'3Statement Model'!G$109 -> 0.058163558 | H87: ='3Statement Model'!H98/'3Statement Model'!H$109 -> 0.051236321 | I87: ='3Statement Model'!I98/'3Statement Model'!I$109 -> 0.055270406 | J87: ='3Statement Model'!J98/'3Statement Model'!J$109 -> 0.065199149 | K87: ='3Statement Model'!K98/'3Statement Model'!K$109 -> 0.068721587 | ... S87: ='3Statement Model'!S98/'3Statement Model'!S$109 -> 0.11295901
B88: Financial Assets
B89: Current Investments | D89: ='3Statement Model'!D100/'3Statement Model'!D$109 -> 0.062174366 | E89: ='3Statement Model'!E100/'3Statement Model'!E$109 -> 0.039370537 | F89: ='3Statement Model'!F100/'3Statement Model'!F$109 -> 0.04990286 | G89: ='3Statement Model'!G100/'3Statement Model'!G$109 -> 0.038461012 | H89: ='3Statement Model'!H100/'3Statement Model'!H$109 -> 0.058064434 | I89: ='3Statement Model'!I100/'3Statement Model'!I$109 -> 0.046957937 | J89: ='3Statement Model'!J100/'3Statement Model'!J$109 -> 0.044253073 | K89: ='3Statement Model'!K100/'3Statement Model'!K$109 -> 0.043075236 | ... S89: ='3Statement Model'!S100/'3Statement Model'!S$109 -> 0.037058996
B90: Trade Receivables | D90: ='3Statement Model'!D101/'3Statement Model'!D$109 -> 0.057013844 | E90: ='3Statement Model'!E101/'3Statement Model'!E$109 -> 0.025568306 | F90: ='3Statement Model'!F101/'3Statement Model'!F$109 -> 0.031708666 | G90: ='3Statement Model'!G101/'3Statement Model'!G$109 -> 0.042127875 | H90: ='3Statement Model'!H101/'3Statement Model'!H$109 -> 0.03817883 | I90: ='3Statement Model'!I101/'3Statement Model'!I$109 -> 0.047809214 | J90: ='3Statement Model'!J101/'3Statement Model'!J$109 -> 0.039917846 | K90: ='3Statement Model'!K101/'3Statement Model'!K$109 -> 0.037572028 | ... S90: ='3Statement Model'!S101/'3Statement Model'!S$109 -> 0.06262454
B91: Cash And Cash Equivalents | D91: ='3Statement Model'!D102/'3Statement Model'!D$109 -> 0.15957922 | E91: ='3Statement Model'!E102/'3Statement Model'!E$109 -> 0.02679 | F91: ='3Statement Model'!F102/'3Statement Model'!F$109 -> 0.016265581 | G91: ='3Statement Model'!G102/'3Statement Model'!G$109 -> 0.0097691792 | H91: ='3Statement Model'!H102/'3Statement Model'!H$109 -> 0.010344081 | I91: ='3Statement Model'!I102/'3Statement Model'!I$109 -> 0.075988983 | J91: ='3Statement Model'!J102/'3Statement Model'!J$109 -> 0.12048377 | K91: ='3Statement Model'!K102/'3Statement Model'!K$109 -> 0.12802527 | ... S91: ='3Statement Model'!S102/'3Statement Model'!S$109 -> 0.061235127
B92: Bank Balances | D92: ='3Statement Model'!D103/'3Statement Model'!D$109 -> 0.094129906 | E92: ='3Statement Model'!E103/'3Statement Model'!E$109 -> 0.038236107 | F92: ='3Statement Model'!F103/'3Statement Model'!F$109 -> 0.038274459 | G92: ='3Statement Model'!G103/'3Statement Model'!G$109 -> 0.054236732 | H92: ='3Statement Model'!H103/'3Statement Model'!H$109 -> 0.085950139 | I92: ='3Statement Model'!I103/'3Statement Model'!I$109 -> 0.018577867 | J92: ='3Statement Model'!J103/'3Statement Model'!J$109 -> 0.017507747 | K92: ='3Statement Model'!K103/'3Statement Model'!K$109 -> 0.017041762 | ... S92: ='3Statement Model'!S103/'3Statement Model'!S$109 -> 0.01466157
B93: Loans | D93: ='3Statement Model'!D104/'3Statement Model'!D$109 -> 0 | E93: ='3Statement Model'!E104/'3Statement Model'!E$109 -> 0 | F93: ='3Statement Model'!F104/'3Statement Model'!F$109 -> 0.00049633422 | G93: ='3Statement Model'!G104/'3Statement Model'!G$109 -> 0.00049256366 | H93: ='3Statement Model'!H104/'3Statement Model'!H$109 -> 0.0004840826 | I93: ='3Statement Model'!I104/'3Statement Model'!I$109 -> 0.0005758638 | J93: ='3Statement Model'!J104/'3Statement Model'!J$109 -> 0.00054269298 | K93: ='3Statement Model'!K104/'3Statement Model'!K$109 -> 0.0005282487 | ... S93: ='3Statement Model'!S104/'3Statement Model'!S$109 -> 0.00045446916
B94: Other Financial Assets | D94: ='3Statement Model'!D105/'3Statement Model'!D$109 -> 0.070460974 | E94: ='3Statement Model'!E105/'3Statement Model'!E$109 -> 0.017278241 | F94: ='3Statement Model'!F105/'3Statement Model'!F$109 -> 0.015443085 | G94: ='3Statement Model'!G105/'3Statement Model'!G$109 -> 0.018963701 | H94: ='3Statement Model'!H105/'3Statement Model'!H$109 -> 0.018153097 | I94: ='3Statement Model'!I105/'3Statement Model'!I$109 -> 0.018627942 | J94: ='3Statement Model'!J105/'3Statement Model'!J$109 -> 0.0079325631 | K94: ='3Statement Model'!K105/'3Statement Model'!K$109 -> 0.0083611265 | ... S94: ='3Statement Model'!S105/'3Statement Model'!S$109 -> 0.013743347
B95: OtherCurrentAssets | D95: ='3Statement Model'!D106/'3Statement Model'!D$109 -> 0.03071503 | E95: ='3Statement Model'!E106/'3Statement Model'!E$109 -> 0.0074756025 | F95: ='3Statement Model'!F106/'3Statement Model'!F$109 -> 0.0099408653 | G95: ='3Statement Model'!G106/'3Statement Model'!G$109 -> 0.010357519 | H95: ='3Statement Model'!H106/'3Statement Model'!H$109 -> 0.0092357864 | I95: ='3Statement Model'!I106/'3Statement Model'!I$109 -> 0.012243365 | J95: ='3Statement Model'!J106/'3Statement Model'!J$109 -> 0.0080944522 | K95: ='3Statement Model'!K106/'3Statement Model'!K$109 -> 0.0085711189 | ... S95: ='3Statement Model'!S106/'3Statement Model'!S$109 -> 0.014286223
B96: Total Current Assets | D96: ='3Statement Model'!D107/'3Statement Model'!D$109 -> 0.611373 | E96: ='3Statement Model'!E107/'3Statement Model'!E$109 -> 0.20677167 | F96: ='3Statement Model'!F107/'3Statement Model'!F$109 -> 0.22011713 | G96: ='3Statement Model'!G107/'3Statement Model'!G$109 -> 0.23257214 | H96: ='3Statement Model'!H107/'3Statement Model'!H$109 -> 0.27164677 | I96: ='3Statement Model'!I107/'3Statement Model'!I$109 -> 0.27605158 | J96: ='3Statement Model'!J107/'3Statement Model'!J$109 -> 0.30393129 | K96: ='3Statement Model'!K107/'3Statement Model'!K$109 -> 0.31189638 | ... S96: ='3Statement Model'!S107/'3Statement Model'!S$109 -> 0.31702329
B98: Total Assets | D98: ='3Statement Model'!D109/'3Statement Model'!D$109 -> 1 | E98: ='3Statement Model'!E109/'3Statement Model'!E$109 -> 1 | F98: ='3Statement Model'!F109/'3Statement Model'!F$109 -> 1 | G98: ='3Statement Model'!G109/'3Statement Model'!G$109 -> 1 | H98: ='3Statement Model'!H109/'3Statement Model'!H$109 -> 1 | I98: ='3Statement Model'!I109/'3Statement Model'!I$109 -> 1 | J98: ='3Statement Model'!J109/'3Statement Model'!J$109 -> 1 | K98: ='3Statement Model'!K109/'3Statement Model'!K$109 -> 1 | ... S98: ='3Statement Model'!S109/'3Statement Model'!S$109 -> 1

Sheet Ratio Analysis
B2: ='Input Sheet'!$C$6 -> Hindustan Unilever Ltd.
B3: Ratio Analysis
H4: Current Case:
D8: Actual | J8: Explicit Forecast Period | O8: Maturity Period
B9: In Crs Unless Stated Otherwise | D9: 2020 | E9: =D9+1 -> 2021 | F9: =E9+1 -> 2022 | G9: =F9+1 -> 2023 | H9: =G9+1 -> 2024 | I9: =H9+1 -> 2025 | J9: =I9+1 -> 2026 | K9: =J9+1 -> 2027 | L9: =K9+1 -> 2028 | ... S9: =R9+1 -> 2035
A11: # | B11: Liquidity Ratios
B13: Current Assets | D13: ='3Statement Model'!D107 -> 12321 | E13: ='3Statement Model'!E107 -> 14217 | F13: ='3Statement Model'!F107 -> 15522 | G13: ='3Statement Model'!G107 -> 16998 | H13: ='3Statement Model'!H107 -> 21324 | I13: ='3Statement Model'!I107 -> 22051 | J13: ='3Statement Model'!J107 -> 25761.969 | K13: ='3Statement Model'!K107 -> 27159.998 | ... S13: ='3Statement Model'!S107 -> 32088.142
B14: Current Liabilities | D14: ='3Statement Model'!D77 -> 9317 | E14: ='3Statement Model'!E77 -> 11103 | F14: ='3Statement Model'!F77 -> 11280 | G14: ='3Statement Model'!G77 -> 12028 | H14: ='3Statement Model'!H77 -> 12879 | I14: ='3Statement Model'!I77 -> 16537 | J14: ='3Statement Model'!J77 -> 20240.282 | K14: ='3Statement Model'!K77 -> 21521.479 | ... S14: ='3Statement Model'!S77 -> 36751.998
B15: Current Ratio | D15: =D13/D14 -> 1.3224214 | E15: =E13/E14 -> 1.2804647 | F15: =F13/F14 -> 1.3760638 | G15: =G13/G14 -> 1.4132025 | H15: =H13/H14 -> 1.6557186 | I15: =I13/I14 -> 1.3334341 | J15: =J13/J14 -> 1.2728068 | K15: =K13/K14 -> 1.2619949 | ... S15: =S13/S14 -> 0.87309925
B17: Current Assets | D17: =D13 -> 12321 | E17: =E13 -> 14217 | F17: =F13 -> 15522 | G17: =G13 -> 16998 | H17: =H13 -> 21324 | I17: =I13 -> 22051 | J17: =J13 -> 25761.969 | K17: =K13 -> 27159.998 | ... S17: =S13 -> 32088.142
B18: Inventory | D18: ='3Statement Model'!D98 -> 2767 | E18: ='3Statement Model'!E98 -> 3579 | F18: ='3Statement Model'!F98 -> 4096 | G18: ='3Statement Model'!G98 -> 4251 | H18: ='3Statement Model'!H98 -> 4022 | I18: ='3Statement Model'!I98 -> 4415 | J18: ='3Statement Model'!J98 -> 5526.4412 | K18: ='3Statement Model'!K98 -> 5984.2892 | ... S18: ='3Statement Model'!S98 -> 11433.371
B19: Other Current Assets | D19: ='3Statement Model'!D106 -> 619 | E19: ='3Statement Model'!E106 -> 514 | F19: ='3Statement Model'!F106 -> 701 | G19: ='3Statement Model'!G106 -> 757 | H19: ='3Statement Model'!H106 -> 725 | I19: ='3Statement Model'!I106 -> 978 | J19: ='3Statement Model'!J106 -> 686.1058 | K19: ='3Statement Model'!K106 -> 746.3747 | ... S19: ='3Statement Model'!S106 -> 1446.0085
B20: Current Liabilities | D20: =D14 -> 9317 | E20: =E14 -> 11103 | F20: =F14 -> 11280 | G20: =G14 -> 12028 | H20: =H14 -> 12879 | I20: =I14 -> 16537 | J20: =J14 -> 20240.282 | K20: =K14 -> 21521.479 | ... S20: =S14 -> 36751.998
B21: Current Ratio | D21: =(D17-D18-D19)/D20 -> 0.95899968 | E21: =(E17-E18-E19)/E20 -> 0.91182563 | F21: =(F17-F18-F19)/F20 -> 0.95079787 | G21: =G17/G20 -> 1.4132025 | H21: =H17/H20 -> 1.6557186 | I21: =I17/I20 -> 1.3334341 | J21: =J17/J20 -> 1.2728068 | K21: =K17/K20 -> 1.2619949 | L21: =L17/L20 -> 1.2424226 | M21: =M17/M20 -> 1.2140399 | N21: =N17/N20 -> 1.1768322 | ... S21: =S17/S20 -> 0.87309925
B23: Inventory Days | D23: ='3Statement Model'!D115 -> 55.312722 | E23: ='3Statement Model'!E115 -> 58.982075 | F23: ='3Statement Model'!F115 -> 58.093647 | G23: ='3Statement Model'!G115 -> 48.922153 | H23: ='3Statement Model'!H115 -> 49.328965 | I23: ='3Statement Model'!I115 -> 52.700471 | J23: ='3Statement Model'!J115 -> 60 | K23: ='3Statement Model'!K115 -> 60 | ... S23: ='3Statement Model'!S115 -> 60
B24: Debtors Days | D24: ='3Statement Model'!D114 -> 10.541814 | E24: ='3Statement Model'!E114 -> 13.644425 | F24: ='3Statement Model'!F114 -> 15.56153 | G24: ='3Statement Model'!G114 -> 18.548193 | H24: ='3Statement Model'!H114 -> 17.690423 | I24: ='3Statement Model'!I114 -> 22.083538 | J24: ='3Statement Model'!J114 -> 18 | K24: ='3Statement Model'!K114 -> 16 | ... S24: ='3Statement Model'!S114 -> 16
B25: Creditor Days | D25: ='3Statement Model'!D116 -> 150.62572 | E25: ='3Statement Model'!E116 -> 145.05734 | F25: ='3Statement Model'!F116 -> 128.61162 | G25: ='3Statement Model'!G116 -> 110.1813 | H25: ='3Statement Model'!H116 -> 128.60853 | I25: ='3Statement Model'!I116 -> 135.06361 | J25: ='3Statement Model'!J116 -> 160 | K25: ='3Statement Model'!K116 -> 160 | ... S25: ='3Statement Model'!S116 -> 160
B26: Cash Conversion Cycle | D26: =D23+D24-D25 -> -84.771182 | E26: =E23+E24-E25 -> -72.430842 | F26: =F23+F24-F25 -> -54.956442 | G26: =G23+G24-G25 -> -42.710951 | H26: =H23+H24-H25 -> -61.589147 | I26: =I23+I24-I25 -> -60.279599 | J26: =J23+J24-J25 -> -82 | K26: =K23+K24-K25 -> -84 | ... S26: =S23+S24-S25 -> -84
A28: # | B28: Leverage/ Solvency Ratios
B30: Total Debt | D30: ='3Statement Model'!D61+'3Statement Model'!D70+'3Statement Model'!D71 -> 0 | E30: ='3Statement Model'!E61+'3Statement Model'!E70+'3Statement Model'!E71 -> 0 | F30: ='3Statement Model'!F61+'3Statement Model'!F70+'3Statement Model'!F71 -> 1043 | G30: ='3Statement Model'!G61+'3Statement Model'!G70+'3Statement Model'!G71 -> 1219 | H30: ='3Statement Model'!H61+'3Statement Model'!H70+'3Statement Model'!H71 -> 1484 | I30: ='3Statement Model'!I61+'3Statement Model'!I70+'3Statement Model'!I71 -> 1648 | J30: ='3Statement Model'!J61+'3Statement Model'!J70+'3Statement Model'!J71 -> 2058.3174 | K30: ='3Statement Model'!K61+'3Statement Model'!K70+'3Statement Model'!K71 -> 2239.1241 | ... S30: ='3Statement Model'!S61+'3Statement Model'!S70+'3Statement Model'!S71 -> 4338.0255
B31: Total Equity | D31: ='3Statement Model'!D57 -> 8246 | E31: ='3Statement Model'!E57 -> 47694 | F31: ='3Statement Model'!F57 -> 49087 | G31: ='3Statement Model'!G57 -> 50522 | H31: ='3Statement Model'!H57 -> 51423 | I31: ='3Statement Model'!I57 -> 49609 | J31: ='3Statement Model'!J57 -> 50658.981 | K31: ='3Statement Model'!K57 -> 51574.966 | ... S31: ='3Statement Model'!S57 -> 49081.973
B32: Debt/Equity Ratio | D32: =D30/D31 -> 0 | E32: =E30/E31 -> 0 | F32: =F30/F31 -> 0.021247988 | G32: =G30/G31 -> 0.024128103 | H32: =H30/H31 -> 0.028858682 | I32: =I30/I31 -> 0.033219779 | J32: =J30/J31 -> 0.040630849 | K32: =K30/K31 -> 0.043414941 | ... S32: =S30/S31 -> 0.088383274
B34: Total Debt | D34: =D30 -> 0 | E34: =E30 -> 0 | F34: =F30 -> 1043 | G34: =G30 -> 1219 | H34: =H30 -> 1484 | I34: =I30 -> 1648 | J34: =J30 -> 2058.3174 | K34: =K30 -> 2239.1241 | ... S34: =S30 -> 4338.0255
B35: Total Assets | D35: ='3Statement Model'!D109 -> 20153 | E35: ='3Statement Model'!E109 -> 68757 | F35: ='3Statement Model'!F109 -> 70517 | G35: ='3Statement Model'!G109 -> 73087 | H35: ='3Statement Model'!H109 -> 78499 | I35: ='3Statement Model'!I109 -> 79880 | J35: ='3Statement Model'!J109 -> 84762.475 | K35: ='3Statement Model'!K109 -> 87080.195 | ... S35: ='3Statement Model'!S109 -> 101216.99
B36: Debt/Total Assets Ratio | D36: =D34/D35 -> 0 | E36: =E34/E35 -> 0 | F36: =F34/F35 -> 0.01479076 | G36: =G34/G35 -> 0.016678753 | H36: =H34/H35 -> 0.018904699 | I36: =I34/I35 -> 0.020630946 | J36: =J34/J35 -> 0.024283356 | K36: =K34/K35 -> 0.025713357 | ... S36: =S34/S35 -> 0.04285867
B38: Total Equity | D38: =D31 -> 8246 | E38: =E31 -> 47694 | F38: =F31 -> 49087 | G38: =G31 -> 50522 | H38: =H31 -> 51423 | I38: =I31 -> 49609 | J38: =J31 -> 50658.981 | K38: =K31 -> 51574.966 | ... S38: =S31 -> 49081.973
B39: Total Assets | D39: =D35 -> 20153 | E39: =E35 -> 68757 | F39: =F35 -> 70517 | G39: =G35 -> 73087 | H39: =H35 -> 78499 | I39: =I35 -> 79880 | J39: =J35 -> 84762.475 | K39: =K35 -> 87080.195 | ... S39: =S35 -> 101216.99
B40: Equity Multiplier Ratio / Financial Leverage | D40: =D39/D38 -> 2.4439728 | E40: =E38/E39 -> 0.69366028 | F40: =F38/F39 -> 0.69610165 | G40: =G38/G39 -> 0.69125836 | H40: =H38/H39 -> 0.65507841 | I40: =I38/I39 -> 0.62104407 | J40: =J38/J39 -> 0.59765812 | K40: =K38/K39 -> 0.59226976 | L40: =L38/L39 -> 0.5855251 | ... S40: =S38/S39 -> 0.48491833
A42: # | B42: Profitability/ Margin Ratios
B44: Gross Profit | D44: ='3Statement Model'!D15 -> 21524 | E44: ='3Statement Model'!E15 -> 24880 | F44: ='3Statement Model'!F15 -> 26711 | G44: ='3Statement Model'!G15 -> 28874 | H44: ='3Statement Model'!H15 -> 32076 | I44: ='3Statement Model'!I15 -> 32543 | J44: ='3Statement Model'!J15 -> 34991.396 | K44: ='3Statement Model'!K15 -> 38233.044 | ... S44: ='3Statement Model'!S15 -> 75047.84
B45: Sales | D45: ='3Statement Model'!D13 -> 39783 | E45: ='3Statement Model'!E13 -> 47028 | F45: ='3Statement Model'!F13 -> 52446 | G45: ='3Statement Model'!G13 -> 60590 | H45: ='3Statement Model'!H13 -> 61836 | I45: ='3Statement Model'!I13 -> 63121 | J45: ='3Statement Model'!J13 -> 68610.58 | K45: ='3Statement Model'!K13 -> 74637.47 | ... S45: ='3Statement Model'!S13 -> 144600.85
B46: Gross Margin Ratio | D46: =D44/D45 -> 0.54103512 | E46: =E44/E45 -> 0.52904653 | F46: =F44/F45 -> 0.50930481 | G46: =G44/G45 -> 0.47654729 | H46: =H44/H45 -> 0.51872696 | I46: =I44/I45 -> 0.51556534 | J46: =J44/J45 -> 0.51 | K46: =K44/K45 -> 0.51225 | ... S46: =S44/S45 -> 0.519
B48: EBITDA | D48: ='3Statement Model'!D22 -> 9861 | E48: ='3Statement Model'!E22 -> 11626 | F48: ='3Statement Model'!F22 -> 12857 | G48: ='3Statement Model'!G22 -> 14159 | H48: ='3Statement Model'!H22 -> 14603 | I48: ='3Statement Model'!I22 -> 14851 | J48: ='3Statement Model'!J22 -> 15780.433 | K48: ='3Statement Model'!K22 -> 17334.553 | ... S48: ='3Statement Model'!S22 -> 34559.603
B49: Sales | D49: =D45 -> 39783 | E49: =E45 -> 47028 | F49: =F45 -> 52446 | G49: =G45 -> 60590 | H49: =H45 -> 61836 | I49: =I45 -> 63121 | J49: =J45 -> 68610.58 | K49: =K45 -> 74637.47 | ... S49: =S45 -> 144600.85
B50: EBITDA Margin Ratio | D50: =D48/D49 -> 0.24786969 | E50: =E48/E49 -> 0.24721443 | F50: =F48/F49 -> 0.24514739 | G50: =G48/G49 -> 0.23368543 | H50: =H48/H49 -> 0.23615693 | I50: =I48/I49 -> 0.23527828 | J50: =J48/J49 -> 0.23 | K50: =K48/K49 -> 0.23225 | ... S50: =S48/S49 -> 0.239
B52: EBIT | D52: ='3Statement Model'!D28 -> 8859 | E52: ='3Statement Model'!E28 -> 10552 | F52: ='3Statement Model'!F28 -> 11766 | G52: ='3Statement Model'!G28 -> 13022 | H52: ='3Statement Model'!H28 -> 13387 | I52: ='3Statement Model'!I28 -> 13496 | J52: ='3Statement Model'!J28 -> 14249.574 | K52: ='3Statement Model'!K28 -> 15630.161 | ... S52: ='3Statement Model'!S28 -> 30783.203
B53: Sales | D53: =D49 -> 39783 | E53: =E49 -> 47028 | F53: =F49 -> 52446 | G53: =G49 -> 60590 | H53: =H49 -> 61836 | I53: =I49 -> 63121 | J53: =J49 -> 68610.58 | K53: =K49 -> 74637.47 | ... S53: =S49 -> 144600.85
B54: EBIT Margin Ratio | D54: =D52/D53 -> 0.22268306 | E54: =E52/E53 -> 0.22437697 | F54: =F52/F53 -> 0.22434504 | G54: =G52/G53 -> 0.21491995 | H54: =H52/H53 -> 0.21649201 | I54: =I52/I53 -> 0.21381157 | J54: =J52/J53 -> 0.2076877 | K54: =K52/K53 -> 0.2094144 | ... S54: =S52/S53 -> 0.21288397
B56: Net Income | D56: ='3Statement Model'!D40 -> 6764 | E56: ='3Statement Model'!E40 -> 8000 | F56: ='3Statement Model'!F40 -> 8887 | G56: ='3Statement Model'!G40 -> 10154 | H56: ='3Statement Model'!H40 -> 10222 | I56: ='3Statement Model'!I40 -> 10671 | J56: ='3Statement Model'!J40 -> 10499.812 | K56: ='3Statement Model'!K40 -> 11449.815 | ... S56: ='3Statement Model'!S40 -> 21866.472
B57: Sales | D57: =D53 -> 39783 | E57: =E53 -> 47028 | F57: =F53 -> 52446 | G57: =G53 -> 60590 | H57: =H53 -> 61836 | I57: =I53 -> 63121 | J57: =J53 -> 68610.58 | K57: =K53 -> 74637.47 | ... S57: =S53 -> 144600.85
B58: Net Profit Margin Ratio | D58: =D56/D57 -> 0.17002237 | E58: =E56/E57 -> 0.17011142 | F58: =F56/F57 -> 0.16945048 | G58: =G56/G57 -> 0.16758541 | H58: =H56/H57 -> 0.16530823 | I58: =I56/I57 -> 0.16905626 | J58: =J56/J57 -> 0.15303488 | K58: =K56/K57 -> 0.15340573 | ... S58: =S56/S57 -> 0.15121953
B60: EBIT | D60: =D52 -> 8859 | E60: =E52 -> 10552 | F60: =F52 -> 11766 | G60: =G52 -> 13022 | H60: =H52 -> 13387 | I60: =I52 -> 13496 | J60: =J52 -> 14249.574 | K60: =K52 -> 15630.161 | ... S60: =S52 -> 30783.203
B61: Total Assets | D61: =D39 -> 20153 | E61: =E39 -> 68757 | F61: =F39 -> 70517 | G61: =G39 -> 73087 | H61: =H39 -> 78499 | I61: =I39 -> 79880 | J61: =J39 -> 84762.475 | K61: =K39 -> 87080.195 | ... S61: =S39 -> 101216.99
B62: Return on Assets Ratio | D62: =D60/D61 -> 0.43958716 | E62: =E60/E61 -> 0.15346801 | F62: =F60/F61 -> 0.16685338 | G62: =G60/G61 -> 0.17817122 | H62: =H60/H61 -> 0.1705372 | I62: =I60/I61 -> 0.16895343 | J62: =J60/J61 -> 0.16811182 | K62: =K60/K61 -> 0.17949157 | ... S62: =S60/S61 -> 0.3041308
B64: Net Income | D64: =D56 -> 6764 | E64: =E56 -> 8000 | F64: =F56 -> 8887 | G64: =G56 -> 10154 | H64: =H56 -> 10222 | I64: =I56 -> 10671 | J64: =J56 -> 10499.812 | K64: =K56 -> 11449.815 | ... S64: =S56 -> 21866.472
B65: Total Equity | D65: =D38 -> 8246 | E65: =E38 -> 47694 | F65: =F38 -> 49087 | G65: =G38 -> 50522 | H65: =H38 -> 51423 | I65: =I38 -> 49609 | J65: =J38 -> 50658.981 | K65: =K38 -> 51574.966 | ... S65: =S38 -> 49081.973
B66: Return on Equity Ratio | D66: =D64/D65 -> 0.8202765 | E66: =E64/E65 -> 0.16773598 | F66: =F64/F65 -> 0.1810459 | G66: =G64/G65 -> 0.20098175 | H66: =H64/H65 -> 0.19878265 | I66: =I64/I65 -> 0.2151021 | J66: =J64/J65 -> 0.20726457 | K66: =K64/K65 -> 0.22200335 | ... S66: =S64/S65 -> 0.44550924
A68: # | B68: Efficiency Ratios
B70: Sales | D70: =D57 -> 39783 | E70: =E57 -> 47028 | F70: =F57 -> 52446 | G70: =G57 -> 60590 | H70: =H57 -> 61836 | I70: =I57 -> 63121 | J70: =J57 -> 68610.58 | K70: =K57 -> 74637.47 | ... S70: =S57 -> 144600.85
B71: Total Assets | D71: =D61 -> 20153 | E71: =E61 -> 68757 | F71: =F61 -> 70517 | G71: =G61 -> 73087 | H71: =H61 -> 78499 | I71: =I61 -> 79880 | J71: =J61 -> 84762.475 | K71: =K61 -> 87080.195 | ... S71: =S61 -> 101216.99
B72: Assets Turnover Ratio | D72: =D70/D71 -> 1.9740485 | E72: =E70/E71 -> 0.683974 | F72: =F70/F71 -> 0.74373555 | G72: =G70/G71 -> 0.829012 | H72: =H70/H71 -> 0.78772978 | I72: =I70/I71 -> 0.7901978 | J72: =J70/J71 -> 0.80944522 | K72: =K70/K71 -> 0.85711189 | ... S72: =S70/S71 -> 1.4286223
B74: COGS | D74: =-'3Statement Model'!D14 -> 18259 | E74: =-'3Statement Model'!E14 -> 22148 | F74: =-'3Statement Model'!F14 -> 25735 | G74: =-'3Statement Model'!G14 -> 31716 | H74: =-'3Statement Model'!H14 -> 29760 | I74: =-'3Statement Model'!I14 -> 30578 | J74: =-'3Statement Model'!J14 -> 33619.184 | K74: =-'3Statement Model'!K14 -> 36404.426 | ... S74: =-'3Statement Model'!S14 -> 69553.008
B75: Inventory | D75: =D18 -> 2767 | E75: =E18 -> 3579 | F75: =F18 -> 4096 | G75: =G18 -> 4251 | H75: =H18 -> 4022 | I75: =I18 -> 4415 | J75: =J18 -> 5526.4412 | K75: =K18 -> 5984.2892 | ... S75: =S18 -> 11433.371
B76: Inventory Turnover Ratio | D76: =D74/D75 -> 6.5988435 | E76: =E74/E75 -> 6.1883208 | F76: =F74/F75 -> 6.282959 | G76: =G74/G75 -> 7.4608327 | H76: =H74/H75 -> 7.3993038 | I76: =I74/I75 -> 6.9259343 | J76: =J74/J75 -> 6.0833333 | K76: =K74/K75 -> 6.0833333 | ... S76: =S74/S75 -> 6.0833333
B78: Capex | D78: =-'3Statement Model'!D138 -> 798 | E78: =-'3Statement Model'!E138 -> 644 | F78: =-'3Statement Model'!F138 -> 1079 | G78: =-'3Statement Model'!G138 -> 1053 | H78: =-'3Statement Model'!H138 -> 1448 | I78: =-'3Statement Model'!I138 -> 1241 | J78: =-'3Statement Model'!J138 -> 1411.5824 | K78: =-'3Statement Model'!K138 -> 1535.5786 | ... S78: =-'3Statement Model'!S138 -> 2974.9933
B79: Intangible Assets Spends | D79: =-'3Statement Model'!D139 -> 12 | E79: =-'3Statement Model'!E139 -> 3422 | F79: =-'3Statement Model'!F139 -> 3 | G79: =-'3Statement Model'!G139 -> 18 | H79: =-'3Statement Model'!H139 -> 9 | I79: =-'3Statement Model'!I139 -> 21 | J79: =-'3Statement Model'!J139 -> 53.41863 | K79: =-'3Statement Model'!K139 -> 58.111029 | ... S79: =-'3Statement Model'!S139 -> 148.23089
B80: Net Working Capital | D80: ='3Statement Model'!D132 -> 411 | E80: ='3Statement Model'!E132 -> -101 | F80: ='3Statement Model'!F132 -> -1000 | G80: ='3Statement Model'!G132 -> -958 | H80: ='3Statement Model'!H132 -> 1313 | I80: ='3Statement Model'!I132 -> -788 | J80: ='3Statement Model'!J132 -> 3853.7105 | K80: ='3Statement Model'!K132 -> 758.86218 | ... S80: ='3Statement Model'!S132 -> 687.52093
B81: NOPAT | D81: =DCFVal!E17 -> 6450 | E81: =DCFVal!F17 -> 7946 | F81: =DCFVal!G17 -> 8779 | G81: =DCFVal!H17 -> 9821 | H81: =DCFVal!I17 -> 9743 | I81: =DCFVal!J17 -> 9752 | J81: =DCFVal!K17 -> 9749.6542 | K81: =DCFVal!L17 -> 10723.098 | ... S81: =DCFVal!T17 -> 21411.858
B82: Reinvestment Rate | D82: =(D78+D79+D80)/D81 -> 0.18930233 | E82: =(E78+E79+E80)/E81 -> 0.4989932 | F82: =(F78+F79+F80)/F81 -> 0.0093404716 | G82: =(G78+G79+G80)/G81 -> 0.011505957 | H82: =(H78+H79+H80)/H81 -> 0.28430668 | I82: =(I78+I79+I80)/I81 -> 0.048605414 | J82: =(J78+J79+J80)/J81 -> 0.54552822 | K82: =(K78+K79+K80)/K81 -> 0.21939107 | ... S82: =(S78+S79+S80)/S81 -> 0.17797358
A84: # | B84: Coverage Ratios
B86: Total Debt | D86: =D34 -> 0 | E86: =E34 -> 0 | F86: =F34 -> 1043 | G86: =G34 -> 1219 | H86: =H34 -> 1484 | I86: =I34 -> 1648 | J86: =J34 -> 2058.3174 | K86: =K34 -> 2239.1241 | ... S86: =S34 -> 4338.0255
B87: EBITDA | D87: =D48 -> 9861 | E87: =E48 -> 11626 | F87: =F48 -> 12857 | G87: =G48 -> 14159 | H87: =H48 -> 14603 | I87: =I48 -> 14851 | J87: =J48 -> 15780.433 | K87: =K48 -> 17334.553 | ... S87: =S48 -> 34559.603
B88: Debt to EBITDA Coverage Ratio | D88: =D86/D87 -> 0 | E88: =E86/E87 -> 0 | F88: =F86/F87 -> 0.081123124 | G88: =G86/G87 -> 0.086093651 | H88: =H86/H87 -> 0.10162295 | I88: =I86/I87 -> 0.11096896 | J88: =J86/J87 -> 0.13043478 | K88: =K86/K87 -> 0.12917115 | ... S88: =S86/S87 -> 0.12552301
B90: EBIT | D90: =D60 -> 8859 | E90: =E60 -> 10552 | F90: =F60 -> 11766 | G90: =G60 -> 13022 | H90: =H60 -> 13387 | I90: =I60 -> 13496 | J90: =J60 -> 14249.574 | K90: =K60 -> 15630.161 | ... S90: =S60 -> 30783.203
B91: Interest | D91: =-'3Statement Model'!D32 -> 118 | E91: =-'3Statement Model'!E32 -> 117 | F91: =-'3Statement Model'!F32 -> 106 | G91: =-'3Statement Model'!G32 -> 114 | H91: =-'3Statement Model'!H32 -> 334 | I91: =-'3Statement Model'!I32 -> 395 | J91: =-'3Statement Model'!J32 -> 266.84209 | K91: =-'3Statement Model'!K32 -> 290.28203 | ... S91: =-'3Statement Model'!S32 -> 562.38546
B92: Debt Repayment | D92: =-'3Statement Model'!D157 -> 453 | E92: =-'3Statement Model'!E157 -> 492 | F92: =-'3Statement Model'!F157 -> 510 | G92: =-'3Statement Model'!G157 -> 541 | H92: =-'3Statement Model'!H157 -> 529 | I92: =-'3Statement Model'!I157 -> 625 | J92: =-'3Statement Model'!J157 -> 761.57744 | K92: =-'3Statement Model'!K157 -> 828.47592 | ... S92: =-'3Statement Model'!S157 -> 1605.0694
B93: Debt Service Coverage Ratio | D93: =D90/(SUM(D91:D92)) -> 15.514886 | E93: =E90/(SUM(E91:E92)) -> 17.326765 | F93: =F90/(SUM(F91:F92)) -> 19.100649 | G93: =G90/(SUM(G91:G92)) -> 19.880916 | H93: =H90/(SUM(H91:H92)) -> 15.512167 | I93: =I90/(SUM(I91:I92)) -> 13.231373 | J93: =J90/(SUM(J91:J92)) -> 13.855798 | K93: =K90/(SUM(K91:K92)) -> 13.970995 | ... S93: =S90/(SUM(S91:S92)) -> 14.202466
B95: EBIT | D95: =D90 -> 8859 | E95: =E90 -> 10552 | F95: =F90 -> 11766 | G95: =G90 -> 13022 | H95: =H90 -> 13387 | I95: =I90 -> 13496 | J95: =J90 -> 14249.574 | K95: =K90 -> 15630.161 | ... S95: =S90 -> 30783.203
B96: Interest | D96: =D91 -> 118 | E96: =E91 -> 117 | F96: =F91 -> 106 | G96: =G91 -> 114 | H96: =H91 -> 334 | I96: =I91 -> 395 | J96: =J91 -> 266.84209 | K96: =K91 -> 290.28203 | ... S96: =S91 -> 562.38546
B97: Interest Coverage Ratio | D97: =D95/D96 -> 75.076271 | E97: =E95/E96 -> 90.188034 | F97: =F95/F96 -> 111 | G97: =G95/G96 -> 114.22807 | H97: =H95/H96 -> 40.080838 | I97: =I95/I96 -> 34.167089 | J97: =J95/J96 -> 53.400772 | K97: =K95/K96 -> 53.844742 | ... S97: =S95/S96 -> 54.73684

Sheet DuPont Analysis
B2: ='Input Sheet'!C6 -> Hindustan Unilever Ltd. | E2: INSERT LOGO
B3: (HINDUNILVR | BSE CODE: 500696)
B5: About the Company
B7: Hindustan Unilever is in the FMCG business comprising primarily of Home Care, Beauty & Personal Care and Foods & Refreshment segments. The Company has manufacturing facilities across the country and sells primarily in India.
B12: Summary
B27: RETURN ON EQUITY (ROE)
B28: Particulars | C28: 2020 | D28: =C28+1 -> 2021 | E28: =D28+1 -> 2022 | F28: =E28+1 -> 2023 | G28: =F28+1 -> 2024 | H28: =G28+1 -> 2025
B29: Net Profit | C29: ='3Statement Model'!D40 -> 6764 | D29: ='3Statement Model'!E40 -> 8000 | E29: ='3Statement Model'!F40 -> 8887 | F29: ='3Statement Model'!G40 -> 10154 | G29: ='3Statement Model'!H40 -> 10222 | H29: ='3Statement Model'!I40 -> 10671
B30: Average Equity | C30: =SUM('3Statement Model'!D57,'Balance Sheet'!C13)/2 -> 8065.5 | D30: =SUM('3Statement Model'!D57:E57)/2 -> 27970 | E30: =SUM('3Statement Model'!E57:F57)/2 -> 48390.5 | F30: =SUM('3Statement Model'!F57:G57)/2 -> 49804.5 | G30: =SUM('3Statement Model'!G57:H57)/2 -> 50972.5 | H30: =SUM('3Statement Model'!H57:I57)/2 -> 50516
B31: Return on Equity (ROE) | C31: =IFERROR(C29/C30,0) -> 0.83863369 | D31: =IFERROR(D29/D30,0) -> 0.28602074 | E31: =IFERROR(E29/E30,0) -> 0.18365175 | F31: =IFERROR(F29/F30,0) -> 0.20387716 | G31: =IFERROR(G29/G30,0) -> 0.20053951 | H31: =IFERROR(H29/H30,0) -> 0.21124
B33: ROE - DUPONT EQUATION
C34: =C28 -> 2020 | D34: =D28 -> 2021 | E34: =E28 -> 2022 | F34: =F28 -> 2023 | G34: =G28 -> 2024 | H34: =H28 -> 2025
B35: Net Profit | C35: =C29 -> 6764 | D35: =D29 -> 8000 | E35: =E29 -> 8887 | F35: =F29 -> 10154 | G35: =G29 -> 10222 | H35: =H29 -> 10671
B36: Revenue | C36: ='3Statement Model'!D13 -> 39783 | D36: ='3Statement Model'!E13 -> 47028 | E36: ='3Statement Model'!F13 -> 52446 | F36: ='3Statement Model'!G13 -> 60590 | G36: ='3Statement Model'!H13 -> 61836 | H36: ='3Statement Model'!I13 -> 63121
